Workbook
Name UPDATE: 'Data Sheet'!$E$1

Sheet Comps Valuation
B2: Comparable Companies Valuation
C4: Market Data | K4: Financials | O4: Valuation
B5: Company | C5: Ticker | D5: Share Price | E5: Shares Outstaning | F5: Equit Value | G5: Net Debt | H5: Enterprise Value | K5: Revenue | L5: EBITDA | M5: Net Income | O5: EV/ Revnue | P5: EV/ EBITDA | Q5: P/E
B6: =Data!C3 -> Asian Paints | C6: ASIANPAINT | D6: =Data!D3 -> 2536.1 | E6: =Data!E3 -> 95.92 | F6: =D6*E6 -> 243262.71 | G6: =Data!G3 -> 2290.29 | H6: =Data!I3 -> 244770.45 | K6: =Data!J3 -> 33874.44 | L6: =Data!K3 -> 6687.7172 | M6: =Data!M3 -> 3639.97 | O6: =$H6/K6 -> 7.2258154 | P6: =$H6/L6 -> 36.6 | Q6: =F6/M6 -> 66.830966
B7: =Data!C4 -> Berger Paints | C7: BERGEPAINT | D7: =Data!D4 -> 532.5 | E7: =Data!E4 -> 116.59 | F7: =D7*E7 -> 62084.175 | G7: =Data!G4 -> 670.27 | H7: =Data!I4 -> 62253.72 | K7: =Data!J4 -> 11654.46 | L7: =Data!K4 -> 1985.7646 | M7: =Data!M4 -> 1143.82 | O7: =$H7/K7 -> 5.341622 | P7: =$H7/L7 -> 31.35 | Q7: =F7/M7 -> 54.277924
B8: =Data!C5 -> Kansai Nerolac | C8: KANSAINER | D8: =Data!D5 -> 245.85 | E8: =Data!E5 -> 80.85 | F8: =D8*E8 -> 19876.972 | G8: =Data!G5 -> 296.39 | H8: =Data!I5 -> 19883.37 | K8: =Data!J5 -> 7851.94 | L8: =Data!K5 -> 1073.6161 | M8: =Data!M5 -> 1100.05 | O8: =$H8/K8 -> 2.5322876 | P8: =$H8/L8 -> 18.52 | Q8: =F8/M8 -> 18.069154
B9: =Data!C6 -> Akzo Nobel | C9: AKZOINDIA | D9: =Data!D6 -> 3389.75 | E9: =Data!E6 -> 4.55 | F9: =D9*E9 -> 15423.362 | G9: =Data!G6 -> 62.1 | H9: =Data!I6 -> 15199.63 | K9: =Data!J6 -> 4050 | L9: =Data!K6 -> 633.58191 | M9: =Data!M6 -> 405 | O9: =$H9/K9 -> 3.7529951 | P9: =$H9/L9 -> 23.99 | Q9: =F9/M9 -> 38.082377
B10: =Data!C7 -> Indigo Paints | C10: INDIGOPNTS | D10: =Data!D7 -> 1130 | E10: =Data!E7 -> 4.76 | F10: =D10*E10 -> 5378.8 | G10: =Data!G7 -> 19.7 | H10: =Data!I7 -> 5365.34 | K10: =Data!J7 -> 1278.1 | L10: =Data!K7 -> 248.51042 | M10: =Data!M7 -> 143.84 | O10: =$H10/K10 -> 4.1979031 | P10: =$H10/L10 -> 21.59 | Q10: =F10/M10 -> 37.394327
B11: =Data!C8 -> Sirca Paints | C11: SIRCA | D11: =Data!D8 -> 461.75 | E11: =Data!E8 -> 5.48 | F11: =D11*E11 -> 2530.39 | G11: =Data!G8 -> 8.33 | H11: =Data!I8 -> 2484.95 | K11: =Data!J8 -> 409.37 | L11: =Data!K8 -> 79.901929 | M11: =Data!M8 -> 53.05 | O11: =$H11/K11 -> 6.070181 | P11: =$H11/L11 -> 31.1 | Q11: =F11/M11 -> 47.698209
B12: =Data!C9 -> Shalimar Paints | C12: SHALPAINTS | D12: =Data!D9 -> 74 | E12: =Data!E9 -> 8.37 | F12: =D12*E12 -> 619.38 | G12: =Data!G9 -> 163.86 | H12: =Data!I9 -> 737.89 | K12: =Data!J9 -> 624.19 | L12: =Data!K9 -> -32.520494 | M12: =Data!M9 -> -69.79 | O12: =$H12/K12 -> 1.1821561 | P12: =$H12/L12 -> -22.69 | Q12: =F12/M12 -> -8.8749104
B13: =Data!C10 -> Kamdhenu Venture | C13: KAMOPAINTS | D13: =Data!D10 -> 9.06 | E13: =Data!E10 -> 31.44 | F13: =D13*E13 -> 284.8464 | G13: =Data!G10 -> 26.98 | H13: =Data!I10 -> 305.89 | K13: =Data!J10 -> 261.89 | L13: =Data!K10 -> 16.770285 | M13: =Data!M10 -> 5.94 | O13: =$H13/K13 -> 1.1680095 | P13: =$H13/L13 -> 18.24 | Q13: =F13/M13 -> 47.953939
B14: =Data!C11 -> Siddhika Coatins | C14: SIDDHIKA | D14: =Data!D11 -> 200.5 | E14: =Data!E11 -> 0.62 | F14: =D14*E14 -> 124.31 | G14: =Data!G11 -> 0 | H14: =Data!I11 -> 118.13 | K14: =Data!J11 -> 48.01 | L14: =Data!K11 -> 10.435512 | M14: =Data!M11 -> 8.03 | O14: =$H14/K14 -> 2.4605291 | P14: =$H14/L14 -> 11.32 | Q14: =F14/M14 -> 15.480697
B15: =Data!C12 -> Retina Paints | D15: =Data!D12 -> 73 | E15: =Data!E12 -> 1.53 | F15: =D15*E15 -> 111.69 | G15: =Data!G12 -> 8.12 | H15: =Data!I12 -> 119.78 | K15: =Data!J12 -> 11.66 | L15: =Data!K12 -> 2.0198988 | M15: =Data!M12 -> 0.74 | O15: =$H15/K15 -> 10.272727 | P15: =$H15/L15 -> 59.3 | Q15: =F15/M15 -> 150.93243
B17: High | O17: =MAX(O6:O15) -> 10.272727 | P17: =MAX(P6:P15) -> 59.3 | Q17: =MAX(Q6:Q15) -> 150.93243
B18: 75th Percentile | O18: =QUARTILE(O6:O15,) -> 1.1680095 | P18: =QUARTILE(P6:P15,) -> -22.69 | Q18: =QUARTILE(Q6:Q15,) -> -8.8749104
B19: Average | O19: =AVERAGE(O6:O15) -> 4.4204226 | P19: =AVERAGE(P6:P15) -> 22.932 | Q19: =AVERAGE(Q6:Q15) -> 46.784512
B20: Median | O20: =MEDIAN(O6:O15) -> 3.9754491 | P20: =MEDIAN(P6:P15) -> 22.79 | Q20: =MEDIAN(Q6:Q15) -> 42.890293
B21: 25th Percentile | O21: =QUARTILE(O6:O15,1) -> 2.4784687 | P21: =QUARTILE(P6:P15,1) -> 18.31 | Q21: =QUARTILE(Q6:Q15,1) -> 22.900447
B22: Low | O22: =MIN(O6:O15) -> 1.1680095 | P22: =MIN(P6:P15) -> -22.69 | Q22: =MIN(Q6:Q15) -> -8.8749104
B24: =$B$6&" Comparable Valuation" -> Asian Paints Comparable Valuation | O24: EV/ Revnue | P24: EV/ EBITDA | Q24: P/E
B26: Implied Enterprise Value | O26: =K6 -> 33874.44 | P26: =L6 -> 6687.7172 | Q26: =Q28+Q27 -> 158409.67
B27: Debt | O27: =$G$6 -> 2290.29 | P27: =$G$6 -> 2290.29 | Q27: =$G$6 -> 2290.29
B28: Implied Market Value | O28: =O26-O27 -> 31584.15 | P28: =P26-P27 -> 4397.4272 | Q28: =M6*Q20 -> 156119.38
B29: Shares Outstanding | O29: =$E$6 -> 95.92 | P29: =$E$6 -> 95.92 | Q29: =$E$6 -> 95.92
B30: Implied Market Value Per Share | O30: =O28/O29 -> 329.27596 | P30: =P28/P29 -> 45.844737 | Q30: =Q28/Q29 -> 1627.5999
O32: =IF(O30>D6,"Undervalued","Overvalued") -> Overvalued | P32: =IF(P30>E6,"Undervalued","Overvalued") -> Overvalued | Q32: =IF(Q30>F6,"Undervalued","Overvalued") -> Overvalued

Sheet Football Field
C2: Football Field Analysis
B20: Data Table -
M21: 1771
M22: 0.1105
C23: Open Low | D23: Low | E23: Open High | F23: High | M23: 0.045
B24: Comps | C24: 45.8 | D24: 45.8 | E24: 329 | F24: 329
B25: Bear Case | C25: 202 | D25: 202 | E25: 229 | F25: 229 | M25: =M21/M22-M23 -> 16027.104
B26: Base Case | C26: 246 | D26: 246 | E26: 293 | F26: 293
B27: Bull Case | C27: 229 | D27: 229 | E27: 267 | F27: 267
B28: 52W H/L | C28: 198 | D28: 198 | E28: 300 | F28: 300

Sheet DCF
B2: ="Discounted Cash-Flow - "&'Profit & Loss'!$A$1 -> Discounted Cash-Flow - ASIAN PAINTS LTD
B5: Calculating PV of FCFF | G5: =FS!J5 -> 44651 | H5: =FS!K5 -> 45016 | I5: =FS!L5 -> 45382 | J5: =FS!M5 -> 45747 | K5: =J5+365 -> 46112 | L5: =K5+365 -> 46477 | M5: =L5+366 -> 46843 | N5: =M5+365 -> 47208 | O5: =N5+365 -> 47573
B7: EBIT | G7: =FS!D27 -> 2662.85 | H7: =FS!E27 -> 2996.87 | I7: =FS!F27 -> 3179.95 | J7: =FS!G27 -> 3416.57 | K7: =J7*(1+$C$23) -> 4364.077 | L7: =K7*(1+$C$23) -> 5574.3533 | M7: =L7*(1+$C$23) -> 7120.2719 | N7: =M7*(1+$C$23) -> 9094.9153 | O7: =N7*(1+$C$23) -> 11617.181
B9: Tax Rate | G9: 0.3 | H9: =G9 -> 0.3 | I9: =H9 -> 0.3 | J9: =I9 -> 0.3 | K9: =J9 -> 0.3 | L9: =K9 -> 0.3 | M9: =L9 -> 0.3 | N9: =M9 -> 0.3 | O9: =N9 -> 0.3
B11: EBIT*(1-T) | G11: =G7*(1-G9) -> 1863.995 | H11: =H7*(1-H9) -> 2097.809 | I11: =I7*(1-I9) -> 2225.965 | J11: =J7*(1-J9) -> 2391.599 | K11: =K7*(1-K9) -> 3054.8539 | L11: =L7*(1-L9) -> 3902.0473 | M11: =M7*(1-M9) -> 4984.1903 | N11: =N7*(1-N9) -> 6366.4407 | O11: =O7*(1-O9) -> 8132.0265
B13: Less: Reinvestment Rate | G13: ='Intrinsic Growth'!$G$52 -> 0.88786204 | H13: ='Intrinsic Growth'!$G$52 -> 0.88786204 | I13: ='Intrinsic Growth'!$G$52 -> 0.88786204 | J13: ='Intrinsic Growth'!$G$52 -> 0.88786204 | K13: ='Intrinsic Growth'!$G$52 -> 0.88786204 | L13: ='Intrinsic Growth'!$G$52 -> 0.88786204 | M13: ='Intrinsic Growth'!$G$52 -> 0.88786204 | N13: ='Intrinsic Growth'!$G$52 -> 0.88786204 | O13: ='Intrinsic Growth'!$G$52 -> 0.88786204
B15: Free Cash Flow to Firm (FCFF) | G15: =G11*(1-G13) -> 209.02459 | H15: =H11*(1-H13) -> 235.24401 | I15: =I11*(1-I13) -> 249.61517 | J15: =J11*(1-J13) -> 268.18903 | K15: =K11*(1-K13) -> 342.56508 | L15: =L11*(1-L13) -> 437.56761 | M15: =M11*(1-M13) -> 558.91692 | N15: =N11*(1-N13) -> 713.91965 | O15: =O11*(1-O13) -> 911.90883
B17: Mid Year Convention | K17: 0.5 | L17: =K17+1 -> 1.5 | M17: =L17+1 -> 2.5 | N17: =M17+1 -> 3.5 | O17: =N17+1 -> 4.5
B19: Discounting Factor | K19: =1/(1+$D$24)^K17 -> 1 | L19: =1/(1+$D$24)^L17 -> 1 | M19: =1/(1+$D$24)^M17 -> 1 | N19: =1/(1+$D$24)^N17 -> 1 | O19: =1/(1+$D$24)^O17 -> 1
B21: PV of FCFF | K21: =K15*K19 -> 342.56508 | L21: =L15*L19 -> 437.56761 | M21: =M15*M19 -> 558.91692 | N21: =N15*N19 -> 713.91965 | O21: =O15*O19 -> 911.90883
B23: Expected Growth Rate | C23: ='Intrinsic Growth'!G60 -> 0.27732698
B24: Terminal Growth Rate | C24: 0.065
B26: Calculating Terminal Value
B28: FCFF (n+1) | E28: =O15*(1+C23) -> 1164.8058
B29: WACC | E29: 0.1205
B30: =B24 -> Terminal Growth Rate | E30: 0.065
B32: Terminal Value | E32: =E28/E29-E30 -> 9666.3728
B34: Calculating Equity Value Per Share
B36: PV of FCFF | E36: =SUM(K21:O21) -> 2964.8781
B37: PV of Terminal Value | E37: =E32*O19 -> 9666.3728
B38: Enterprise Value | E38: =SUM(E36:E37) -> 12631.251
B40: Add: Cash | E40: ='Data Sheet'!K69 -> 781.98
B41: Less: Debt | E41: =SUM('Raw FS'!N7:N8) -> 864
B42: Equity Value | E42: =E38+E40-E41 -> 12549.231
B43: No. of Shares | E43: ='Data Sheet'!B6 -> 95.919781
B45: Equity Value per Share | E45: =E42/E43 -> 130.83048
B47: Share Price | E47: 2541
B48: Discount/Premium | E48: =E47/E45 -> 19.42208

Sheet CSS
B2: ='Profit & Loss'!$A$1 -> ASIAN PAINTS LTD
B5: ="Common Size Income Statement - "& 'Profit & Loss'!$A$1 -> Common Size Income Statement - ASIAN PAINTS LTD
B7: Particulars | C7: =FS!D5 -> 42460 | D7: =FS!E5 -> 42825 | E7: =FS!F5 -> 43190 | F7: =FS!G5 -> 43555 | G7: =FS!H5 -> 43921 | H7: =FS!I5 -> 44286 | I7: =FS!J5 -> 44651 | J7: =FS!K5 -> 45016 | ... L7: =FS!M5 -> 45747
B9: =FS!B9 -> Sales | C9: =FS!D9/FS!D$9 -> 1 | D9: =FS!E9/FS!E$9 -> 1 | E9: =FS!F9/FS!F$9 -> 1 | F9: =FS!G9/FS!G$9 -> 1 | G9: =FS!H9/FS!H$9 -> 1 | H9: =FS!I9/FS!I$9 -> 1 | I9: =FS!J9/FS!J$9 -> 1 | J9: =FS!K9/FS!K$9 -> 1 | ... L9: =FS!M9/FS!M$9 -> 1
B10: =FS!B12 -> COGS | C10: =FS!D12/FS!D$9 -> 0.55395197 | D10: =FS!E12/FS!E$9 -> 0.5771329 | E10: =FS!F12/FS!F$9 -> 0.59866564 | F10: =FS!G12/FS!G$9 -> 0.60618717 | G10: =FS!H12/FS!H$9 -> 0.58317769 | H10: =FS!I12/FS!I$9 -> 0.57512001 | I10: =FS!J12/FS!J$9 -> 0.64588087 | J10: =FS!K12/FS!K$9 -> 0.63007186 | ... L10: =FS!M12/FS!M$9 -> 0.5938688
B11: =FS!B15 -> Gross Profit | C11: =FS!D15/FS!D$9 -> 0.44604803 | D11: =FS!E15/FS!E$9 -> 0.4228671 | E11: =FS!F15/FS!F$9 -> 0.40133436 | F11: =FS!G15/FS!G$9 -> 0.39381283 | G11: =FS!H15/FS!H$9 -> 0.41682231 | H11: =FS!I15/FS!I$9 -> 0.42487999 | I11: =FS!J15/FS!J$9 -> 0.35411913 | J11: =FS!K15/FS!K$9 -> 0.36992814 | ... L11: =FS!M15/FS!M$9 -> 0.4061312
B12: =FS!B18 -> S&G Expenses | C12: =FS!D18/FS!D$9 -> 0.25918177 | D12: =FS!E18/FS!E$9 -> 0.26730465 | E12: =FS!F18/FS!F$9 -> 0.11403039 | F12: =FS!G18/FS!G$9 -> 0.10878825 | G12: =FS!H18/FS!H$9 -> 0.096800544 | H12: =FS!I18/FS!I$9 -> 0.088152651 | I12: =FS!J18/FS!J$9 -> 0.090927272 | J12: =FS!K18/FS!K$9 -> 0.08899697 | ... L12: =FS!M18/FS!M$9 -> 0.10395681
B13: =FS!B21 -> EBITDA | C13: =FS!D21/FS!D$9 -> 0.19094292 | D13: =FS!E21/FS!E$9 -> 0.19876258 | E13: =FS!F21/FS!F$9 -> 0.19043659 | F13: =FS!G21/FS!G$9 -> 0.19568163 | G13: =FS!H21/FS!H$9 -> 0.20566863 | H13: =FS!I21/FS!I$9 -> 0.22362856 | I13: =FS!J21/FS!J$9 -> 0.16506525 | J13: =FS!K21/FS!K$9 -> 0.18150467 | ... L13: =FS!M21/FS!M$9 -> 0.17714497
B14: =FS!B24 -> Depriciation | C14: =FS!D24/FS!D$9 -> 0.019309827 | D14: =FS!E24/FS!E$9 -> 0.022227475 | E14: =FS!F24/FS!F$9 -> 0.021425239 | F14: =FS!G24/FS!G$9 -> 0.03233554 | G14: =FS!H24/FS!H$9 -> 0.038617107 | H14: =FS!I24/FS!I$9 -> 0.036442576 | I14: =FS!J24/FS!J$9 -> 0.028052374 | J14: =FS!K24/FS!K$9 -> 0.024878373 | ... L14: =FS!M24/FS!M$9 -> 0.030270498
B15: =FS!B27 -> EBIT | C15: =FS!D27/FS!D$9 -> 0.18658528 | D15: =FS!E27/FS!E$9 -> 0.19896906 | E15: =FS!F27/FS!F$9 -> 0.18900654 | F15: =FS!G27/FS!G$9 -> 0.1775752 | G15: =FS!H27/FS!H$9 -> 0.18461847 | H15: =FS!I27/FS!I$9 -> 0.20246039 | I15: =FS!J27/FS!J$9 -> 0.14718012 | J15: =FS!K27/FS!K$9 -> 0.16913652 | ... L15: =FS!M27/FS!M$9 -> 0.15720373
B16: =FS!B30 -> Interest | C16: =FS!D30/FS!D$9 -> 0.0034334187 | D16: =FS!E30/FS!E$9 -> 0.0024784242 | E16: =FS!F30/FS!F$9 -> 0.0024648505 | F16: =FS!G30/FS!G$9 -> 0.0057416452 | G16: =FS!H30/FS!H$9 -> 0.0050630218 | H16: =FS!I30/FS!I$9 -> 0.0042200933 | I16: =FS!J30/FS!J$9 -> 0.0032785499 | J16: =FS!K30/FS!K$9 -> 0.0041883417 | ... L16: =FS!M30/FS!M$9 -> 0.0066956451
B17: =FS!B33 -> EBT | C17: =FS!D33/FS!D$9 -> 0.18315186 | D17: =FS!E33/FS!E$9 -> 0.19649064 | E17: =FS!F33/FS!F$9 -> 0.18654169 | F17: =FS!G33/FS!G$9 -> 0.17183356 | G17: =FS!H33/FS!H$9 -> 0.17955545 | H17: =FS!I33/FS!I$9 -> 0.1982403 | I17: =FS!J33/FS!J$9 -> 0.14390157 | J17: =FS!K33/FS!K$9 -> 0.16494818 | ... L17: =FS!M33/FS!M$9 -> 0.15050809
B18: =FS!B36 -> Tax | C18: =FS!D36/FS!D$9 -> 0.059173219 | D18: =FS!E36/FS!E$9 -> 0.062627183 | E18: =FS!F36/FS!F$9 -> 0.061871491 | F18: =FS!G36/FS!G$9 -> 0.05707134 | G18: =FS!H36/FS!H$9 -> 0.042295751 | H18: =FS!I36/FS!I$9 -> 0.05055085 | I18: =FS!J36/FS!J$9 -> 0.03789902 | J18: =FS!K36/FS!K$9 -> 0.043304177 | ... L18: =FS!M36/FS!M$9 -> 0.041095252
B19: =FS!B39 -> Net Profit | C19: =FS!D39/FS!D$9 -> 0.12228296 | D19: =FS!E39/FS!E$9 -> 0.1287632 | E19: =FS!F39/FS!F$9 -> 0.12118779 | F19: =FS!G39/FS!G$9 -> 0.1120533 | G19: =FS!H39/FS!H$9 -> 0.13384476 | H19: =FS!I39/FS!I$9 -> 0.14458252 | I19: =FS!J39/FS!J$9 -> 0.10413872 | J19: =FS!K39/FS!K$9 -> 0.11906691 | ... L19: =FS!M39/FS!M$9 -> 0.10815995
B22: ="Common Size Balance Sheet - "& 'Profit & Loss'!$A$1 -> Common Size Balance Sheet - ASIAN PAINTS LTD
B24: Particulars | C24: =FS!D5 -> 42460 | D24: =FS!E5 -> 42825 | E24: =FS!F5 -> 43190 | F24: =FS!G5 -> 43555 | G24: =FS!H5 -> 43921 | H24: =FS!I5 -> 44286 | I24: =FS!J5 -> 44651 | J24: =FS!K5 -> 45016 | ... L24: =FS!M5 -> 45747
B26: =FS!B55 -> Equity Share Capital | C26: =FS!D55/FS!D$59 -> 0.0090841678 | D26: =FS!E55/FS!E$59 -> 0.0077322476 | E26: =FS!F55/FS!F$59 -> 0.0069691677 | F26: =FS!G55/FS!G$59 -> 0.0059031906 | G26: =FS!H55/FS!H$59 -> 0.0059437463 | H26: =FS!I55/FS!I$59 -> 0.004712277 | I26: =FS!J55/FS!J$59 -> 0.004177986 | J26: =FS!K55/FS!K$59 -> 0.0037208104 | ... L26: =FS!M55/FS!M$59 -> 0.0031599147
B27: =FS!B56 -> Reserves | C27: =FS!D56/FS!D$59 -> 0.60885328 | D27: =FS!E56/FS!E$59 -> 0.60522813 | E27: =FS!F56/FS!F$59 -> 0.60408487 | F27: =FS!G56/FS!G$59 -> 0.57694149 | G27: =FS!H56/FS!H$59 -> 0.62177833 | H27: =FS!I56/FS!I$59 -> 0.62442435 | I27: =FS!J56/FS!J$59 -> 0.59741193 | J27: =FS!K56/FS!K$59 -> 0.61663007 | ... L27: =FS!M56/FS!M$59 -> 0.6359325
B28: =FS!B57 -> Borrowings | C28: =FS!D57/FS!D$59 -> 0.030617396 | D28: =FS!E57/FS!E$59 -> 0.045169804 | E28: =FS!F57/FS!F$59 -> 0.038756913 | F28: =FS!G57/FS!G$59 -> 0.081211951 | G28: =FS!H57/FS!H$59 -> 0.069308593 | H28: =FS!I57/FS!I$59 -> 0.053701879 | I28: =FS!J57/FS!J$59 -> 0.069119709 | J28: =FS!K57/FS!K$59 -> 0.074967813 | ... L28: =FS!M57/FS!M$59 -> 0.075449552
B29: =FS!B58 -> Other Liabilities | C29: =FS!D58/FS!D$59 -> 0.35144516 | D29: =FS!E58/FS!E$59 -> 0.34186981 | E29: =FS!F58/FS!F$59 -> 0.35018905 | F29: =FS!G58/FS!G$59 -> 0.33594337 | G29: =FS!H58/FS!H$59 -> 0.30296933 | H29: =FS!I58/FS!I$59 -> 0.31716149 | I29: =FS!J58/FS!J$59 -> 0.32929037 | J29: =FS!K58/FS!K$59 -> 0.30468131 | ... L29: =FS!M58/FS!M$59 -> 0.28545803
B30: =FS!B59 -> Total Liabilities | C30: =FS!D59/FS!D$59 -> 1 | D30: =FS!E59/FS!E$59 -> 1 | E30: =FS!F59/FS!F$59 -> 1 | F30: =FS!G59/FS!G$59 -> 1 | G30: =FS!H59/FS!H$59 -> 1 | H30: =FS!I59/FS!I$59 -> 1 | I30: =FS!J59/FS!J$59 -> 1 | J30: =FS!K59/FS!K$59 -> 1 | ... L30: =FS!M59/FS!M$59 -> 1
B32: =FS!B61 -> Net Block | C32: =FS!D61/FS!D$72 -> 0.32354771 | D32: =FS!E61/FS!E$72 -> 0.26631918 | E32: =FS!F61/FS!F$72 -> 0.27116979 | F32: =FS!G61/FS!G$72 -> 0.39981685 | G32: =FS!H61/FS!H$72 -> 0.38866784 | H32: =FS!I61/FS!I$72 -> 0.28781244 | I32: =FS!J61/FS!J$72 -> 0.24039362 | J32: =FS!K61/FS!K$72 -> 0.22384057 | ... L32: =FS!M61/FS!M$72 -> 0.30373988
B33: =FS!B62 -> Capital Work in Progress | C33: =FS!D62/FS!D$72 -> 0.010094677 | D33: =FS!E62/FS!E$72 -> 0.020760665 | E33: =FS!F62/FS!F$72 -> 0.10208973 | F33: =FS!G62/FS!G$72 -> 0.01290369 | G33: =FS!H62/FS!H$72 -> 0.0086900645 | H33: =FS!I62/FS!I$72 -> 0.0089892873 | I33: =FS!J62/FS!J$72 -> 0.018574005 | J33: =FS!K62/FS!K$72 -> 0.039550679 | ... L33: =FS!M62/FS!M$72 -> 0.041326953
B34: =FS!B63 -> Investments | C34: =FS!D63/FS!D$72 -> 0.25685409 | D34: =FS!E63/FS!E$72 -> 0.21378068 | E34: =FS!F63/FS!F$72 -> 0.15553479 | F34: =FS!G63/FS!G$72 -> 0.15807775 | G34: =FS!H63/FS!H$72 -> 0.12509938 | H34: =FS!I63/FS!I$72 -> 0.23270552 | I34: =FS!J63/FS!J$72 -> 0.14145262 | J34: =FS!K63/FS!K$72 -> 0.165315 | ... L34: =FS!M63/FS!M$72 -> 0.15564853
B35: =FS!B64 -> Other Assets | C35: =FS!D64/FS!D$72 -> 0.049800029 | D35: =FS!E64/FS!E$72 -> 0.013495964 | E35: =FS!F64/FS!F$72 -> 0.031306036 | F35: =FS!G64/FS!G$72 -> 0.024709456 | G35: =FS!H64/FS!H$72 -> -0.018324486 | H35: =FS!I64/FS!I$72 -> 0.002709854 | I35: =FS!J64/FS!J$72 -> -0.10734314 | J35: =FS!K64/FS!K$72 -> -0.11610465 | ... L35: =FS!M64/FS!M$72 -> -0.078001993
B36: =FS!B65 -> Total Non-Current Assets (A) | C36: =FS!D65/FS!D$72 -> 0.6402965 | D36: =FS!E65/FS!E$72 -> 0.51435649 | E36: =FS!F65/FS!F$72 -> 0.56010035 | F36: =FS!G65/FS!G$72 -> 0.59550774 | G36: =FS!H65/FS!H$72 -> 0.5041328 | H36: =FS!I65/FS!I$72 -> 0.5322171 | I36: =FS!J65/FS!J$72 -> 0.2930771 | J36: =FS!K65/FS!K$72 -> 0.31260161 | ... L36: =FS!M65/FS!M$72 -> 0.42271337
B38: =FS!B67 -> Working Capital | C38: =FS!D67/FS!D$72 -> 0.058058363 | D38: =FS!E67/FS!E$72 -> 0.15726966 | E38: =FS!F67/FS!F$72 -> 0.12101663 | F38: =FS!G67/FS!G$72 -> 0.09325835 | G38: =FS!H67/FS!H$72 -> 0.17457338 | H38: =FS!I67/FS!I$72 -> 0.15333126 | I38: =FS!J67/FS!J$72 -> 0.27028939 | J38: =FS!K67/FS!K$72 -> 0.26661244 | ... L38: =FS!M67/FS!M$72 -> 0.2138266
B39: =FS!B68 -> Debtors | C39: =FS!D68/FS!D$72 -> 0.11240048 | D39: =FS!E68/FS!E$72 -> 0.11661248 | E39: =FS!F68/FS!F$72 -> 0.12574073 | F39: =FS!G68/FS!G$72 -> 0.11738253 | G39: =FS!H68/FS!H$72 -> 0.111242 | H39: =FS!I68/FS!I$72 -> 0.12783722 | I39: =FS!J68/FS!J$72 -> 0.16862826 | J39: =FS!K68/FS!K$72 -> 0.17987046 | ... L39: =FS!M68/FS!M$72 -> 0.14210557
B40: =FS!B69 -> Inventory | C40: =FS!D69/FS!D$72 -> 0.18924466 | D40: =FS!E69/FS!E$72 -> 0.21176137 | E40: =FS!F69/FS!F$72 -> 0.19314229 | F40: =FS!G69/FS!G$72 -> 0.19385138 | G40: =FS!H69/FS!H$72 -> 0.21005182 | H40: =FS!I69/FS!I$72 -> 0.18661442 | I40: =FS!J69/FS!J$72 -> 0.26800526 | J40: =FS!K69/FS!K$72 -> 0.24091549 | ... L40: =FS!M69/FS!M$72 -> 0.22135446
B41: =FS!B70 -> Total Current Assets (B) | C41: =FS!D70/FS!D$72 -> 0.3597035 | D41: =FS!E70/FS!E$72 -> 0.48564351 | E41: =FS!F70/FS!F$72 -> 0.43989965 | F41: =FS!G70/FS!G$72 -> 0.40449226 | G41: =FS!H70/FS!H$72 -> 0.4958672 | H41: =FS!I70/FS!I$72 -> 0.4677829 | I41: =FS!J70/FS!J$72 -> 0.7069229 | J41: =FS!K70/FS!K$72 -> 0.68739839 | ... L41: =FS!M70/FS!M$72 -> 0.57728663
B43: =FS!B72 -> Total Assets (A)+(B) | C43: =FS!D72/FS!D$72 -> 1 | D43: =FS!E72/FS!E$72 -> 1 | E43: =FS!F72/FS!F$72 -> 1 | F43: =FS!G72/FS!G$72 -> 1 | G43: =FS!H72/FS!H$72 -> 1 | H43: =FS!I72/FS!I$72 -> 1 | I43: =FS!J72/FS!J$72 -> 1 | J43: =FS!K72/FS!K$72 -> 1 | ... L43: =FS!M72/FS!M$72 -> 1

Sheet Intrinsic Growth
B2: ="Intrinsic Growth Calculation - "&'Profit & Loss'!$A$1 -> Intrinsic Growth Calculation - ASIAN PAINTS LTD
B5: ="ROIC Calculation - "&'Profit & Loss'!$A$1 -> ROIC Calculation - ASIAN PAINTS LTD | C5: ='Raw FS'!J3 -> 44256 | D5: ='Raw FS'!K3 -> 44621 | E5: ='Raw FS'!L3 -> 44986 | F5: ='Raw FS'!M3 -> 45352 | G5: ='Raw FS'!N3 -> 45717
B6: Current Assets -
B7: ='Raw FS'!B34 -> Inventories | C7: ='Raw FS'!J34 -> 3799 | D7: ='Raw FS'!K34 -> 6153 | E7: ='Raw FS'!L34 -> 6211 | F7: ='Raw FS'!M34 -> 5923 | G7: ='Raw FS'!N34 -> 6719
B8: ='Raw FS'!B35 -> Trade receivables + | C8: ='Raw FS'!J35 -> 2602 | D8: ='Raw FS'!K35 -> 3871 | E8: ='Raw FS'!L35 -> 4637 | F8: ='Raw FS'!M35 -> 4889 | G8: ='Raw FS'!N35 -> 4314
B9: ='Raw FS'!B37 -> Loans n Advances | C9: ='Raw FS'!J36 -> 611 | D9: ='Raw FS'!K36 -> 864 | E9: ='Raw FS'!L36 -> 844 | F9: ='Raw FS'!M36 -> 1084 | G9: ='Raw FS'!N36 -> 782
B10: ='Raw FS'!B38 -> Other asset items | C10: ='Raw FS'!J37 -> 11 | D10: ='Raw FS'!K37 -> 8 | E10: ='Raw FS'!L37 -> 12 | F10: ='Raw FS'!M37 -> 17 | G10: ='Raw FS'!N37 -> 22
B11: Total Current Assets | C11: =SUM(C7:C10) -> 7023 | D11: =SUM(D7:D10) -> 10896 | E11: =SUM(E7:E10) -> 11704 | F11: =SUM(F7:F10) -> 11913 | G11: =SUM(G7:G10) -> 11837
B13: Current Liabilities -
B14: ='Raw FS'!B13 -> Trade Payables | C14: ='Raw FS'!J13 -> 3379 | D14: ='Raw FS'!K13 -> 4164 | E14: ='Raw FS'!L13 -> 3635 | F14: ='Raw FS'!M13 -> 3831 | G14: ='Raw FS'!N13 -> 3848
B15: ='Raw FS'!B14 -> Advance from Customers | C15: ='Raw FS'!J14 -> 41 | D15: ='Raw FS'!K14 -> 76 | E15: ='Raw FS'!L14 -> 108 | F15: ='Raw FS'!M14 -> 154 | G15: ='Raw FS'!N14 -> 173
B16: ='Raw FS'!B15 -> Other liability items | C16: ='Raw FS'!J15 -> 2613 | D16: ='Raw FS'!K15 -> 2932 | E16: ='Raw FS'!L15 -> 3657 | F16: ='Raw FS'!M15 -> 4017 | G16: ='Raw FS'!N15 -> 3985
B17: Total Current Liabilities | C17: =SUM(C14:C16) -> 6033 | D17: =SUM(D14:D16) -> 7172 | E17: =SUM(E14:E16) -> 7400 | F17: =SUM(F14:F16) -> 8002 | G17: =SUM(G14:G16) -> 8006
B19: Net Working Capital | C19: =C11-C17 -> 990 | D19: =D11-D17 -> 3724 | E19: =E11-E17 -> 4304 | F19: =F11-F17 -> 3911 | G19: =G11-G17 -> 3831
B21: Non-Current Assets -
B22: ='Raw FS'!B19 -> Land | C22: ='Raw FS'!J19 -> 644 | D22: ='Raw FS'!K19 -> 644 | E22: ='Raw FS'!L19 -> 804 | F22: ='Raw FS'!M19 -> 1126 | G22: ='Raw FS'!N19 -> 1050
B23: ='Raw FS'!B20 -> Building | C23: ='Raw FS'!J20 -> 2249 | D23: ='Raw FS'!K20 -> 2325 | E23: ='Raw FS'!L20 -> 2883 | F23: ='Raw FS'!M20 -> 3390 | G23: ='Raw FS'!N20 -> 4136
B24: ='Raw FS'!B21 -> Plant Machinery | C24: ='Raw FS'!J21 -> 4340 | D24: ='Raw FS'!K21 -> 4531 | E24: ='Raw FS'!L21 -> 4825 | F24: ='Raw FS'!M21 -> 5422 | G24: ='Raw FS'!N21 -> 7576
B25: ='Raw FS'!B22 -> Equipments | C25: ='Raw FS'!J22 -> 243 | D25: ='Raw FS'!K22 -> 253 | E25: ='Raw FS'!L22 -> 270 | F25: ='Raw FS'!M22 -> 298 | G25: ='Raw FS'!N22 -> 325
B26: ='Raw FS'!B23 -> Furniture n fittings | C26: ='Raw FS'!J23 -> 99 | D26: ='Raw FS'!K23 -> 113 | E26: ='Raw FS'!L23 -> 146 | F26: ='Raw FS'!M23 -> 175 | G26: ='Raw FS'!N23 -> 203
B27: ='Raw FS'!B24 -> Vehicles | C27: ='Raw FS'!J24 -> 38 | D27: ='Raw FS'!K24 -> 32 | E27: ='Raw FS'!L24 -> 36 | F27: ='Raw FS'!M24 -> 40 | G27: ='Raw FS'!N24 -> 39
B28: ='Raw FS'!B25 -> Intangible Assets | C28: ='Raw FS'!J25 -> 476 | D28: ='Raw FS'!K25 -> 345 | E28: ='Raw FS'!L25 -> 422 | F28: ='Raw FS'!M25 -> 850 | G28: ='Raw FS'!N25 -> 827
B29: ='Raw FS'!B26 -> Other fixed assets | C29: ='Raw FS'!J26 -> 302 | D29: ='Raw FS'!K26 -> 294 | E29: ='Raw FS'!L26 -> 289 | F29: ='Raw FS'!M26 -> 321 | G29: ='Raw FS'!N26 -> 328
B30: ='Raw FS'!B27 -> Gross Block | C30: =SUM(C21:C29) -> 8391 | D30: =SUM(D21:D29) -> 8537 | E30: =SUM(E21:E29) -> 9675 | F30: =SUM(F21:F29) -> 11622 | G30: =SUM(G21:G29) -> 14484
B31: ='Raw FS'!B28 -> Accumulated Depreciation | C31: =-'Raw FS'!J28 -> -2533 | D31: =-'Raw FS'!K28 -> -3019 | E31: =-'Raw FS'!L28 -> -3905 | F31: =-'Raw FS'!M28 -> -4475 | G31: =-'Raw FS'!N28 -> -5264
B32: Net Assets | C32: =SUM(C30:C31) -> 5858 | D32: =SUM(D30:D31) -> 5518 | E32: =SUM(E30:E31) -> 5770 | F32: =SUM(F30:F31) -> 7147 | G32: =SUM(G30:G31) -> 9220
B34: Invested Capital | C34: =C32+C19 -> 6848 | D34: =D32+D19 -> 9242 | E34: =E32+E19 -> 10074 | F34: =F32+F19 -> 11058 | G34: =G32+G19 -> 13051
B35: EBIT | C35: =FS!D27 -> 2662.85 | D35: =FS!E27 -> 2996.87 | E35: =FS!F27 -> 3179.95 | F35: =FS!G27 -> 3416.57 | G35: =FS!H27 -> 3731.37
B37: ROIC | C37: =C35/C34 -> 0.38885076 | D37: =D35/D34 -> 0.32426639 | E37: =E35/E34 -> 0.31565912 | F37: =F35/F34 -> 0.30896817 | G37: =G35/G34 -> 0.28590683
B40: ="Reinvestment Rate Calculation - "&'Profit & Loss'!$A$1 -> Reinvestment Rate Calculation - ASIAN PAINTS LTD | C40: ='Raw FS'!J3 -> 44256 | D40: ='Raw FS'!K3 -> 44621 | E40: ='Raw FS'!L3 -> 44986 | F40: ='Raw FS'!M3 -> 45352 | G40: ='Raw FS'!N3 -> 45717
B42: Net Capex | C42: =-SUM('Raw FS'!J52:J53) -> 254 | D42: =-SUM('Raw FS'!K52:K53) -> 511 | E42: =-SUM('Raw FS'!L52:L53) -> 1420 | F42: =-SUM('Raw FS'!M52:M53) -> 2491 | G42: =-SUM('Raw FS'!N52:N53) -> 1820
B43: Change in Working Capital | D43: =D19-C19 -> 2734 | E43: =E19-D19 -> 580 | F43: =F19-E19 -> -393 | G43: =G19-F19 -> -80
B45: EBIT | C45: =FS!D27 -> 2662.85 | D45: =FS!E27 -> 2996.87 | E45: =FS!F27 -> 3179.95 | F45: =FS!G27 -> 3416.57 | G45: =FS!H27 -> 3731.37
B46: Marginal Tax Rate | C46: 0.3 | D46: =C46 -> 0.3 | E46: =D46 -> 0.3 | F46: =E46 -> 0.3 | G46: =F46 -> 0.3
B47: EBIT*(1-T) | C47: =C45*(1-C46) -> 1863.995 | D47: =D45*(1-D46) -> 2097.809 | E47: =E45*(1-E46) -> 2225.965 | F47: =F45*(1-F46) -> 2391.599 | G47: =G45*(1-G46) -> 2611.959
B49: Reinvestment | D49: =SUM(D42:D43) -> 3245 | E49: =SUM(E42:E43) -> 2000 | F49: =SUM(F42:F43) -> 2098 | G49: =SUM(G42:G43) -> 1740
B50: Reinvestment Rate | D50: =D49/D47 -> 1.546852 | E50: =E49/E47 -> 0.89848672 | F50: =F49/F47 -> 0.87723736 | G50: =G49/G47 -> 0.66616666
E51: 4 Year Average | G51: =AVERAGE(D50:G50) -> 0.99718568
E52: 4 Year Median | G52: =MEDIAN(D50:G50) -> 0.88786204
B54: ="Intrinsic Growth Calculation - "&'Profit & Loss'!$A$1 -> Intrinsic Growth Calculation - ASIAN PAINTS LTD | D54: ='Raw FS'!K3 -> 44621 | E54: ='Raw FS'!L3 -> 44986 | F54: ='Raw FS'!M3 -> 45352 | G54: ='Raw FS'!N3 -> 45717
B55: =B37 -> ROIC | D55: =D37 -> 0.32426639 | E55: =E37 -> 0.31565912 | F55: =F37 -> 0.30896817 | G55: =G37 -> 0.28590683
B56: =B50 -> Reinvestment Rate | D56: =D50 -> 1.546852 | E56: =E50 -> 0.89848672 | F56: =F50 -> 0.87723736 | G56: =G50 -> 0.66616666
B58: Intrinsic Growth | D58: =D55*D56 -> 0.50159211 | E58: =E55*E56 -> 0.28361553 | F58: =F55*F56 -> 0.27103842 | G58: =G55*G56 -> 0.1904616
E59: 4 Year Average | G59: =AVERAGE(D58:G58) -> 0.31167691
E60: 4 Year Median | G60: =MEDIAN(D58:G58) -> 0.27732698

Sheet Raw FS
C3: 41699 | D3: 42064 | E3: 42430 | F3: 42795 | G3: 43160 | H3: 43525 | I3: 43891 | J3: 44256 | K3: 44621 | L3: 44986 | M3: 45352 | N3: 45717
B4: Equity Capital | C4: 96 | D4: 96 | E4: 96 | F4: 96 | G4: 96 | H4: 96 | I4: 96 | J4: 96 | K4: 96 | L4: 96 | M4: 96 | N4: 96
B5: Reserves | C5: 3943 | D5: 4646 | E5: 6429 | F5: 7508 | G5: 8314 | H5: 9375 | I5: 10034 | J5: 12710 | K5: 13716 | L5: 15896 | M5: 18632 | N5: 19304
B6: Borrowings -
B7: Long term Borrowings | C7: 41 | D7: 78 | E7: 73 | F7: 41 | G7: 28 | H7: 19 | I7: 19 | J7: 15 | K7: 45 | L7: 76 | M7: 54 | N7: 260
B8: Short term Borrowings | C8: 199 | D8: 332 | E8: 231 | F8: 504 | G8: 492 | H8: 597 | I8: 321 | J8: 334 | K8: 731 | L8: 896 | M8: 1053 | N8: 604
B9: Lease Liabilities | C9: 0 | D9: 0 | E9: 0 | F9: 0 | G9: 0 | H9: 693 | I9: 764 | J9: 745 | K9: 811 | L9: 960 | M9: 1367 | N9: 1427
B10: Other Borrowings | C10: 9 | D10: 8 | E10: 20 | F10: 15 | G10: 13 | H10: 11 | I10: 15 | J10: 0 | K10: 0 | L10: 0 | M10: 0 | N10: 0
B11: Other Liabilities -
B12: Non controlling int | C12: 246 | D12: 264 | E12: 384 | F12: 375 | G12: 328 | H12: 361 | I12: 404 | J12: 423 | K12: 388 | L12: 454 | M12: 695 | N12: 659
B13: Trade Payables | C13: 1746 | D13: 1549 | E13: 1565 | F13: 1923 | G13: 2160 | H13: 2394 | I13: 2137 | J13: 3379 | K13: 4164 | L13: 3635 | M13: 3831 | N13: 3848
B14: Advance from Customers | C14: 0 | D14: 5 | E14: 12 | F14: 17 | G14: 16 | H14: 13 | I14: 29 | J14: 41 | K14: 76 | L14: 108 | M14: 154 | N14: 173
B15: Other liability items | C15: 1795 | D15: 1937 | E15: 1750 | F15: 1925 | G15: 2316 | H15: 2690 | I15: 2320 | J15: 2613 | K15: 2932 | L15: 3657 | M15: 4017 | N15: 3985
B16: Total Liabilities | C16: 8075 | D16: 8914 | E16: 10559 | F16: 12405 | G16: 13763 | H16: 16249 | I16: 16138 | J16: 20355 | K16: 22958 | L16: 25779 | M16: 29901 | N16: 30355
B18: Fixed Assets -
B19: Land | C19: 247 | D19: 251 | E19: 429 | F19: 408 | G19: 586 | H19: 605 | I19: 640 | J19: 644 | K19: 644 | L19: 804 | M19: 1126 | N19: 1050
B20: Building | C20: 931 | D20: 962 | E20: 923 | F20: 931 | G20: 957 | H20: 2402 | I20: 2257 | J20: 2249 | K20: 2325 | L20: 2883 | M20: 3390 | N20: 4136
B21: Plant Machinery | C21: 2054 | D21: 2132 | E21: 1793 | F21: 1980 | G21: 2157 | H21: 4006 | I21: 4208 | J21: 4340 | K21: 4531 | L21: 4825 | M21: 5422 | N21: 7576
B22: Equipments | C22: 155 | D22: 171 | E22: 97 | F22: 119 | G22: 200 | H22: 221 | I22: 241 | J22: 243 | K22: 253 | L22: 270 | M22: 298 | N22: 325
B23: Furniture n fittings | C23: 71 | D23: 83 | E23: 49 | F23: 59 | G23: 72 | H23: 88 | I23: 94 | J23: 99 | K23: 113 | L23: 146 | M23: 175 | N23: 203
B24: Vehicles | C24: 14 | D24: 18 | E24: 11 | F24: 14 | G24: 27 | H24: 47 | I24: 43 | J24: 38 | K24: 32 | L24: 36 | M24: 40 | N24: 39
B25: Intangible Assets | C25: 203 | D25: 351 | E25: 339 | F25: 276 | G25: 468 | H25: 512 | I25: 505 | J25: 476 | K25: 345 | L25: 422 | M25: 850 | N25: 827
B26: Other fixed assets | C26: 128 | D26: 145 | E26: 103 | F26: 128 | G26: 238 | H26: 261 | I26: 293 | J26: 302 | K26: 294 | L26: 289 | M26: 321 | N26: 328
B27: Gross Block | C27: 3804 | D27: 4112 | E27: 3744 | F27: 3914 | G27: 4705 | H27: 8141 | I27: 8282 | J27: 8392 | K27: 8538 | L27: 9676 | M27: 11622 | N27: 14484
B28: Accumulated Depreciation | C28: 1242 | D28: 1452 | E28: 327 | F28: 610 | G28: 973 | H28: 1644 | I28: 2010 | J28: 2533 | K28: 3019 | L28: 3905 | M28: 4475 | N28: 5264
B29: Net Block | C29: =C27-C28 -> 2562 | D29: =D27-D28 -> 2660 | E29: =E27-E28 -> 3417 | F29: =F27-F28 -> 3304 | G29: =G27-G28 -> 3732 | H29: =H27-H28 -> 6497 | I29: =I27-I28 -> 6272 | J29: =J27-J28 -> 5859 | ... N29: =N27-N28 -> 9220
B31: CWIP | C31: 72 | D31: 196 | E31: 107 | F31: 258 | G31: 1405 | H31: 210 | I31: 140 | J31: 183 | K31: 426 | L31: 1020 | M31: 2698 | N31: 1254
B32: Investments | C32: 1424 | D32: 1588 | E32: 2712 | F32: 2652 | G32: 2141 | H32: 2569 | I32: 2019 | J32: 4737 | K32: 3248 | L32: 4262 | M32: 4588 | N32: 4725
B33: Other Assets -
B34: Inventories | C34: 2070 | D34: 2259 | E34: 1998 | F34: 2627 | G34: 2658 | H34: 3150 | I34: 3390 | J34: 3799 | K34: 6153 | L34: 6211 | M34: 5923 | N34: 6719
B35: Trade receivables + | C35: 1110 | D35: 1182 | E35: 1187 | F35: 1447 | G35: 1731 | H35: 1907 | I35: 1795 | J35: 2602 | K35: 3871 | L35: 4637 | M35: 4889 | N35: 4314
B36: Cash Equivalents | C36: 229 | D36: 204 | E36: 424 | F36: 801 | G36: 405 | H36: 445 | I36: 783 | J36: 611 | K36: 864 | L36: 844 | M36: 1084 | N36: 782
B37: Loans n Advances | C37: 7 | D37: 8 | E37: 9 | F37: 14 | G37: 13 | H37: 16 | I37: 12 | J37: 11 | K37: 8 | L37: 12 | M37: 17 | N37: 22
B38: Other asset items | C38: 603 | D38: 817 | E38: 705 | F38: 1303 | G38: 1678 | H38: 1456 | I38: 1727 | J38: 2555 | K38: 2869 | L38: 3024 | M38: 3555 | N38: 3319
B39: Total Assets | C39: 8075 | D39: 8914 | E39: 10559 | F39: 12405 | G39: 13763 | H39: 16249 | I39: 16138 | J39: 20355 | K39: 22958 | L39: 25779 | M39: 29901 | N39: 30355
C42: Cashflow Statement
B43: Cash from Operating Activity - | C43: 1402 | D43: 1188 | E43: 2243 | F43: 1527 | G43: 2113 | H43: 2470 | I43: 3038 | J43: 3683 | K43: 986 | L43: 4193 | M43: 6104 | N43: 4424
B44: Profit from operations | C44: 2051 | D44: 2271 | E44: 2848 | F44: 3056 | G44: 3274 | H44: 3861 | I44: 4380 | J44: 4970 | K44: 4957 | L44: 6460 | M44: 7929 | N44: 6390
B45: Receivables | C45: -254 | D45: -155 | E45: -146 | F45: -475 | G45: -483 | H45: -205 | I45: 160 | J45: -849 | K45: -1326 | L45: -834 | M45: -362 | N45: 282
B46: Inventory | C46: -231 | D46: -144 | E46: 202 | F46: -629 | G46: -39 | H46: -492 | I46: -251 | J46: -409 | K46: -2354 | L46: -56 | M46: 315 | N46: -805
B47: Payables | C47: 317 | D47: -151 | E47: 142 | F47: 501 | G47: 442 | H47: 287 | I47: -241 | J47: 1143 | K47: 644 | L47: -539 | M47: 269 | N47: -160
B48: Other WC items | C48: 0 | D48: 0 | E48: 0 | F48: 0 | G48: 0 | H48: 0 | I48: 0 | J48: -92 | K48: 242 | L48: 657 | M48: -212 | N48: 114
B49: Working capital changes | C49: -168 | D49: -450 | E49: 198 | F49: -603 | G49: -80 | H49: -410 | I49: -331 | J49: -206 | K49: -2795 | L49: -772 | M49: 10 | N49: -570
B50: Direct taxes | C50: -480 | D50: -633 | E50: -802 | F50: -925 | G50: -1081 | H50: -982 | I50: -1011 | J50: -1080 | K50: -1176 | L50: -1494 | M50: -1835 | N50: -1396
B51: Cash from Investing Activity - | C51: -586 | D51: -465 | E51: -866 | F51: -681 | G51: -1556 | H51: -918 | I51: -518 | J51: -541 | K51: -317 | L51: -1282 | M51: -2548 | N51: -941
B52: Fixed assets purchased | C52: -251 | D52: -454 | E52: -817 | F52: -684 | G52: -1426 | H52: -1151 | I52: -404 | J52: -282 | K52: -551 | L52: -1446 | M52: -2496 | N52: -1830
B53: Fixed assets sold | C53: 16 | D53: 16 | E53: 15 | F53: 17 | G53: 17 | H53: 17 | I53: 37 | J53: 28 | K53: 40 | L53: 26 | M53: 5 | N53: 10
B54: Investments purchased | C54: -872 | D54: -243 | E54: -282 | F54: -153 | G54: -320 | H54: -573 | I54: -25 | J54: -140 | K54: 0 | L54: -146 | M54: -212 | N54: -1
... B70: Net Cash Flow | C70: 190 | D70: 147 | E70: 528 | F70: 90 | G70: -822 | H70: 434 | I70: -351 | J70: 2492 | K70: -1138 | L70: 771 | M70: 573 | N70: -270

Sheet Data
B2: S.No. | C2: Name | D2: CMP Rs. | E2: No. Eq. Shares Cr. | F2: Mar Cap Rs.Cr. | G2: Debt Rs.Cr. | H2: Cash End Rs.Cr. | I2: EV Rs.Cr. | J2: Sales Rs.Cr. | K2: EBITDA | L2: EV / EBITDA | M2: NP 12M Rs.Cr.
B3: 1 | C3: Asian Paints | D3: 2536.1 | E3: 95.92 | F3: 243262.14 | G3: 2290.29 | H3: 781.98 | I3: 244770.45 | J3: 33874.44 | K3: =I3/L3 -> 6687.7172 | L3: 36.6 | M3: 3639.97
B4: 2 | C4: Berger Paints | D4: 532.5 | E4: 116.59 | F4: 62083.93 | G4: 670.27 | H4: 500.48 | I4: 62253.72 | J4: 11654.46 | K4: =I4/L4 -> 1985.7646 | L4: 31.35 | M4: 1143.82
B5: 3 | C5: Kansai Nerolac | D5: 245.85 | E5: 80.85 | F5: 19877.04 | G5: 296.39 | H5: 290.06 | I5: 19883.37 | J5: 7851.94 | K5: =I5/L5 -> 1073.6161 | L5: 18.52 | M5: 1100.05
B6: 4 | C6: Akzo Nobel | D6: 3389.75 | E6: 4.55 | F6: 15437.03 | G6: 62.1 | H6: 299.5 | I6: 15199.63 | J6: 4050 | K6: =I6/L6 -> 633.58191 | L6: 23.99 | M6: 405
B7: 5 | C7: Indigo Paints | D7: 1130 | E7: 4.76 | F7: 5382.74 | G7: 19.7 | H7: 37.1 | I7: 5365.34 | J7: 1278.1 | K7: =I7/L7 -> 248.51042 | L7: 21.59 | M7: 143.84
B8: 6 | C8: Sirca Paints | D8: 461.75 | E8: 5.48 | F8: 2530.82 | G8: 8.33 | H8: 54.2 | I8: 2484.95 | J8: 409.37 | K8: =I8/L8 -> 79.901929 | L8: 31.1 | M8: 53.05
B9: 7 | C9: Shalimar Paints | D9: 74 | E9: 8.37 | F9: 619.5 | G9: 163.86 | H9: 45.47 | I9: 737.89 | J9: 624.19 | K9: =I9/L9 -> -32.520494 | L9: -22.69 | M9: -69.79
B10: 8 | C10: Kamdhenu Venture | D10: 9.06 | E10: 31.44 | F10: 284.81 | G10: 26.98 | H10: 5.9 | I10: 305.89 | J10: 261.89 | K10: =I10/L10 -> 16.770285 | L10: 18.24 | M10: 5.94
B11: 9 | C11: Siddhika Coatins | D11: 200.5 | E11: 0.62 | F11: 123.89 | G11: 0 | H11: 5.76 | I11: 118.13 | J11: 48.01 | K11: =I11/L11 -> 10.435512 | L11: 11.32 | M11: 8.03
B12: 10 | C12: Retina Paints | D12: 73 | E12: 1.53 | F12: 111.99 | G12: 8.12 | H12: 0.36 | I12: 119.78 | J12: 11.66 | K12: =I12/L12 -> 2.0198988 | L12: 59.3 | M12: 0.74

Sheet WACC
B2: WACC
B5: Weighted Average Cost of Capital
B7: All figures in inr crores unless stated otherwise
B9: Peer Comps
J10: Debt/ | K10: Debt/
B11: Name of the company | F11: Country | G11: Total Debt | H11: Total Equity | I11: Tax Rate 1 | J11: Equity | K11: Capital | L11: Levered Beta 2 | M11: Unlevered Beta 3
B12: Asian Paints | F12: India | G12: 2290 | H12: 244873.61 | I12: 0.3 | J12: =G12/H12 -> 0.0093517631 | K12: =G12/(G12+H12) -> 0.009265118 | L12: =Beta!AF8 -> 0.81569883 | M12: =L12/(1+(1-I12)*J12) -> 0.8103938
B13: Berger Paints | F13: India | G13: 670 | H13: 63692.79 | I13: 0.3 | J13: =G13/H13 -> 0.010519244 | K13: =G13/(G13+H13) -> 0.010409741 | L13: =Beta!AF9 -> 0.84864224 | M13: =L13/(1+(1-I13)*J13) -> 0.84243896
B14: Indigo Paints | F14: India | G14: 27.3 | H14: 5425.61 | I14: 0.3 | J14: =G14/H14 -> 0.0050316923 | K14: =G14/(G14+H14) -> 0.0050065011 | L14: =Beta!AF10 -> 0.72419311 | M14: =L14/(1+(1-I14)*J14) -> 0.72165132
B15: Sirca Paints | F15: India | G15: 50 | H15: 2516.81 | I15: 0.3 | J15: =G15/H15 -> 0.019866418 | K15: =G15/(G15+H15) -> 0.019479432 | L15: =Beta!AF11 -> 0.90098808 | M15: =L15/(1+(1-I15)*J15) -> 0.88863035
B16: Shalimar Paints | F16: India | G16: 164 | H16: 616.99 | I16: 0.3 | J16: =G16/H16 -> 0.26580658 | K16: =G16/(G16+H16) -> 0.20998988 | L16: =Beta!AF12 -> 0.69537713 | M16: =L16/(1+(1-I16)*J16) -> 0.58628942
B17: Kansai Nerolac Paints | F17: India | G17: 296 | H17: 20042.86 | I17: 0.3 | J17: =G17/H17 -> 0.014768351 | K17: =G17/(G17+H17) -> 0.014553421 | L17: =Beta!AF13 -> 0.80537586 | M17: =L17/(1+(1-I17)*J17) -> 0.7971352
H19: Average | I19: =AVERAGE(I13:I17) -> 0.3 | J19: =AVERAGE(J13:J17) -> 0.063198457 | K19: =AVERAGE(K13:K17) -> 0.051887796 | L19: =AVERAGE(L13:L17) -> 0.79491528 | M19: =AVERAGE(M13:M17) -> 0.76722905
H20: Median | I20: =MEDIAN(I13:I17) -> 0.3 | J20: =MEDIAN(J13:J17) -> 0.014768351 | K20: =MEDIAN(K13:K17) -> 0.014553421 | L20: =MEDIAN(L13:L17) -> 0.80537586 | M20: =MEDIAN(M13:M17) -> 0.7971352
B22: Cost of Debt | I22: Cost of Equity
B24: Pre Tax Cost of Debt | G24: =216/G12 -> 0.094323144 | I24: Risk Free Rate | M24: 0.0649
B25: Tax Rate | G25: 0.3 | I25: Equity Risk Premium | M25: ='Market Returns'!G8-WACC!M24 -> 0.088448
B26: Post Tax Cost of Debt | G26: =G24*(1-G25) -> 0.066026201 | I26: Levered Beta 4 | M26: =Beta!AF15 -> 0.80537586
I27: Total Equity | M27: =(M24+M25)*M26 -> 0.12350278
B29: Total Capital | I29: Levered Beta
F31: Current | G31: Target | I31: Peer Comps Unlevered Beta Median | M31: =M20 -> 0.7971352
B32: Total Debt | E32: =G13 -> 670 | F32: =E32/$E$34 -> 0.010409741 | G32: =K19 -> 0.051887796 | I32: Target D/E | M32: =G36 -> 0.054727485
B33: Total Equity | E33: =H13 -> 63692.79 | F33: =E33/$E$34 -> 0.98959026 | G33: =G34-G32 -> 0.9481122 | I33: Tax Rate | M33: =G25 -> 0.3
B34: Total Capital | E34: =SUM(E32:E33) -> 64362.79 | F34: =SUM(F32:F33) -> 1 | G34: =F34 -> 1 | I34: Levered Beta | M34: =M31*(1+(1-M32)*M33) -> 1.0231882
B36: Debt/Equity | F36: =F32/F33 -> 0.010519244 | G36: =G32/G33 -> 0.054727485 | I36: Weighted Avg. Cost of Capital
I38: Cost of Debt | M38: =G26 -> 0.066026201
I39: Weight of Debt | M39: =G32 -> 0.051887796
B40: Notes:
B41: 1. Tax Rate is marginal tax rate for the country | I41: Cost of Equity | M41: =M27 -> 0.12350278
B42: 2. Levered Beta = Unlevered beta/(1+(1 - Tax rate)* Debt/Equity | I42: Weight of Equity | M42: =G33 -> 0.9481122
B43: 3. Unlevered Beta = Levered beta*(1+(1 - Tax rate)* Debt/Equity | I43: WACC | M43: =(M38*M39)+(M41*M42) -> 0.12052044

Sheet WACC Data->

Sheet Beta
B2: ="Beta Regression "&'Profit & Loss'!A1&" & Peer Comps" -> Beta Regression ASIAN PAINTS LTD & Peer Comps
B5: ='Profit & Loss'!A1 &" 2 Year Weekly Returns" -> ASIAN PAINTS LTD 2 Year Weekly Returns | F5: Berger Paints 2 Year Weekly Returns | J5: Indigo Paints 2 Year Weekly Returns | N5: Sirca Paints 2 Year Weekly Returns | R5: Shalimar Paints 2 Year Weekly Returns | V5: Kansai Nerolac 2 Year Weekly Returns | Z5: Nifty 2 Year Weekly Returns | AD5: Beta of companies with respect to Nifty
B7: Date | C7: Closing Price | D7: Returns | F7: Date | G7: Closing Price | H7: Returns | J7: Date | K7: Closing Price | L7: Returns | N7: Date | O7: Closing Price | P7: Returns | R7: Date | S7: Closing Price | T7: Returns | V7: Date | W7: Closing Price | X7: Returns | Z7: Date | AA7: Closing Price | AB7: Returns | AD7: Companies | AF7: Beta
B8: 45179 | C8: 3196.65 | F8: 45179 | G8: 599.71 | J8: 45179 | K8: 1535.15 | N8: 45179 | O8: 400.5 | R8: 45179 | S8: 157.9 | V8: 45179 | W8: 325.21 | Z8: 45179 | AA8: 20192.35 | AD8: Asian Paints | AF8: =SLOPE(D$9:D$111,$AB$9:$AB$111) -> 0.81569883
B9: =B8+7 -> 45186 | C9: 3274.85 | D9: =C9/C8-1 -> 0.02446311 | F9: =F8+7 -> 45186 | G9: 667.8 | H9: =G9/G8-1 -> 0.11353821 | J9: =J8+7 -> 45186 | K9: 1549.15 | L9: =K9/K8-1 -> 0.00911963 | N9: =N8+7 -> 45186 | O9: 390.1 | P9: =O9/O8-1 -> -0.025967541 | R9: =R8+7 -> 45186 | S9: 153.25 | T9: =S9/S8-1 -> -0.029449018 | V9: =V8+7 -> 45186 | W9: 321.03 | X9: =W9/W8-1 -> -0.012853233 | Z9: =Z8+7 -> 45186 | AA9: 19674.25 | AB9: =AA9/AA8-1 -> -0.025658232 | AD9: =WACC!B13 -> Berger Paints | AF9: =SLOPE(H$9:H$111,$AB$9:$AB$111) -> 0.84864224
B10: =B9+7 -> 45193 | C10: 3161.05 | D10: =C10/C9-1 -> -0.034749683 | F10: =F9+7 -> 45193 | G10: 568.9 | H10: =G10/G9-1 -> -0.14809823 | J10: =J9+7 -> 45193 | K10: 1485.8 | L10: =K10/K9-1 -> -0.040893393 | N10: =N9+7 -> 45193 | O10: 388.65 | P10: =O10/O9-1 -> -0.0037169956 | R10: =R9+7 -> 45193 | S10: 161.3 | T10: =S10/S9-1 -> 0.052528548 | V10: =V9+7 -> 45193 | W10: 316.05 | X10: =W10/W9-1 -> -0.015512569 | Z10: =Z9+7 -> 45193 | AA10: 19638.3 | AB10: =AA10/AA9-1 -> -0.0018272615 | AD10: =WACC!B14 -> Indigo Paints | AF10: =SLOPE(L$9:L$111,$AB$9:$AB$111) -> 0.72419311
B11: =B10+7 -> 45200 | C11: 3195.75 | D11: =C11/C10-1 -> 0.010977365 | F11: =F10+7 -> 45200 | G11: 565.2 | H11: =G11/G10-1 -> -0.0065037792 | J11: =J10+7 -> 45200 | K11: 1506.45 | L11: =K11/K10-1 -> 0.013898237 | N11: =N10+7 -> 45200 | O11: 387.3 | P11: =O11/O10-1 -> -0.0034735623 | R11: =R10+7 -> 45200 | S11: 164 | T11: =S11/S10-1 -> 0.016738996 | V11: =V10+7 -> 45200 | W11: 322.37 | X11: =W11/W10-1 -> 0.019996836 | Z11: =Z10+7 -> 45200 | AA11: 19653.5 | AB11: =AA11/AA10-1 -> 0.00077399775 | AD11: =WACC!B15 -> Sirca Paints | AF11: =SLOPE(P$9:P$111,$AB$9:$AB$111) -> 0.90098808
B12: =B11+7 -> 45207 | C12: 3148.8 | D12: =C12/C11-1 -> -0.014691387 | F12: =F11+7 -> 45207 | G12: 568.1 | H12: =G12/G11-1 -> 0.0051309271 | J12: =J11+7 -> 45207 | K12: 1455.4 | L12: =K12/K11-1 -> -0.033887617 | N12: =N11+7 -> 45207 | O12: 386.65 | P12: =O12/O11-1 -> -0.0016782856 | R12: =R11+7 -> 45207 | S12: 192.45 | T12: =S12/S11-1 -> 0.17347561 | V12: =V11+7 -> 45207 | W12: 321.47 | X12: =W12/W11-1 -> -0.0027918231 | Z12: =Z11+7 -> 45207 | AA12: 19751.05 | AB12: =AA12/AA11-1 -> 0.0049634925 | AD12: =WACC!B16 -> Shalimar Paints | AF12: =SLOPE(T$9:T$111,$AB$9:$AB$111) -> 0.69537713
B13: =B12+7 -> 45214 | C13: 3105.85 | D13: =C13/C12-1 -> -0.013640117 | F13: =F12+7 -> 45214 | G13: 584.2 | H13: =G13/G12-1 -> 0.028340081 | J13: =J12+7 -> 45214 | K13: 1458.6 | L13: =K13/K12-1 -> 0.0021987083 | N13: =N12+7 -> 45214 | O13: 371.15 | P13: =O13/O12-1 -> -0.040087935 | R13: =R12+7 -> 45214 | S13: 186.15 | T13: =S13/S12-1 -> -0.032735776 | V13: =V12+7 -> 45214 | W13: 319.83 | X13: =W13/W12-1 -> -0.0051015647 | Z13: =Z12+7 -> 45214 | AA13: 19542.65 | AB13: =AA13/AA12-1 -> -0.010551338 | AD13: =WACC!B17 -> Kansai Nerolac Paints | AF13: =SLOPE(X$9:X$111,$AB$9:$AB$111) -> 0.80537586
B14: =B13+7 -> 45221 | C14: 2955.15 | D14: =C14/C13-1 -> -0.048521339 | F14: =F13+7 -> 45221 | G14: 535.35 | H14: =G14/G13-1 -> -0.083618624 | J14: =J13+7 -> 45221 | K14: 1411.8 | L14: =K14/K13-1 -> -0.032085561 | N14: =N13+7 -> 45221 | O14: 368.3 | P14: =O14/O13-1 -> -0.0076788361 | R14: =R13+7 -> 45221 | S14: 184.75 | T14: =S14/S13-1 -> -0.0075208165 | V14: =V13+7 -> 45221 | W14: 312.17 | X14: =W14/W13-1 -> -0.023950224 | Z14: =Z13+7 -> 45221 | AA14: 19047.25 | AB14: =AA14/AA13-1 -> -0.025349684
B15: =B14+7 -> 45228 | C15: 2977.85 | D15: =C15/C14-1 -> 0.0076815052 | F15: =F14+7 -> 45228 | G15: 553.25 | H15: =G15/G14-1 -> 0.03343607 | J15: =J14+7 -> 45228 | K15: 1464.1 | L15: =K15/K14-1 -> 0.037044907 | N15: =N14+7 -> 45228 | O15: 369 | P15: =O15/O14-1 -> 0.0019006245 | R15: =R14+7 -> 45228 | S15: 180.45 | T15: =S15/S14-1 -> -0.023274696 | V15: =V14+7 -> 45228 | W15: 303.65 | X15: =W15/W14-1 -> -0.027292821 | Z15: =Z14+7 -> 45228 | AA15: 19230.6 | AB15: =AA15/AA14-1 -> 0.0096260615 | AD15: Peer Comps Beta Median | AF15: =MEDIAN(AF9:AF13) -> 0.80537586
B16: =B15+7 -> 45235 | C16: 3076.45 | D16: =C16/C15-1 -> 0.033111137 | F16: =F15+7 -> 45235 | G16: 578.25 | H16: =G16/G15-1 -> 0.045187528 | J16: =J15+7 -> 45235 | K16: 1502.95 | L16: =K16/K15-1 -> 0.026535073 | N16: =N15+7 -> 45235 | O16: 375.55 | P16: =O16/O15-1 -> 0.017750678 | R16: =R15+7 -> 45235 | S16: 173.4 | T16: =S16/S15-1 -> -0.039068994 | V16: =V15+7 -> 45235 | W16: 303.05 | X16: =W16/W15-1 -> -0.0019759592 | Z16: =Z15+7 -> 45235 | AA16: 19425.35 | AB16: =AA16/AA15-1 -> 0.010127089
B17: =B16+7 -> 45242 | C17: 3168.9 | D17: =C17/C16-1 -> 0.03005087 | F17: =F16+7 -> 45242 | G17: 587.8 | H17: =G17/G16-1 -> 0.016515348 | J17: =J16+7 -> 45242 | K17: 1539.65 | L17: =K17/K16-1 -> 0.024418643 | N17: =N16+7 -> 45242 | O17: 380.8 | P17: =O17/O16-1 -> 0.013979497 | R17: =R16+7 -> 45242 | S17: 178.65 | T17: =S17/S16-1 -> 0.030276817 | V17: =V16+7 -> 45242 | W17: 323.96 | X17: =W17/W16-1 -> 0.068998515 | Z17: =Z16+7 -> 45242 | AA17: 19731.8 | AB17: =AA17/AA16-1 -> 0.015775778
B18: =B17+7 -> 45249 | C18: 3136.15 | D18: =C18/C17-1 -> -0.010334816 | F18: =F17+7 -> 45249 | G18: 573.2 | H18: =G18/G17-1 -> -0.02483838 | J18: =J17+7 -> 45249 | K18: 1482.5 | L18: =K18/K17-1 -> -0.037118826 | N18: =N17+7 -> 45249 | O18: 370.1 | P18: =O18/O17-1 -> -0.028098739 | R18: =R17+7 -> 45249 | S18: 170.25 | T18: =S18/S17-1 -> -0.047019312 | V18: =V17+7 -> 45249 | W18: 318.93 | X18: =W18/W17-1 -> -0.015526608 | Z18: =Z17+7 -> 45249 | AA18: 19794.7 | AB18: =AA18/AA17-1 -> 0.0031877477 | AD18: Beta Drifting
B19: =B18+7 -> 45256 | C19: 3173.4 | D19: =C19/C18-1 -> 0.011877621 | F19: =F18+7 -> 45256 | G19: 586.05 | H19: =G19/G18-1 -> 0.022418004 | J19: =J18+7 -> 45256 | K19: 1497.75 | L19: =K19/K18-1 -> 0.010286678 | N19: =N18+7 -> 45256 | O19: 382.65 | P19: =O19/O18-1 -> 0.033909754 | R19: =R18+7 -> 45256 | S19: 198.7 | T19: =S19/S18-1 -> 0.1671072 | V19: =V18+7 -> 45256 | W19: 318.64 | X19: =W19/W18-1 -> -0.00090929044 | Z19: =Z18+7 -> 45256 | AA19: 20267.9 | AB19: =AA19/AA18-1 -> 0.023905389 | AD19: Levered Raw Beta | AF19: =AF8 -> 0.81569883
B20: =B19+7 -> 45263 | C20: 3232 | D20: =C20/C19-1 -> 0.018465999 | F20: =F19+7 -> 45263 | G20: 578.75 | H20: =G20/G19-1 -> -0.012456275 | J20: =J19+7 -> 45263 | K20: 1489 | L20: =K20/K19-1 -> -0.0058420965 | N20: =N19+7 -> 45263 | O20: 392.2 | P20: =O20/O19-1 -> 0.024957533 | R20: =R19+7 -> 45263 | S20: 181.8 | T20: =S20/S19-1 -> -0.085052843 | V20: =V19+7 -> 45263 | W20: 328.89 | X20: =W20/W19-1 -> 0.032167964 | Z20: =Z19+7 -> 45263 | AA20: 20969.4 | AB20: =AA20/AA19-1 -> 0.034611381 | AD20: Beta Weight | AF20: 0.75
B21: =B20+7 -> 45270 | C21: 3313.9 | D21: =C21/C20-1 -> 0.025340347 | F21: =F20+7 -> 45270 | G21: 585.35 | H21: =G21/G20-1 -> 0.011403888 | J21: =J20+7 -> 45270 | K21: 1478.9 | L21: =K21/K20-1 -> -0.0067830759 | N21: =N20+7 -> 45270 | O21: 390.4 | P21: =O21/O20-1 -> -0.0045894952 | R21: =R20+7 -> 45270 | S21: 181.9 | T21: =S21/S20-1 -> 0.00055005501 | V21: =V20+7 -> 45270 | W21: 331.43 | X21: =W21/W20-1 -> 0.0077229469 | Z21: =Z20+7 -> 45270 | AA21: 21456.65 | AB21: =AA21/AA20-1 -> 0.023236239
B22: =B21+7 -> 45277 | C22: 3341.3 | D22: =C22/C21-1 -> 0.0082682036 | F22: =F21+7 -> 45277 | G22: 582.55 | H22: =G22/G21-1 -> -0.0047834629 | J22: =J21+7 -> 45277 | K22: 1465.6 | L22: =K22/K21-1 -> -0.0089931706 | N22: =N21+7 -> 45277 | O22: 399.35 | P22: =O22/O21-1 -> 0.022925205 | R22: =R21+7 -> 45277 | S22: 181.4 | T22: =S22/S21-1 -> -0.0027487631 | V22: =V21+7 -> 45277 | W22: 321.03 | X22: =W22/W21-1 -> -0.031379175 | Z22: =Z21+7 -> 45277 | AA22: 21349.4 | AB22: =AA22/AA21-1 -> -0.0049984504 | AD22: Market Beta | AF22: 1
B23: =B22+7 -> 45284 | C23: 3402.4 | D23: =C23/C22-1 -> 0.018286296 | F23: =F22+7 -> 45284 | G23: 604.45 | H23: =G23/G22-1 -> 0.03759334 | J23: =J22+7 -> 45284 | K23: 1490.5 | L23: =K23/K22-1 -> 0.016989629 | N23: =N22+7 -> 45284 | O23: 409.85 | P23: =O23/O22-1 -> 0.026292726 | R23: =R22+7 -> 45284 | S23: 177.7 | T23: =S23/S22-1 -> -0.020396913 | V23: =V22+7 -> 45284 | W23: 331.78 | X23: =W23/W22-1 -> 0.033485967 | Z23: =Z22+7 -> 45284 | AA23: 21731.4 | AB23: =AA23/AA22-1 -> 0.017892775 | AD23: Market Beta Weight | AF23: =1-AF20 -> 0.25
B24: =B23+7 -> 45291 | C24: 3355.55 | D24: =C24/C23-1 -> -0.013769692 | F24: =F23+7 -> 45291 | G24: 595.9 | H24: =G24/G23-1 -> -0.014145091 | J24: =J23+7 -> 45291 | K24: 1498.75 | L24: =K24/K23-1 -> 0.0055350554 | N24: =N23+7 -> 45291 | O24: 427.8 | P24: =O24/O23-1 -> 0.043796511 | R24: =R23+7 -> 45291 | S24: 184.2 | T24: =S24/S23-1 -> 0.036578503 | V24: =V23+7 -> 45291 | W24: 335.21 | X24: =W24/W23-1 -> 0.010338176 | Z24: =Z23+7 -> 45291 | AA24: 21710.8 | AB24: =AA24/AA23-1 -> -0.00094793709
B25: =B24+7 -> 45298 | C25: 3277.8 | D25: =C25/C24-1 -> -0.023170568 | F25: =F24+7 -> 45298 | G25: 596.1 | H25: =G25/G24-1 -> 0.00033562678 | J25: =J24+7 -> 45298 | K25: 1484.55 | L25: =K25/K24-1 -> -0.0094745621 | N25: =N24+7 -> 45298 | O25: 424.9 | P25: =O25/O24-1 -> -0.0067788686 | R25: =R24+7 -> 45298 | S25: 180.55 | T25: =S25/S24-1 -> -0.019815418 | V25: =V24+7 -> 45298 | W25: 338.8 | X25: =W25/W24-1 -> 0.010709704 | Z25: =Z24+7 -> 45298 | AA25: 21894.55 | AB25: =AA25/AA24-1 -> 0.0084635297 | AD25: Adjusted Beta | AF25: =(AF19*AF20)+(AF22*AF23) -> 0.86177412
B26: =B25+7 -> 45305 | C26: 3165.85 | D26: =C26/C25-1 -> -0.034154006 | F26: =F25+7 -> 45305 | G26: 579.55 | H26: =G26/G25-1 -> -0.027763798 | J26: =J25+7 -> 45305 | K26: 1469.25 | L26: =K26/K25-1 -> -0.010306153 | N26: =N25+7 -> 45305 | O26: 409 | P26: =O26/O25-1 -> -0.03742057 | R26: =R25+7 -> 45305 | S26: 217.75 | T26: =S26/S25-1 -> 0.20603711 | V26: =V25+7 -> 45305 | W26: 342.78 | X26: =W26/W25-1 -> 0.011747344 | Z26: =Z25+7 -> 45305 | AA26: 21622.4 | AB26: =AA26/AA25-1 -> -0.012430034
B27: =B26+7 -> 45312 | C27: 2949.2 | D27: =C27/C26-1 -> -0.068433438 | F27: =F26+7 -> 45312 | G27: 554.1 | H27: =G27/G26-1 -> -0.043913381 | J27: =J26+7 -> 45312 | K27: 1450 | L27: =K27/K26-1 -> -0.013101923 | N27: =N26+7 -> 45312 | O27: 387.3 | P27: =O27/O26-1 -> -0.053056235 | R27: =R26+7 -> 45312 | S27: 202.35 | T27: =S27/S26-1 -> -0.070723307 | V27: =V26+7 -> 45312 | W27: 331.28 | X27: =W27/W26-1 -> -0.033549215 | Z27: =Z26+7 -> 45312 | AA27: 21352.6 | AB27: =AA27/AA26-1 -> -0.012477801
B28: =B27+7 -> 45319 | C28: 2936.3 | D28: =C28/C27-1 -> -0.0043740675 | F28: =F27+7 -> 45319 | G28: 569.85 | H28: =G28/G27-1 -> 0.028424472 | J28: =J27+7 -> 45319 | K28: 1418.9 | L28: =K28/K27-1 -> -0.021448276 | N28: =N27+7 -> 45319 | O28: 377.85 | P28: =O28/O27-1 -> -0.02439969 | R28: =R27+7 -> 45319 | S28: 194 | T28: =S28/S27-1 -> -0.041265135 | V28: =V27+7 -> 45319 | W28: 339 | X28: =W28/W27-1 -> 0.02330355 | Z28: =Z27+7 -> 45319 | AA28: 21853.8 | AB28: =AA28/AA27-1 -> 0.023472551
B29: =B28+7 -> 45326 | C29: 2951.65 | D29: =C29/C28-1 -> 0.0052276675 | F29: =F28+7 -> 45326 | G29: 554.05 | H29: =G29/G28-1 -> -0.027726595 | J29: =J28+7 -> 45326 | K29: 1423.3 | L29: =K29/K28-1 -> 0.0031009937 | N29: =N28+7 -> 45326 | O29: 376.7 | P29: =O29/O28-1 -> -0.0030435358 | R29: =R28+7 -> 45326 | S29: 199.95 | T29: =S29/S28-1 -> 0.030670103 | V29: =V28+7 -> 45326 | W29: 315.35 | X29: =W29/W28-1 -> -0.069764012 | Z29: =Z28+7 -> 45326 | AA29: 21782.5 | AB29: =AA29/AA28-1 -> -0.0032625905
B30: =B29+7 -> 45333 | C30: 3007.9 | D30: =C30/C29-1 -> 0.019057138 | F30: =F29+7 -> 45333 | G30: 562.7 | H30: =G30/G29-1 -> 0.015612309 | J30: =J29+7 -> 45333 | K30: 1494.7 | L30: =K30/K29-1 -> 0.050165109 | N30: =N29+7 -> 45333 | O30: 369.25 | P30: =O30/O29-1 -> -0.019777011 | R30: =R29+7 -> 45333 | S30: 196.5 | T30: =S30/S29-1 -> -0.017254314 | V30: =V29+7 -> 45333 | W30: 303.05 | X30: =W30/W29-1 -> -0.039004281 | Z30: =Z29+7 -> 45333 | AA30: 22040.7 | AB30: =AA30/AA29-1 -> 0.011853552
B31: =B30+7 -> 45340 | C31: 2985.95 | D31: =C31/C30-1 -> -0.00729745 | F31: =F30+7 -> 45340 | G31: 571.8 | H31: =G31/G30-1 -> 0.016172028 | J31: =J30+7 -> 45340 | K31: 1443.5 | L31: =K31/K30-1 -> -0.034254365 | N31: =N30+7 -> 45340 | O31: 364.6 | P31: =O31/O30-1 -> -0.012593094 | R31: =R30+7 -> 45340 | S31: 195.6 | T31: =S31/S30-1 -> -0.0045801527 | V31: =V30+7 -> 45340 | W31: 300.62 | X31: =W31/W30-1 -> -0.0080184788 | Z31: =Z30+7 -> 45340 | AA31: 22212.7 | AB31: =AA31/AA30-1 -> 0.0078037449
B32: =B31+7 -> 45347 | C32: 2831.75 | D32: =C32/C31-1 -> -0.051641856 | F32: =F31+7 -> 45347 | G32: 589.05 | H32: =G32/G31-1 -> 0.030167891 | J32: =J31+7 -> 45347 | K32: 1400.95 | L32: =K32/K31-1 -> -0.029476966 | N32: =N31+7 -> 45347 | O32: 347.65 | P32: =O32/O31-1 -> -0.046489303 | R32: =R31+7 -> 45347 | S32: 172.25 | T32: =S32/S31-1 -> -0.11937628 | V32: =V31+7 -> 45347 | W32: 288.77 | X32: =W32/W31-1 -> -0.039418535 | Z32: =Z31+7 -> 45347 | AA32: 22338.75 | AB32: =AA32/AA31-1 -> 0.0056746816
B33: =B32+7 -> 45354 | C33: 2870.55 | D33: =C33/C32-1 -> 0.013701775 | F33: =F32+7 -> 45354 | G33: 573.25 | H33: =G33/G32-1 -> -0.02682285 | J33: =J32+7 -> 45354 | K33: 1363.55 | L33: =K33/K32-1 -> -0.02669617 | N33: =N32+7 -> 45354 | O33: 334.5 | P33: =O33/O32-1 -> -0.037825399 | R33: =R32+7 -> 45354 | S33: 180.4 | T33: =S33/S32-1 -> 0.047314949 | V33: =V32+7 -> 45354 | W33: 282.8 | X33: =W33/W32-1 -> -0.020673893 | Z33: =Z32+7 -> 45354 | AA33: 22493.55 | AB33: =AA33/AA32-1 -> 0.0069296626
B34: =B33+7 -> 45361 | C34: 2867.55 | D34: =C34/C33-1 -> -0.0010450959 | F34: =F33+7 -> 45361 | G34: 557.9 | H34: =G34/G33-1 -> -0.026777148 | J34: =J33+7 -> 45361 | K34: 1341.45 | L34: =K34/K33-1 -> -0.016207693 | N34: =N33+7 -> 45361 | O34: 302.5 | P34: =O34/O33-1 -> -0.095665172 | R34: =R33+7 -> 45361 | S34: 166.4 | T34: =S34/S33-1 -> -0.077605322 | V34: =V33+7 -> 45361 | W34: 270.15 | X34: =W34/W33-1 -> -0.044731259 | Z34: =Z33+7 -> 45361 | AA34: 22023.35 | AB34: =AA34/AA33-1 -> -0.02090377
B35: =B34+7 -> 45368 | C35: 2841.5 | D35: =C35/C34-1 -> -0.00908441 | F35: =F34+7 -> 45368 | G35: 558.05 | H35: =G35/G34-1 -> 0.00026886539 | J35: =J34+7 -> 45368 | K35: 1321.2 | L35: =K35/K34-1 -> -0.015095606 | N35: =N34+7 -> 45368 | O35: 299.05 | P35: =O35/O34-1 -> -0.011404959 | R35: =R34+7 -> 45368 | S35: 165 | T35: =S35/S34-1 -> -0.0084134615 | V35: =V34+7 -> 45368 | W35: 267.46 | X35: =W35/W34-1 -> -0.0099574311 | Z35: =Z34+7 -> 45368 | AA35: 22096.75 | AB35: =AA35/AA34-1 -> 0.0033328263
B36: =B35+7 -> 45375 | C36: 2846.75 | D36: =C36/C35-1 -> 0.0018476157 | F36: =F35+7 -> 45375 | G36: 572.9 | H36: =G36/G35-1 -> 0.026610519 | J36: =J35+7 -> 45375 | K36: 1256.6 | L36: =K36/K35-1 -> -0.048894944 | N36: =N35+7 -> 45375 | O36: 284.65 | P36: =O36/O35-1 -> -0.048152483 | R36: =R35+7 -> 45375 | S36: 166.1 | T36: =S36/S35-1 -> 0.0066666667 | V36: =V35+7 -> 45375 | W36: 261.09 | X36: =W36/W35-1 -> -0.023816645 | Z36: =Z35+7 -> 45375 | AA36: 22326.9 | AB36: =AA36/AA35-1 -> 0.010415559
B37: =B36+7 -> 45382 | C37: 2883.45 | D37: =C37/C36-1 -> 0.012891894 | F37: =F36+7 -> 45382 | G37: 561.8 | H37: =G37/G36-1 -> -0.019375109 | J37: =J36+7 -> 45382 | K37: 1394.65 | L37: =K37/K36-1 -> 0.10985994 | N37: =N36+7 -> 45382 | O37: 352.2 | P37: =O37/O36-1 -> 0.23730898 | R37: =R36+7 -> 45382 | S37: 176 | T37: =S37/S36-1 -> 0.059602649 | V37: =V36+7 -> 45382 | W37: 283.89 | X37: =W37/W36-1 -> 0.087326209 | Z37: =Z36+7 -> 45382 | AA37: 22513.7 | AB37: =AA37/AA36-1 -> 0.0083665892
... B111: =B110+7 -> 45900 | C111: 2579.9 | D111: =C111/C110-1 -> 0.024338918 | F111: =F110+7 -> 45900 | G111: 538.95 | H111: =G111/G110-1 -> 0.012112676 | J111: =J110+7 -> 45900 | K111: 1145.4 | L111: =K111/K110-1 -> 0.041556788 | N111: =N110+7 -> 45900 | O111: 467.75 | P111: =O111/O110-1 -> 0.01080497 | R111: =R110+7 -> 45900 | S111: 72.58 | T111: =S111/S110-1 -> 0.011849993 | V111: =V110+7 -> 45900 | W111: 242.88 | X111: =W111/W110-1 -> 0.012042168 | Z111: =Z110+7 -> 45900 | AA111: 24741 | AB111: =AA111/AA110-1 -> 0.012860848

Sheet Market Returns
B2: Nifty-50
B3: Annually Returns
B5: Year | C5: Annual
B6: 2000 | C6: -0.1465 | E6: Average Return | G6: =AVERAGE(C6:C30) -> 0.153348
B7: 2001 | C7: -0.1618 | E7: Dividend Yield | G7: 1.38% 1
B8: 2002 | C8: 0.0325 | E8: Total Market Return | G8: =SUM(G6:G7) -> 0.153348
B9: 2003 | C9: 0.719
B10: 2004 | C10: 0.1068
B11: 2005 | C11: 0.3634
B12: 2006 | C12: 0.3983
B13: 2007 | C13: 0.5477
B14: 2008 | C14: -0.5179
B15: 2009 | C15: 0.7576
B16: 2010 | C16: 0.1795
B17: 2011 | C17: -0.2462
B18: 2012 | C18: 0.277
B19: 2013 | C19: 0.0676
B20: 2014 | C20: 0.3139
... B30: 2024 | C30: 0.0875

Sheet FINANCIALS ->

Sheet FS
B4: ="Financial Statements - " & 'Profit & Loss'!A1 -> Financial Statements - ASIAN PAINTS LTD
B5: Years | D5: ='Profit & Loss'!B3 -> 42460 | E5: ='Profit & Loss'!C3 -> 42825 | F5: ='Profit & Loss'!D3 -> 43190 | G5: ='Profit & Loss'!E3 -> 43555 | H5: ='Profit & Loss'!F3 -> 43921 | I5: ='Profit & Loss'!G3 -> 44286 | J5: ='Profit & Loss'!H3 -> 44651 | K5: ='Profit & Loss'!I3 -> 45016 | ... M5: ='Profit & Loss'!K3 -> 45747
A7: # | B7: ="Income Statement - " &'Data Sheet'!$B$1 -> Income Statement - ASIAN PAINTS LTD
B9: Sales | D9: =IFERROR('Profit & Loss'!B4,0) -> 14271.49 | E9: =IFERROR('Profit & Loss'!C4,0) -> 15061.99 | F9: =IFERROR('Profit & Loss'!D4,0) -> 16824.55 | G9: =IFERROR('Profit & Loss'!E4,0) -> 19240.13 | H9: =IFERROR('Profit & Loss'!F4,0) -> 20211.25 | I9: =IFERROR('Profit & Loss'!G4,0) -> 21712.79 | J9: =IFERROR('Profit & Loss'!H4,0) -> 29101.28 | K9: =IFERROR('Profit & Loss'!I4,0) -> 34488.59 | ... M9: =IFERROR('Profit & Loss'!K4,0) -> 33905.62
B10: Sales Growth | D10: - | E10: =IFERROR(E9/D9-1,0) -> 0.055390152 | F10: =IFERROR(F9/E9-1,0) -> 0.11702039 | G10: =IFERROR(G9/F9-1,0) -> 0.14357472 | H10: =IFERROR(H9/G9-1,0) -> 0.050473671 | I10: =IFERROR(I9/H9-1,0) -> 0.074292288 | J10: =IFERROR(J9/I9-1,0) -> 0.34028285 | K10: =IFERROR(K9/J9-1,0) -> 0.18512278 | L10: =IFERROR(L9/K9-1,0) -> 0.029173127 | M10: =IFERROR(M9/L9-1,0) -> -0.044770308
B12: COGS | D12: =IFERROR(SUM('Data Sheet'!B18,1*('Data Sheet'!B19),'Data Sheet'!B21),0) -> 7905.72 | E12: =IFERROR(SUM('Data Sheet'!C18,-1*('Data Sheet'!C19),'Data Sheet'!C20,'Data Sheet'!C21),0) -> 8692.77 | F12: =IFERROR(SUM('Data Sheet'!D18,-1*('Data Sheet'!D19),'Data Sheet'!D20,'Data Sheet'!D21),0) -> 10072.28 | G12: =IFERROR(SUM('Data Sheet'!E18,-1*('Data Sheet'!E19),'Data Sheet'!E20,'Data Sheet'!E21),0) -> 11663.12 | H12: =IFERROR(SUM('Data Sheet'!F18,-1*('Data Sheet'!F19),'Data Sheet'!F20,'Data Sheet'!F21),0) -> 11786.75 | I12: =IFERROR(SUM('Data Sheet'!G18,-1*('Data Sheet'!G19),'Data Sheet'!G20,'Data Sheet'!G21),0) -> 12487.46 | J12: =IFERROR(SUM('Data Sheet'!H18,-1*('Data Sheet'!H19),'Data Sheet'!H20,'Data Sheet'!H21),0) -> 18795.96 | K12: =IFERROR(SUM('Data Sheet'!I18,-1*('Data Sheet'!I19),'Data Sheet'!I20,'Data Sheet'!I21),0) -> 21730.29 | L12: =IFERROR(SUM('Data Sheet'!J18,-1*('Data Sheet'!J19),'Data Sheet'!J20,'Data Sheet'!J21),0) -> 20675.07 | M12: =IFERROR(SUM('Data Sheet'!K18,-1*('Data Sheet'!K19),'Data Sheet'!K20,'Data Sheet'!K21),0) -> 20135.49
B13: COGS as % of Sales | D13: =IFERROR(D12/D9,0) -> 0.55395197 | E13: =IFERROR(E12/E9,0) -> 0.5771329 | F13: =IFERROR(F12/F9,0) -> 0.59866564 | G13: =IFERROR(G12/G9,0) -> 0.60618717 | H13: =IFERROR(H12/H9,0) -> 0.58317769 | I13: =IFERROR(I12/I9,0) -> 0.57512001 | J13: =IFERROR(J12/J9,0) -> 0.64588087 | K13: =IFERROR(K12/K9,0) -> 0.63007186 | ... M13: =IFERROR(M12/M9,0) -> 0.5938688
B15: Gross Profit | D15: =IFERROR(D9-D12,0) -> 6365.77 | E15: =IFERROR(E9-E12,0) -> 6369.22 | F15: =IFERROR(F9-F12,0) -> 6752.27 | G15: =IFERROR(G9-G12,0) -> 7577.01 | H15: =IFERROR(H9-H12,0) -> 8424.5 | I15: =IFERROR(I9-I12,0) -> 9225.33 | J15: =IFERROR(J9-J12,0) -> 10305.32 | K15: =IFERROR(K9-K12,0) -> 12758.3 | ... M15: =IFERROR(M9-M12,0) -> 13770.13
B16: Gross Margin | D16: =IFERROR(D15/D9,0) -> 0.44604803 | E16: =IFERROR(E15/E9,0) -> 0.4228671 | F16: =IFERROR(F15/F9,0) -> 0.40133436 | G16: =IFERROR(G15/G9,0) -> 0.39381283 | H16: =IFERROR(H15/H9,0) -> 0.41682231 | I16: =IFERROR(I15/I9,0) -> 0.42487999 | J16: =IFERROR(J15/J9,0) -> 0.35411913 | K16: =IFERROR(K15/K9,0) -> 0.36992814 | ... M16: =IFERROR(M15/M9,0) -> 0.4061312
B18: S&G Expenses | D18: =IFERROR('Data Sheet'!B23-'Data Sheet'!B25,0) -> 3698.91 | E18: =IFERROR('Data Sheet'!C23-'Data Sheet'!C25,0) -> 4026.14 | F18: =IFERROR('Data Sheet'!D23-'Data Sheet'!D25,0) -> 1918.51 | G18: =IFERROR('Data Sheet'!E23-'Data Sheet'!E25,0) -> 2093.1 | H18: =IFERROR('Data Sheet'!F23-'Data Sheet'!F25,0) -> 1956.46 | I18: =IFERROR('Data Sheet'!G23-'Data Sheet'!G25,0) -> 1914.04 | J18: =IFERROR('Data Sheet'!H23-'Data Sheet'!H25,0) -> 2646.1 | K18: =IFERROR('Data Sheet'!I23-'Data Sheet'!I25,0) -> 3069.38 | ... M18: =IFERROR('Data Sheet'!K23-'Data Sheet'!K25,0) -> 3524.72
B19: S&A Expenses as % of Sales | D19: =IFERROR(D18/D9,0) -> 0.25918177 | E19: =IFERROR(E18/E9,0) -> 0.26730465 | F19: =IFERROR(F18/F9,0) -> 0.11403039 | G19: =IFERROR(G18/G9,0) -> 0.10878825 | H19: =IFERROR(H18/H9,0) -> 0.096800544 | I19: =IFERROR(I18/I9,0) -> 0.088152651 | J19: =IFERROR(J18/J9,0) -> 0.090927272 | K19: =IFERROR(K18/K9,0) -> 0.08899697 | ... M19: =IFERROR(M18/M9,0) -> 0.10395681
B21: EBITDA | D21: =IFERROR('Profit & Loss'!B6,0) -> 2725.04 | E21: =IFERROR('Profit & Loss'!C6,0) -> 2993.76 | F21: =IFERROR('Profit & Loss'!D6,0) -> 3204.01 | G21: =IFERROR('Profit & Loss'!E6,0) -> 3764.94 | H21: =IFERROR('Profit & Loss'!F6,0) -> 4156.82 | I21: =IFERROR('Profit & Loss'!G6,0) -> 4855.6 | J21: =IFERROR('Profit & Loss'!H6,0) -> 4803.61 | K21: =IFERROR('Profit & Loss'!I6,0) -> 6259.84 | ... M21: =IFERROR('Profit & Loss'!K6,0) -> 6006.21
B22: EBITDA Margin | D22: =IFERROR(D21/D9,0) -> 0.19094292 | E22: =IFERROR(E21/E9,0) -> 0.19876258 | F22: =IFERROR(F21/F9,0) -> 0.19043659 | G22: =IFERROR(G21/G9,0) -> 0.19568163 | H22: =IFERROR(H21/H9,0) -> 0.20566863 | I22: =IFERROR(I21/I9,0) -> 0.22362856 | J22: =IFERROR(J21/J9,0) -> 0.16506525 | K22: =IFERROR(K21/K9,0) -> 0.18150467 | ... M22: =IFERROR(M21/M9,0) -> 0.17714497
B24: Depriciation | D24: ='Profit & Loss'!B8 -> 275.58 | E24: ='Profit & Loss'!C8 -> 334.79 | F24: ='Profit & Loss'!D8 -> 360.47 | G24: ='Profit & Loss'!E8 -> 622.14 | H24: ='Profit & Loss'!F8 -> 780.5 | I24: ='Profit & Loss'!G8 -> 791.27 | J24: ='Profit & Loss'!H8 -> 816.36 | K24: ='Profit & Loss'!I8 -> 858.02 | ... M24: ='Profit & Loss'!K8 -> 1026.34
B25: Depriciation as % of sales | D25: =D24/D9 -> 0.019309827 | E25: =E24/E9 -> 0.022227475 | F25: =F24/F9 -> 0.021425239 | G25: =G24/G9 -> 0.03233554 | H25: =H24/H9 -> 0.038617107 | I25: =I24/I9 -> 0.036442576 | J25: =J24/J9 -> 0.028052374 | K25: =K24/K9 -> 0.024878373 | ... M25: =M24/M9 -> 0.030270498
B27: EBIT | D27: =IFERROR(SUM('Profit & Loss'!B6:B7),0)-'Profit & Loss'!B8 -> 2662.85 | E27: =IFERROR(SUM('Profit & Loss'!C6:C7),0)-'Profit & Loss'!C8 -> 2996.87 | F27: =IFERROR(SUM('Profit & Loss'!D6:D7),0)-'Profit & Loss'!D8 -> 3179.95 | G27: =IFERROR(SUM('Profit & Loss'!E6:E7),0)-'Profit & Loss'!E8 -> 3416.57 | H27: =IFERROR(SUM('Profit & Loss'!F6:F7),0)-'Profit & Loss'!F8 -> 3731.37 | I27: =IFERROR(SUM('Profit & Loss'!G6:G7),0)-'Profit & Loss'!G8 -> 4395.98 | J27: =IFERROR(SUM('Profit & Loss'!H6:H7),0)-'Profit & Loss'!H8 -> 4283.13 | K27: =IFERROR(SUM('Profit & Loss'!I6:I7),0)-'Profit & Loss'!I8 -> 5833.28 | ... M27: =IFERROR(SUM('Profit & Loss'!K6:K7),0)-'Profit & Loss'!K8 -> 5330.09
B28: EBIT Margin | D28: =IFERROR(D27/D9,0) -> 0.18658528 | E28: =IFERROR(E27/E9,0) -> 0.19896906 | F28: =IFERROR(F27/F9,0) -> 0.18900654 | G28: =IFERROR(G27/G9,0) -> 0.1775752 | H28: =IFERROR(H27/H9,0) -> 0.18461847 | I28: =IFERROR(I27/I9,0) -> 0.20246039 | J28: =IFERROR(J27/J9,0) -> 0.14718012 | K28: =IFERROR(K27/K9,0) -> 0.16913652 | ... M28: =IFERROR(M27/M9,0) -> 0.15720373
B30: Interest | D30: =IFERROR('Profit & Loss'!B9,0) -> 49 | E30: =IFERROR('Profit & Loss'!C9,0) -> 37.33 | F30: =IFERROR('Profit & Loss'!D9,0) -> 41.47 | G30: =IFERROR('Profit & Loss'!E9,0) -> 110.47 | H30: =IFERROR('Profit & Loss'!F9,0) -> 102.33 | I30: =IFERROR('Profit & Loss'!G9,0) -> 91.63 | J30: =IFERROR('Profit & Loss'!H9,0) -> 95.41 | K30: =IFERROR('Profit & Loss'!I9,0) -> 144.45 | ... M30: =IFERROR('Profit & Loss'!K9,0) -> 227.02
B31: Interest as % of Sales | D31: =IFERROR(D30/D9,0) -> 0.0034334187 | E31: =IFERROR(E30/E9,0) -> 0.0024784242 | F31: =IFERROR(F30/F9,0) -> 0.0024648505 | G31: =IFERROR(G30/G9,0) -> 0.0057416452 | H31: =IFERROR(H30/H9,0) -> 0.0050630218 | I31: =IFERROR(I30/I9,0) -> 0.0042200933 | J31: =IFERROR(J30/J9,0) -> 0.0032785499 | K31: =IFERROR(K30/K9,0) -> 0.0041883417 | ... M31: =IFERROR(M30/M9,0) -> 0.0066956451
B33: EBT | D33: ='Profit & Loss'!B10 -> 2613.85 | E33: =IFERROR('Profit & Loss'!C10,0) -> 2959.54 | F33: =IFERROR('Profit & Loss'!D10,0) -> 3138.48 | G33: =IFERROR('Profit & Loss'!E10,0) -> 3306.1 | H33: =IFERROR('Profit & Loss'!F10,0) -> 3629.04 | I33: =IFERROR('Profit & Loss'!G10,0) -> 4304.35 | J33: =IFERROR('Profit & Loss'!H10,0) -> 4187.72 | K33: =IFERROR('Profit & Loss'!I10,0) -> 5688.83 | L33: =IFERROR('Profit & Loss'!J10,0) -> 7347.77 | M33: =IFERROR('Profit & Loss'!K10,0) -> 5103.07
B34: EBT Margin | D34: =IFERROR(D33/D9,0) -> 0.18315186 | E34: =IFERROR(E33/E9,0) -> 0.19649064 | F34: =IFERROR(F33/F9,0) -> 0.18654169 | G34: =IFERROR(G33/G9,0) -> 0.17183356 | H34: =IFERROR(H33/H9,0) -> 0.17955545 | I34: =IFERROR(I33/I9,0) -> 0.1982403 | J34: =IFERROR(J33/J9,0) -> 0.14390157 | K34: =IFERROR(K33/K9,0) -> 0.16494818 | ... M34: =IFERROR(M33/M9,0) -> 0.15050809
B36: Tax | D36: =IFERROR('Profit & Loss'!B11,0) -> 844.49 | E36: =IFERROR('Profit & Loss'!C11,0) -> 943.29 | F36: =IFERROR('Profit & Loss'!D11,0) -> 1040.96 | G36: =IFERROR('Profit & Loss'!E11,0) -> 1098.06 | H36: =IFERROR('Profit & Loss'!F11,0) -> 854.85 | I36: =IFERROR('Profit & Loss'!G11,0) -> 1097.6 | J36: =IFERROR('Profit & Loss'!H11,0) -> 1102.91 | K36: =IFERROR('Profit & Loss'!I11,0) -> 1493.5 | ... M36: =IFERROR('Profit & Loss'!K11,0) -> 1393.36
B37: Effective Tax Rate | D37: =IFERROR(D36/D33,0) -> 0.32308281 | E37: =IFERROR(E36/E33,0) -> 0.31872859 | F37: =IFERROR(F36/F33,0) -> 0.33167648 | G37: =IFERROR(G36/G33,0) -> 0.33213151 | H37: =IFERROR(H36/H33,0) -> 0.23555816 | I37: =IFERROR(I36/I33,0) -> 0.25499785 | J37: =IFERROR(J36/J33,0) -> 0.26336766 | K37: =IFERROR(K36/K33,0) -> 0.26253201 | ... M37: =IFERROR(M36/M33,0) -> 0.27304348
B39: Net Profit | D39: =IFERROR('Profit & Loss'!B12,0) -> 1745.16 | E39: =IFERROR('Profit & Loss'!C12,0) -> 1939.43 | F39: =IFERROR('Profit & Loss'!D12,0) -> 2038.93 | G39: =IFERROR('Profit & Loss'!E12,0) -> 2155.92 | H39: =IFERROR('Profit & Loss'!F12,0) -> 2705.17 | I39: =IFERROR('Profit & Loss'!G12,0) -> 3139.29 | J39: =IFERROR('Profit & Loss'!H12,0) -> 3030.57 | K39: =IFERROR('Profit & Loss'!I12,0) -> 4106.45 | ... M39: =IFERROR('Profit & Loss'!K12,0) -> 3667.23
B40: Profit Margin | D40: =IFERROR(D39/D9,0) -> 0.12228296 | E40: =IFERROR(E39/E9,0) -> 0.1287632 | F40: =IFERROR(F39/F9,0) -> 0.12118779 | G40: =IFERROR(G39/G9,0) -> 0.1120533 | H40: =IFERROR(H39/H9,0) -> 0.13384476 | I40: =IFERROR(I39/I9,0) -> 0.14458252 | J40: =IFERROR(J39/J9,0) -> 0.10413872 | K40: =IFERROR(K39/K9,0) -> 0.11906691 | ... M40: =IFERROR(M39/M9,0) -> 0.10815995
B42: No of Equity Shares | D42: =IFERROR('Data Sheet'!B93,0) -> 95.92 | E42: =IFERROR('Data Sheet'!C93,0) -> 95.92 | F42: =IFERROR('Data Sheet'!D93,0) -> 95.92 | G42: =IFERROR('Data Sheet'!E93,0) -> 95.92 | H42: =IFERROR('Data Sheet'!F93,0) -> 95.92 | I42: =IFERROR('Data Sheet'!G93,0) -> 95.92 | J42: =IFERROR('Data Sheet'!H93,0) -> 95.92 | K42: =IFERROR('Data Sheet'!I93,0) -> 95.92 | ... M42: =IFERROR('Data Sheet'!K93,0) -> 95.92
B44: Earnings Per Share | D44: =IFERROR('Profit & Loss'!B13,0) -> 18.193912 | E44: =IFERROR('Profit & Loss'!C13,0) -> 20.219245 | F44: =IFERROR('Profit & Loss'!D13,0) -> 21.256568 | G44: =IFERROR('Profit & Loss'!E13,0) -> 22.47623 | H44: =IFERROR('Profit & Loss'!F13,0) -> 28.202356 | I44: =IFERROR('Profit & Loss'!G13,0) -> 32.728211 | J44: =IFERROR('Profit & Loss'!H13,0) -> 31.594766 | K44: =IFERROR('Profit & Loss'!I13,0) -> 42.811197 | ... M44: =IFERROR('Profit & Loss'!K13,0) -> 38.232173
B45: EPS Growth | E45: =IFERROR(E44/D44-1,0) -> 0.11131931 | F45: =IFERROR(F44/E44-1,0) -> 0.051303734 | G45: =IFERROR(G44/F44-1,0) -> 0.057378135 | H45: =IFERROR(H44/G44-1,0) -> 0.25476363 | I45: =IFERROR(I44/H44-1,0) -> 0.1604779 | J45: =IFERROR(J44/I44-1,0) -> -0.034632035 | K45: =IFERROR(K44/J44-1,0) -> 0.35500912 | L45: =IFERROR(L44/K44-1,0) -> 0.32967161 | M45: =IFERROR(M44/L44-1,0) -> -0.32837445
B47: Divident Per Share | D47: =IFERROR('Data Sheet'!B31/FS!D42,0) -> 7.5 | E47: =IFERROR('Data Sheet'!C31/FS!E42,0) -> 10.300042 | F47: =IFERROR('Data Sheet'!D31/FS!F42,0) -> 8.6999583 | G47: =IFERROR('Data Sheet'!E31/FS!G42,0) -> 10.5 | H47: =IFERROR('Data Sheet'!F31/FS!H42,0) -> 12 | I47: =IFERROR('Data Sheet'!G31/FS!I42,0) -> 17.849979 | J47: =IFERROR('Data Sheet'!H31/FS!J42,0) -> 19.150021 | K47: =IFERROR('Data Sheet'!I31/FS!K42,0) -> 25.650021 | ... M47: =IFERROR('Data Sheet'!K31/FS!M42,0) -> 24.800042
B48: Divident Payout Ratio | D48: =IFERROR(D47/D44,0) -> 0.41222581 | E48: =IFERROR(E47/E44,0) -> 0.50941772 | F48: =IFERROR(F47/F44,0) -> 0.4092833 | G48: =IFERROR(G47/G44,0) -> 0.46716019 | H48: =IFERROR(H47/H44,0) -> 0.42549636 | I48: =IFERROR(I47/I44,0) -> 0.54540039 | J48: =IFERROR(J47/J44,0) -> 0.6061137 | K48: =IFERROR(K47/K44,0) -> 0.59914281 | ... M48: =IFERROR(M47/M44,0) -> 0.64866943
B50: Retained Earnings | D50: =IFERROR(IF(D44>D47,1-D48,0),0) -> 0.58777419 | E50: =IFERROR(IF(E44>E47,1-E48,0),0) -> 0.49058228 | F50: =IFERROR(IF(F44>F47,1-F48,0),0) -> 0.5907167 | G50: =IFERROR(IF(G44>G47,1-G48,0),0) -> 0.53283981 | H50: =IFERROR(IF(H44>H47,1-H48,0),0) -> 0.57450364 | I50: =IFERROR(IF(I44>I47,1-I48,0),0) -> 0.45459961 | J50: =IFERROR(IF(J44>J47,1-J48,0),0) -> 0.3938863 | K50: =IFERROR(IF(K44>K47,1-K48,0),0) -> 0.40085719 | ... M50: =IFERROR(IF(M44>M47,1-M48,0),0) -> 0.35133057
A53: # | B53: ="Balance Sheet - " &'Data Sheet'!$B$1 -> Balance Sheet - ASIAN PAINTS LTD
B55: Equity Share Capital | D55: =IFERROR('Balance Sheet'!B4,0) -> 95.92 | E55: =IFERROR('Balance Sheet'!C4,0) -> 95.92 | F55: =IFERROR('Balance Sheet'!D4,0) -> 95.92 | G55: =IFERROR('Balance Sheet'!E4,0) -> 95.92 | H55: =IFERROR('Balance Sheet'!F4,0) -> 95.92 | I55: =IFERROR('Balance Sheet'!G4,0) -> 95.92 | J55: =IFERROR('Balance Sheet'!H4,0) -> 95.92 | K55: =IFERROR('Balance Sheet'!I4,0) -> 95.92 | ... M55: =IFERROR('Balance Sheet'!K4,0) -> 95.92
B56: Reserves | D56: =IFERROR('Balance Sheet'!B5,0) -> 6428.9 | E56: =IFERROR('Balance Sheet'!C5,0) -> 7507.97 | F56: =IFERROR('Balance Sheet'!D5,0) -> 8314.31 | G56: =IFERROR('Balance Sheet'!E5,0) -> 9374.63 | H56: =IFERROR('Balance Sheet'!F5,0) -> 10034.24 | I56: =IFERROR('Balance Sheet'!G5,0) -> 12710.37 | J56: =IFERROR('Balance Sheet'!H5,0) -> 13715.64 | K56: =IFERROR('Balance Sheet'!I5,0) -> 15896.31 | ... M56: =IFERROR('Balance Sheet'!K5,0) -> 19303.89
B57: Borrowings | D57: =IFERROR('Balance Sheet'!B6,0) -> 323.29 | E57: =IFERROR('Balance Sheet'!C6,0) -> 560.34 | F57: =IFERROR('Balance Sheet'!D6,0) -> 533.43 | G57: =IFERROR('Balance Sheet'!E6,0) -> 1319.6 | H57: =IFERROR('Balance Sheet'!F6,0) -> 1118.5 | I57: =IFERROR('Balance Sheet'!G6,0) -> 1093.12 | J57: =IFERROR('Balance Sheet'!H6,0) -> 1586.88 | K57: =IFERROR('Balance Sheet'!I6,0) -> 1932.62 | ... M57: =IFERROR('Balance Sheet'!K6,0) -> 2290.29
B58: Other Liabilities | D58: =IFERROR('Balance Sheet'!B7,0) -> 3710.92 | E58: =IFERROR('Balance Sheet'!C7,0) -> 4240.96 | F58: =IFERROR('Balance Sheet'!D7,0) -> 4819.82 | G58: =IFERROR('Balance Sheet'!E7,0) -> 5458.69 | H58: =IFERROR('Balance Sheet'!F7,0) -> 4889.31 | I58: =IFERROR('Balance Sheet'!G7,0) -> 6455.93 | J58: =IFERROR('Balance Sheet'!H7,0) -> 7559.99 | K58: =IFERROR('Balance Sheet'!I7,0) -> 7854.48 | ... M58: =IFERROR('Balance Sheet'!K7,0) -> 8665.15
B59: Total Liabilities | D59: =IFERROR('Balance Sheet'!B8,0) -> 10559.03 | E59: =IFERROR('Balance Sheet'!C8,0) -> 12405.19 | F59: =IFERROR('Balance Sheet'!D8,0) -> 13763.48 | G59: =IFERROR('Balance Sheet'!E8,0) -> 16248.84 | H59: =IFERROR('Balance Sheet'!F8,0) -> 16137.97 | I59: =IFERROR('Balance Sheet'!G8,0) -> 20355.34 | J59: =IFERROR('Balance Sheet'!H8,0) -> 22958.43 | K59: =IFERROR('Balance Sheet'!I8,0) -> 25779.33 | ... M59: =IFERROR('Balance Sheet'!K8,0) -> 30355.25
B61: Net Block | D61: =IFERROR('Balance Sheet'!B10,0) -> 3416.35 | E61: =IFERROR('Balance Sheet'!C10,0) -> 3303.74 | F61: =IFERROR('Balance Sheet'!D10,0) -> 3732.24 | G61: =IFERROR('Balance Sheet'!E10,0) -> 6496.56 | H61: =IFERROR('Balance Sheet'!F10,0) -> 6272.31 | I61: =IFERROR('Balance Sheet'!G10,0) -> 5858.52 | J61: =IFERROR('Balance Sheet'!H10,0) -> 5519.06 | K61: =IFERROR('Balance Sheet'!I10,0) -> 5770.46 | ... M61: =IFERROR('Balance Sheet'!K10,0) -> 9220.1
B62: Capital Work in Progress | D62: =IFERROR('Balance Sheet'!B11,0) -> 106.59 | E62: =IFERROR('Balance Sheet'!C11,0) -> 257.54 | F62: =IFERROR('Balance Sheet'!D11,0) -> 1405.11 | G62: =IFERROR('Balance Sheet'!E11,0) -> 209.67 | H62: =IFERROR('Balance Sheet'!F11,0) -> 140.24 | I62: =IFERROR('Balance Sheet'!G11,0) -> 182.98 | J62: =IFERROR('Balance Sheet'!H11,0) -> 426.43 | K62: =IFERROR('Balance Sheet'!I11,0) -> 1019.59 | ... M62: =IFERROR('Balance Sheet'!K11,0) -> 1254.49
B63: Investments | D63: =IFERROR('Balance Sheet'!B12,0) -> 2712.13 | E63: =IFERROR('Balance Sheet'!C12,0) -> 2651.99 | F63: =IFERROR('Balance Sheet'!D12,0) -> 2140.7 | G63: =IFERROR('Balance Sheet'!E12,0) -> 2568.58 | H63: =IFERROR('Balance Sheet'!F12,0) -> 2018.85 | I63: =IFERROR('Balance Sheet'!G12,0) -> 4736.8 | J63: =IFERROR('Balance Sheet'!H12,0) -> 3247.53 | K63: =IFERROR('Balance Sheet'!I12,0) -> 4261.71 | ... M63: =IFERROR('Balance Sheet'!K12,0) -> 4724.75
B64: Other Assets | D64: =IFERROR('Balance Sheet'!B13-SUM('Balance Sheet'!B16:B18),0) -> 525.84 | E64: =IFERROR('Balance Sheet'!C13-SUM('Balance Sheet'!C16:C18),0) -> 167.42 | F64: =IFERROR('Balance Sheet'!D13-SUM('Balance Sheet'!D16:D18),0) -> 430.88 | G64: =IFERROR('Balance Sheet'!E13-SUM('Balance Sheet'!E16:E18),0) -> 401.5 | H64: =IFERROR('Balance Sheet'!F13-SUM('Balance Sheet'!F16:F18),0) -> -295.72 | I64: =IFERROR('Balance Sheet'!G13-SUM('Balance Sheet'!G16:G18),0) -> 55.16 | J64: =IFERROR('Balance Sheet'!H13-SUM('Balance Sheet'!H16:H18),0) -> -2464.43 | K64: =IFERROR('Balance Sheet'!I13-SUM('Balance Sheet'!I16:I18),0) -> -2993.1 | ... M64: =IFERROR('Balance Sheet'!K13-SUM('Balance Sheet'!K16:K18),0) -> -2367.77
B65: Total Non-Current Assets (A) | D65: =IFERROR(SUM(D61:D64),0) -> 6760.91 | E65: =IFERROR(SUM(E61:E64),0) -> 6380.69 | F65: =IFERROR(SUM(F61:F64),0) -> 7708.93 | G65: =IFERROR(SUM(G61:G64),0) -> 9676.31 | H65: =IFERROR(SUM(H61:H64),0) -> 8135.68 | I65: =IFERROR(SUM(I61:I64),0) -> 10833.46 | J65: =IFERROR(SUM(J61:J64),0) -> 6728.59 | K65: =IFERROR(SUM(K61:K64),0) -> 8058.66 | ... M65: =IFERROR(SUM(M61:M64),0) -> 12831.57
B67: Working Capital | D67: =IFERROR('Balance Sheet'!B16,0) -> 613.04 | E67: =IFERROR('Balance Sheet'!C16,0) -> 1950.96 | F67: =IFERROR('Balance Sheet'!D16,0) -> 1665.61 | G67: =IFERROR('Balance Sheet'!E16,0) -> 1515.34 | H67: =IFERROR('Balance Sheet'!F16,0) -> 2817.26 | I67: =IFERROR('Balance Sheet'!G16,0) -> 3121.11 | J67: =IFERROR('Balance Sheet'!H16,0) -> 6205.42 | K67: =IFERROR('Balance Sheet'!I16,0) -> 6873.09 | ... M67: =IFERROR('Balance Sheet'!K16,0) -> 6490.76
B68: Debtors | D68: =IFERROR('Balance Sheet'!B17,0) -> 1186.84 | E68: =IFERROR('Balance Sheet'!C17,0) -> 1446.6 | F68: =IFERROR('Balance Sheet'!D17,0) -> 1730.63 | G68: =IFERROR('Balance Sheet'!E17,0) -> 1907.33 | H68: =IFERROR('Balance Sheet'!F17,0) -> 1795.22 | I68: =IFERROR('Balance Sheet'!G17,0) -> 2602.17 | J68: =IFERROR('Balance Sheet'!H17,0) -> 3871.44 | K68: =IFERROR('Balance Sheet'!I17,0) -> 4636.94 | ... M68: =IFERROR('Balance Sheet'!K17,0) -> 4313.65
B69: Inventory | D69: =IFERROR('Balance Sheet'!B18,0) -> 1998.24 | E69: =IFERROR('Balance Sheet'!C18,0) -> 2626.94 | F69: =IFERROR('Balance Sheet'!D18,0) -> 2658.31 | G69: =IFERROR('Balance Sheet'!E18,0) -> 3149.86 | H69: =IFERROR('Balance Sheet'!F18,0) -> 3389.81 | I69: =IFERROR('Balance Sheet'!G18,0) -> 3798.6 | J69: =IFERROR('Balance Sheet'!H18,0) -> 6152.98 | K69: =IFERROR('Balance Sheet'!I18,0) -> 6210.64 | ... M69: =IFERROR('Balance Sheet'!K18,0) -> 6719.27
B70: Total Current Assets (B) | D70: =IFERROR(SUM(D67:D69),0) -> 3798.12 | E70: =IFERROR(SUM(E67:E69),0) -> 6024.5 | F70: =IFERROR(SUM(F67:F69),0) -> 6054.55 | G70: =IFERROR(SUM(G67:G69),0) -> 6572.53 | H70: =IFERROR(SUM(H67:H69),0) -> 8002.29 | I70: =IFERROR(SUM(I67:I69),0) -> 9521.88 | J70: =IFERROR(SUM(J67:J69),0) -> 16229.84 | K70: =IFERROR(SUM(K67:K69),0) -> 17720.67 | ... M70: =IFERROR(SUM(M67:M69),0) -> 17523.68
B72: Total Assets (A)+(B) | D72: =IFERROR(SUM(D65,D70),0) -> 10559.03 | E72: =IFERROR(SUM(E65,E70),0) -> 12405.19 | F72: =IFERROR(SUM(F65,F70),0) -> 13763.48 | G72: =IFERROR(SUM(G65,G70),0) -> 16248.84 | H72: =IFERROR(SUM(H65,H70),0) -> 16137.97 | I72: =IFERROR(SUM(I65,I70),0) -> 20355.34 | J72: =IFERROR(SUM(J65,J70),0) -> 22958.43 | K72: =IFERROR(SUM(K65,K70),0) -> 25779.33 | ... M72: =IFERROR(SUM(M65,M70),0) -> 30355.25
B74: Check | D74: =D72=D59 -> TRUE | E74: =E72=E59 -> TRUE | F74: =F72=F59 -> TRUE | G74: =G72=G59 -> TRUE | H74: =H72=H59 -> TRUE | I74: =I72=I59 -> TRUE | J74: =J72=J59 -> TRUE | K74: =K72=K59 -> TRUE | ... M74: =M72=M59 -> TRUE
A76: # | B76: ="Cash - Flow Statement - " &'Data Sheet'!$B$1 -> Cash - Flow Statement - ASIAN PAINTS LTD
B78: Operating Activity
B79: Profit from operations | D79: =IFERROR('Cash Flow'!D12,0) -> 2848 | E79: =IFERROR('Cash Flow'!E12,0) -> 3056 | F79: =IFERROR('Cash Flow'!F12,0) -> 3274 | G79: =IFERROR('Cash Flow'!G12,0) -> 3861 | H79: =IFERROR('Cash Flow'!H12,0) -> 4380 | I79: =IFERROR('Cash Flow'!I12,0) -> 4970 | J79: =IFERROR('Cash Flow'!J12,0) -> 4957 | K79: =IFERROR('Cash Flow'!K12,0) -> 6460 | ... M79: =IFERROR('Cash Flow'!M12,0) -> 6390
B80: Receivables | D80: =IFERROR('Cash Flow'!D13,0) -> -146 | E80: =IFERROR('Cash Flow'!E13,0) -> -475 | F80: =IFERROR('Cash Flow'!F13,0) -> -483 | G80: =IFERROR('Cash Flow'!G13,0) -> -205 | H80: =IFERROR('Cash Flow'!H13,0) -> 160 | I80: =IFERROR('Cash Flow'!I13,0) -> -849 | J80: =IFERROR('Cash Flow'!J13,0) -> -1326 | K80: =IFERROR('Cash Flow'!K13,0) -> -834 | ... M80: =IFERROR('Cash Flow'!M13,0) -> 282
B81: Inventory | D81: =IFERROR('Cash Flow'!D14,0) -> 202 | E81: =IFERROR('Cash Flow'!E14,0) -> -629 | F81: =IFERROR('Cash Flow'!F14,0) -> -39 | G81: =IFERROR('Cash Flow'!G14,0) -> -492 | H81: =IFERROR('Cash Flow'!H14,0) -> -251 | I81: =IFERROR('Cash Flow'!I14,0) -> -409 | J81: =IFERROR('Cash Flow'!J14,0) -> -2354 | K81: =IFERROR('Cash Flow'!K14,0) -> -56 | ... M81: =IFERROR('Cash Flow'!M14,0) -> -805
B82: Payables | D82: =IFERROR('Cash Flow'!D15,0) -> 142 | E82: =IFERROR('Cash Flow'!E15,0) -> 501 | F82: =IFERROR('Cash Flow'!F15,0) -> 442 | G82: =IFERROR('Cash Flow'!G15,0) -> 287 | H82: =IFERROR('Cash Flow'!H15,0) -> -241 | I82: =IFERROR('Cash Flow'!I15,0) -> 1143 | J82: =IFERROR('Cash Flow'!J15,0) -> 644 | K82: =IFERROR('Cash Flow'!K15,0) -> -539 | ... M82: =IFERROR('Cash Flow'!M15,0) -> -160
B83: Other WC items | D83: =IFERROR('Cash Flow'!D16,0) -> 0 | E83: =IFERROR('Cash Flow'!E16,0) -> 0 | F83: =IFERROR('Cash Flow'!F16,0) -> 0 | G83: =IFERROR('Cash Flow'!G16,0) -> 0 | H83: =IFERROR('Cash Flow'!H16,0) -> 0 | I83: =IFERROR('Cash Flow'!I16,0) -> -92 | J83: =IFERROR('Cash Flow'!J16,0) -> 242 | K83: =IFERROR('Cash Flow'!K16,0) -> 657 | ... M83: =IFERROR('Cash Flow'!M16,0) -> 114
B84: Working capital changes | D84: =IFERROR('Cash Flow'!D17,0) -> 198 | E84: =IFERROR('Cash Flow'!E17,0) -> -603 | F84: =IFERROR('Cash Flow'!F17,0) -> -80 | G84: =IFERROR('Cash Flow'!G17,0) -> -410 | H84: =IFERROR('Cash Flow'!H17,0) -> -331 | I84: =IFERROR('Cash Flow'!I17,0) -> -206 | J84: =IFERROR('Cash Flow'!J17,0) -> -2795 | K84: =IFERROR('Cash Flow'!K17,0) -> -772 | ... M84: =IFERROR('Cash Flow'!M17,0) -> -570
B85: Direct taxes | D85: =IFERROR('Cash Flow'!D18,0) -> -802 | E85: =IFERROR('Cash Flow'!E18,0) -> -925 | F85: =IFERROR('Cash Flow'!F18,0) -> -1081 | G85: =IFERROR('Cash Flow'!G18,0) -> -982 | H85: =IFERROR('Cash Flow'!H18,0) -> -1011 | I85: =IFERROR('Cash Flow'!I18,0) -> -1080 | J85: =IFERROR('Cash Flow'!J18,0) -> -1176 | K85: =IFERROR('Cash Flow'!K18,0) -> -1494 | ... M85: =IFERROR('Cash Flow'!M18,0) -> -1396
B86: Cash From Operating Activity | D86: =IFERROR(SUM(D79,D84,D85),0) -> 2244 | E86: =IFERROR(SUM(E79,E84,E85),0) -> 1528 | F86: =IFERROR(SUM(F79,F84,F85),0) -> 2113 | G86: =IFERROR(SUM(G79,G84,G85),0) -> 2469 | H86: =IFERROR(SUM(H79,H84,H85),0) -> 3038 | I86: =IFERROR(SUM(I79,I84,I85),0) -> 3684 | J86: =IFERROR(SUM(J79,J84,J85),0) -> 986 | K86: =IFERROR(SUM(K79,K84,K85),0) -> 4194 | ... M86: =IFERROR(SUM(M79,M84,M85),0) -> 4424
B88: Investing Activity
B89: Fixed assets purchased | D89: =IFERROR('Cash Flow'!D20,0) -> -817 | E89: =IFERROR('Cash Flow'!E20,0) -> -684 | F89: =IFERROR('Cash Flow'!F20,0) -> -1426 | G89: =IFERROR('Cash Flow'!G20,0) -> -1151 | H89: =IFERROR('Cash Flow'!H20,0) -> -404 | I89: =IFERROR('Cash Flow'!I20,0) -> -282 | J89: =IFERROR('Cash Flow'!J20,0) -> -551 | K89: =IFERROR('Cash Flow'!K20,0) -> -1446 | ... M89: =IFERROR('Cash Flow'!M20,0) -> -1830
B90: Fixed assets sold | D90: =IFERROR('Cash Flow'!D21,0) -> 15 | E90: =IFERROR('Cash Flow'!E21,0) -> 17 | F90: =IFERROR('Cash Flow'!F21,0) -> 17 | G90: =IFERROR('Cash Flow'!G21,0) -> 17 | H90: =IFERROR('Cash Flow'!H21,0) -> 37 | I90: =IFERROR('Cash Flow'!I21,0) -> 28 | J90: =IFERROR('Cash Flow'!J21,0) -> 40 | K90: =IFERROR('Cash Flow'!K21,0) -> 26 | ... M90: =IFERROR('Cash Flow'!M21,0) -> 10
B91: Investments purchased | D91: =IFERROR('Cash Flow'!D22,0) -> -282 | E91: =IFERROR('Cash Flow'!E22,0) -> -153 | F91: =IFERROR('Cash Flow'!F22,0) -> -320 | G91: =IFERROR('Cash Flow'!G22,0) -> -573 | H91: =IFERROR('Cash Flow'!H22,0) -> -25 | I91: =IFERROR('Cash Flow'!I22,0) -> -140 | J91: =IFERROR('Cash Flow'!J22,0) -> 0 | K91: =IFERROR('Cash Flow'!K22,0) -> -146 | ... M91: =IFERROR('Cash Flow'!M22,0) -> -1
B92: Investments sold | D92: =IFERROR('Cash Flow'!D23,0) -> 205 | E92: =IFERROR('Cash Flow'!E23,0) -> 357 | F92: =IFERROR('Cash Flow'!F23,0) -> 362 | G92: =IFERROR('Cash Flow'!G23,0) -> 733 | H92: =IFERROR('Cash Flow'!H23,0) -> 134 | I92: =IFERROR('Cash Flow'!I23,0) -> 272 | J92: =IFERROR('Cash Flow'!J23,0) -> 207 | K92: =IFERROR('Cash Flow'!K23,0) -> 446 | ... M92: =IFERROR('Cash Flow'!M23,0) -> 421
B93: Interest received | D93: =IFERROR('Cash Flow'!D24,0) -> 15 | E93: =IFERROR('Cash Flow'!E24,0) -> 32 | F93: =IFERROR('Cash Flow'!F24,0) -> 39 | G93: =IFERROR('Cash Flow'!G24,0) -> 40 | H93: =IFERROR('Cash Flow'!H24,0) -> 65 | I93: =IFERROR('Cash Flow'!I24,0) -> 73 | J93: =IFERROR('Cash Flow'!J24,0) -> 77 | K93: =IFERROR('Cash Flow'!K24,0) -> 87 | ... M93: =IFERROR('Cash Flow'!M24,0) -> 155
B94: Dividends received | D94: =IFERROR('Cash Flow'!D25,0) -> 69 | E94: =IFERROR('Cash Flow'!E25,0) -> 74 | F94: =IFERROR('Cash Flow'!F25,0) -> 38 | G94: =IFERROR('Cash Flow'!G25,0) -> 40 | H94: =IFERROR('Cash Flow'!H25,0) -> 27 | I94: =IFERROR('Cash Flow'!I25,0) -> 8 | J94: =IFERROR('Cash Flow'!J25,0) -> 15 | K94: =IFERROR('Cash Flow'!K25,0) -> 56 | ... M94: =IFERROR('Cash Flow'!M25,0) -> 136
B95: Investment in group cos | D95: =IFERROR('Cash Flow'!D26,0) -> 0 | E95: =IFERROR('Cash Flow'!E26,0) -> 0 | F95: =IFERROR('Cash Flow'!F26,0) -> 0 | G95: =IFERROR('Cash Flow'!G26,0) -> 0 | H95: =IFERROR('Cash Flow'!H26,0) -> 0 | I95: =IFERROR('Cash Flow'!I26,0) -> 0 | J95: =IFERROR('Cash Flow'!J26,0) -> 0 | K95: =IFERROR('Cash Flow'!K26,0) -> -180 | ... M95: =IFERROR('Cash Flow'!M26,0) -> 0
B96: Redemp n Canc of Shares | D96: =IFERROR('Cash Flow'!D27,0) -> 0 | E96: =IFERROR('Cash Flow'!E27,0) -> 0 | F96: =IFERROR('Cash Flow'!F27,0) -> 141 | G96: =IFERROR('Cash Flow'!G27,0) -> 0 | H96: =IFERROR('Cash Flow'!H27,0) -> 0 | I96: =IFERROR('Cash Flow'!I27,0) -> 0 | J96: =IFERROR('Cash Flow'!J27,0) -> 0 | K96: =IFERROR('Cash Flow'!K27,0) -> 0 | ... M96: =IFERROR('Cash Flow'!M27,0) -> 38
B97: Acquisition of companies | D97: =IFERROR('Cash Flow'!D28,0) -> 0 | E97: =IFERROR('Cash Flow'!E28,0) -> 0 | F97: =IFERROR('Cash Flow'!F28,0) -> -525 | G97: =IFERROR('Cash Flow'!G28,0) -> 0 | H97: =IFERROR('Cash Flow'!H28,0) -> 0 | I97: =IFERROR('Cash Flow'!I28,0) -> 0 | J97: =IFERROR('Cash Flow'!J28,0) -> 0 | K97: =IFERROR('Cash Flow'!K28,0) -> 0 | ... M97: =IFERROR('Cash Flow'!M28,0) -> 0
B98: Other investing items | D98: =IFERROR('Cash Flow'!D29,0) -> -70 | E98: =IFERROR('Cash Flow'!E29,0) -> -324 | F98: =IFERROR('Cash Flow'!F29,0) -> 118 | G98: =IFERROR('Cash Flow'!G29,0) -> -24 | H98: =IFERROR('Cash Flow'!H29,0) -> -353 | I98: =IFERROR('Cash Flow'!I29,0) -> -500 | J98: =IFERROR('Cash Flow'!J29,0) -> -105 | K98: =IFERROR('Cash Flow'!K29,0) -> -126 | ... M98: =IFERROR('Cash Flow'!M29,0) -> 130
B99: Cash From Investing Activity | D99: =IFERROR(SUM(D89:D98),0) -> -865 | E99: =IFERROR(SUM(E89:E98),0) -> -681 | F99: =IFERROR(SUM(F89:F98),0) -> -1556 | G99: =IFERROR(SUM(G89:G98),0) -> -918 | H99: =IFERROR(SUM(H89:H98),0) -> -519 | I99: =IFERROR(SUM(I89:I98),0) -> -541 | J99: =IFERROR(SUM(J89:J98),0) -> -317 | K99: =IFERROR(SUM(K89:K98),0) -> -1283 | ... M99: =IFERROR(SUM(M89:M98),0) -> -941
B101: Financing Activity
B102: Proceeds from shares | D102: =IFERROR('Cash Flow'!D31,0) -> 0 | E102: =IFERROR('Cash Flow'!E31,0) -> 0 | F102: =IFERROR('Cash Flow'!F31,0) -> 0 | G102: =IFERROR('Cash Flow'!G31,0) -> 0 | H102: =IFERROR('Cash Flow'!H31,0) -> 0 | I102: =IFERROR('Cash Flow'!I31,0) -> 0 | J102: =IFERROR('Cash Flow'!J31,0) -> 0 | K102: =IFERROR('Cash Flow'!K31,0) -> 0 | ... M102: =IFERROR('Cash Flow'!M31,0) -> 0
B103: Proceeds from borrowings | D103: =IFERROR('Cash Flow'!D32,0) -> 8 | E103: =IFERROR('Cash Flow'!E32,0) -> 271 | F103: =IFERROR('Cash Flow'!F32,0) -> 10 | G103: =IFERROR('Cash Flow'!G32,0) -> 243 | H103: =IFERROR('Cash Flow'!H32,0) -> 18 | I103: =IFERROR('Cash Flow'!I32,0) -> 155 | J103: =IFERROR('Cash Flow'!J32,0) -> 418 | K103: =IFERROR('Cash Flow'!K32,0) -> 254 | ... M103: =IFERROR('Cash Flow'!M32,0) -> 415
B104: Repayment of borrowings | D104: =IFERROR('Cash Flow'!D33,0) -> -119 | E104: =IFERROR('Cash Flow'!E33,0) -> -58 | F104: =IFERROR('Cash Flow'!F33,0) -> -54 | G104: =IFERROR('Cash Flow'!G33,0) -> -26 | H104: =IFERROR('Cash Flow'!H33,0) -> -279 | I104: =IFERROR('Cash Flow'!I33,0) -> -14 | J104: =IFERROR('Cash Flow'!J33,0) -> -8 | K104: =IFERROR('Cash Flow'!K33,0) -> -25 | ... M104: =IFERROR('Cash Flow'!M33,0) -> -428
B105: Interest paid fin | D105: =IFERROR('Cash Flow'!D34,0) -> -40 | E105: =IFERROR('Cash Flow'!E34,0) -> -36 | F105: =IFERROR('Cash Flow'!F34,0) -> -35 | G105: =IFERROR('Cash Flow'!G34,0) -> -106 | H105: =IFERROR('Cash Flow'!H34,0) -> -101 | I105: =IFERROR('Cash Flow'!I34,0) -> -89 | J105: =IFERROR('Cash Flow'!J34,0) -> -94 | K105: =IFERROR('Cash Flow'!K34,0) -> -142 | ... M105: =IFERROR('Cash Flow'!M34,0) -> -203
B106: Dividends paid | D106: =IFERROR('Cash Flow'!D35,0) -> -764 | E106: =IFERROR('Cash Flow'!E35,0) -> -947 | F106: =IFERROR('Cash Flow'!F35,0) -> -1218 | G106: =IFERROR('Cash Flow'!G35,0) -> -1049 | H106: =IFERROR('Cash Flow'!H35,0) -> -2121 | I106: =IFERROR('Cash Flow'!I35,0) -> -499 | J106: =IFERROR('Cash Flow'!J35,0) -> -1763 | K106: =IFERROR('Cash Flow'!K35,0) -> -1936 | ... M106: =IFERROR('Cash Flow'!M35,0) -> -3140
B107: Financial liabilities | D107: =IFERROR('Cash Flow'!D36,0) -> 0 | E107: =IFERROR('Cash Flow'!E36,0) -> 0 | F107: =IFERROR('Cash Flow'!F36,0) -> 0 | G107: =IFERROR('Cash Flow'!G36,0) -> -180 | H107: =IFERROR('Cash Flow'!H36,0) -> -179 | I107: =IFERROR('Cash Flow'!I36,0) -> -203 | J107: =IFERROR('Cash Flow'!J36,0) -> -221 | K107: =IFERROR('Cash Flow'!K36,0) -> -256 | ... M107: =IFERROR('Cash Flow'!M36,0) -> -325
B108: Other financing items | D108: =IFERROR('Cash Flow'!D37,0) -> 66 | E108: =IFERROR('Cash Flow'!E37,0) -> 13 | F108: =IFERROR('Cash Flow'!F37,0) -> -82 | G108: =IFERROR('Cash Flow'!G37,0) -> 0 | H108: =IFERROR('Cash Flow'!H37,0) -> -209 | I108: =IFERROR('Cash Flow'!I37,0) -> 0 | J108: =IFERROR('Cash Flow'!J37,0) -> -140 | K108: =IFERROR('Cash Flow'!K37,0) -> -36 | ... M108: =IFERROR('Cash Flow'!M37,0) -> -72
B109: Cash From Investing Activity | D109: =IFERROR(SUM(D102:D108),0) -> -849 | E109: =IFERROR(SUM(E102:E108),0) -> -757 | F109: =IFERROR(SUM(F102:F108),0) -> -1379 | G109: =IFERROR(SUM(G102:G108),0) -> -1118 | H109: =IFERROR(SUM(H102:H108),0) -> -2871 | I109: =IFERROR(SUM(I102:I108),0) -> -650 | J109: =IFERROR(SUM(J102:J108),0) -> -1808 | K109: =IFERROR(SUM(K102:K108),0) -> -2141 | ... M109: =IFERROR(SUM(M102:M108),0) -> -3753
B111: Net Cash Flow | D111: =IFERROR(SUM(D86+D99+D109),0) -> 530 | E111: =IFERROR(SUM(E86+E99+E109),0) -> 90 | F111: =IFERROR(SUM(F86+F99+F109),0) -> -822 | G111: =IFERROR(SUM(G86+G99+G109),0) -> 433 | H111: =IFERROR(SUM(H86+H99+H109),0) -> -352 | I111: =IFERROR(SUM(I86+I99+I109),0) -> 2493 | J111: =IFERROR(SUM(J86+J99+J109),0) -> -1139 | K111: =IFERROR(SUM(K86+K99+K109),0) -> 770 | ... M111: =IFERROR(SUM(M86+M99+M109),0) -> -270

Sheet Ratio Analysis
B2: ="Ratio Analysis - " &'Data Sheet'!B1 -> Ratio Analysis - ASIAN PAINTS LTD
B3: Years | D3: ='Data Sheet'!B16 -> 42460 | E3: ='Data Sheet'!C16 -> 42825 | F3: ='Data Sheet'!D16 -> 43190 | G3: ='Data Sheet'!E16 -> 43555 | H3: ='Data Sheet'!F16 -> 43921 | I3: ='Data Sheet'!G16 -> 44286 | J3: ='Data Sheet'!H16 -> 44651 | K3: ='Data Sheet'!I16 -> 45016 | ... M3: ='Data Sheet'!K16 -> 45747 | N3: Trend | O3: Mean | P3: Median
B5: Sales Growth | D5: - | E5: =FS!E10 -> 0.055390152 | F5: =FS!F10 -> 0.11702039 | G5: =FS!G10 -> 0.14357472 | H5: =FS!H10 -> 0.050473671 | I5: =FS!I10 -> 0.074292288 | J5: =FS!J10 -> 0.34028285 | K5: =FS!K10 -> 0.18512278 | L5: =FS!L10 -> 0.029173127 | M5: =FS!M10 -> -0.044770308 | O5: =IFERROR(AVERAGE(E5:M5),0) -> 0.10561774 | P5: =IFERROR(MEDIAN(D5:M5),0) -> 0.074292288
B6: EBITDA Growth | D6: - | E6: =FS!E21/FS!D21-1 -> 0.098611397 | F6: =FS!F21/FS!E21-1 -> 0.070229411 | G6: =FS!G21/FS!F21-1 -> 0.17507124 | H6: =FS!H21/FS!G21-1 -> 0.10408665 | I6: =FS!I21/FS!H21-1 -> 0.16810446 | J6: =FS!J21/FS!I21-1 -> -0.010707225 | K6: =FS!K21/FS!J21-1 -> 0.30315325 | L6: =FS!L21/FS!K21-1 -> 0.21168912 | M6: =FS!M21/FS!L21-1 -> -0.20814425 | O6: =IFERROR(AVERAGE(E6:M6),0) -> 0.10134378 | P6: =IFERROR(MEDIAN(D6:M6),0) -> 0.10408665
B7: EBIT Growth | D7: - | E7: =FS!E27/FS!D27-1 -> 0.12543703 | F7: =FS!F27/FS!E27-1 -> 0.061090404 | G7: =FS!G27/FS!F27-1 -> 0.074409975 | H7: =FS!H27/FS!G27-1 -> 0.092139192 | I7: =FS!I27/FS!H27-1 -> 0.1781142 | J7: =FS!J27/FS!I27-1 -> -0.025671181 | K7: =FS!K27/FS!J27-1 -> 0.3619199 | L7: =FS!L27/FS!K27-1 -> 0.29480155 | M7: =FS!M27/FS!L27-1 -> -0.29430262 | O7: =IFERROR(AVERAGE(E7:M7),0) -> 0.096437608 | P7: =IFERROR(MEDIAN(D7:M7),0) -> 0.092139192
B8: Net Profit Growth | D8: - | E8: =FS!E39/FS!D39-1 -> 0.11131931 | F8: =FS!F39/FS!E39-1 -> 0.051303734 | G8: =FS!G39/FS!F39-1 -> 0.057378135 | H8: =FS!H39/FS!G39-1 -> 0.25476363 | I8: =FS!I39/FS!H39-1 -> 0.1604779 | J8: =FS!J39/FS!I39-1 -> -0.034632035 | K8: =FS!K39/FS!J39-1 -> 0.35500912 | L8: =FS!L39/FS!K39-1 -> 0.32967161 | M8: =FS!M39/FS!L39-1 -> -0.32837445 | O8: =IFERROR(AVERAGE(E8:M8),0) -> 0.10632411 | P8: =IFERROR(MEDIAN(D8:M8),0) -> 0.11131931
B9: Dividend Growth | D9: - | E9: =FS!E47/FS!D47-1 -> 0.37333889 | F9: =FS!F47/FS!E47-1 -> -0.15534727 | G9: =FS!G47/FS!F47-1 -> 0.20690234 | H9: =FS!H47/FS!G47-1 -> 0.14285714 | I9: =FS!I47/FS!H47-1 -> 0.48749826 | J9: =FS!J47/FS!I47-1 -> 0.072831553 | K9: =FS!K47/FS!J47-1 -> 0.33942522 | L9: =FS!L47/FS!K47-1 -> 0.29824618 | M9: =FS!M47/FS!L47-1 -> -0.25525494 | O9: =IFERROR(AVERAGE(E9:M9),0) -> 0.16783304 | P9: =IFERROR(MEDIAN(D9:M9),0) -> 0.20690234
B11: Gross Margin | D11: =FS!D16 -> 0.44604803 | E11: =FS!E16 -> 0.4228671 | F11: =FS!F16 -> 0.40133436 | G11: =FS!G16 -> 0.39381283 | H11: =FS!H16 -> 0.41682231 | I11: =FS!I16 -> 0.42487999 | J11: =FS!J16 -> 0.35411913 | K11: =FS!K16 -> 0.36992814 | ... M11: =FS!M16 -> 0.4061312 | O11: =IFERROR(AVERAGE(E11:M11),0) -> 0.40082358 | P11: =IFERROR(MEDIAN(D11:M11),0) -> 0.41147676
B12: EBITDA Margin | D12: =FS!D22 -> 0.19094292 | E12: =FS!E22 -> 0.19876258 | F12: =FS!F22 -> 0.19043659 | G12: =FS!G22 -> 0.19568163 | H12: =FS!H22 -> 0.20566863 | I12: =FS!I22 -> 0.22362856 | J12: =FS!J22 -> 0.16506525 | K12: =FS!K22 -> 0.18150467 | ... M12: =FS!M22 -> 0.17714497 | O12: =IFERROR(AVERAGE(E12:M12),0) -> 0.19462067 | P12: =IFERROR(MEDIAN(D12:M12),0) -> 0.19331228
B13: EBIT Margin | D13: =FS!D28 -> 0.18658528 | E13: =FS!E28 -> 0.19896906 | F13: =FS!F28 -> 0.18900654 | G13: =FS!G28 -> 0.1775752 | H13: =FS!H28 -> 0.18461847 | I13: =FS!I28 -> 0.20246039 | J13: =FS!J28 -> 0.14718012 | K13: =FS!K28 -> 0.16913652 | ... M13: =FS!M28 -> 0.15720373 | O13: =IFERROR(AVERAGE(E13:M13),0) -> 0.1821045 | P13: =IFERROR(MEDIAN(D13:M13),0) -> 0.18560188
B14: EBT Margin | D14: =FS!D34 -> 0.18315186 | E14: =FS!E34 -> 0.19649064 | F14: =FS!F34 -> 0.18654169 | G14: =FS!G34 -> 0.17183356 | H14: =FS!H34 -> 0.17955545 | I14: =FS!I34 -> 0.1982403 | J14: =FS!J34 -> 0.14390157 | K14: =FS!K34 -> 0.16494818 | ... M14: =FS!M34 -> 0.15050809 | O14: =IFERROR(AVERAGE(E14:M14),0) -> 0.17766996 | P14: =IFERROR(MEDIAN(D14:M14),0) -> 0.18135365
B15: Net Profit Margin | D15: =FS!D40 -> 0.12228296 | E15: =FS!E40 -> 0.1287632 | F15: =FS!F40 -> 0.12118779 | G15: =FS!G40 -> 0.1120533 | H15: =FS!H40 -> 0.13384476 | I15: =FS!I40 -> 0.14458252 | J15: =FS!J40 -> 0.10413872 | K15: =FS!K40 -> 0.11906691 | ... M15: =FS!M40 -> 0.10815995 | O15: =IFERROR(AVERAGE(E15:M15),0) -> 0.12506992 | P15: =IFERROR(MEDIAN(D15:M15),0) -> 0.12173537
B17: Sales Expenses as % of Sales | D17: =FS!D19 -> 0.25918177 | E17: =FS!E19 -> 0.26730465 | F17: =FS!F19 -> 0.11403039 | G17: =FS!G19 -> 0.10878825 | H17: =FS!H19 -> 0.096800544 | I17: =FS!I19 -> 0.088152651 | J17: =FS!J19 -> 0.090927272 | K17: =FS!K19 -> 0.08899697 | ... M17: =FS!M19 -> 0.10395681 | O17: =IFERROR(AVERAGE(E17:M17),0) -> 0.11591342 | P17: =IFERROR(MEDIAN(D17:M17),0) -> 0.10037868
B18: Depriciation as % of Sales | D18: =FS!D25 -> 0.019309827 | E18: =FS!E25 -> 0.022227475 | F18: =FS!F25 -> 0.021425239 | G18: =FS!G25 -> 0.03233554 | H18: =FS!H25 -> 0.038617107 | I18: =FS!I25 -> 0.036442576 | J18: =FS!J25 -> 0.028052374 | K18: =FS!K25 -> 0.024878373 | ... M18: =FS!M25 -> 0.030270498 | O18: =IFERROR(AVERAGE(E18:M18),0) -> 0.02869788 | P18: =IFERROR(MEDIAN(D18:M18),0) -> 0.026465374
B19: Operating Income as % of Sales | D19: =FS!D22 -> 0.19094292 | E19: =FS!E22 -> 0.19876258 | F19: =FS!F22 -> 0.19043659 | G19: =FS!G22 -> 0.19568163 | H19: =FS!H22 -> 0.20566863 | I19: =FS!I22 -> 0.22362856 | J19: =FS!J22 -> 0.16506525 | K19: =FS!K22 -> 0.18150467 | ... M19: =FS!M22 -> 0.17714497 | O19: =IFERROR(AVERAGE(E19:M19),0) -> 0.19462067 | P19: =IFERROR(MEDIAN(D19:M19),0) -> 0.19331228
B21: Return on capital employed | D21: =FS!D27/SUM(FS!D55:D57) -> 0.38884451 | E21: =FS!E27/SUM(FS!E55:E57) -> 0.3670732 | F21: =FS!F27/SUM(FS!F55:F57) -> 0.35555354 | G21: =FS!G27/SUM(FS!G55:G57) -> 0.31663786 | H21: =FS!H27/SUM(FS!H55:H57) -> 0.33171684 | I21: =FS!I27/SUM(FS!I55:I57) -> 0.31627098 | J21: =FS!J27/SUM(FS!J55:J57) -> 0.2781535 | K21: =FS!K27/SUM(FS!K55:K57) -> 0.32542978 | ... M21: =FS!M27/SUM(FS!M55:M57) -> 0.24573838 | O21: =IFERROR(AVERAGE(E21:M21),0) -> 0.3214222 | P21: =IFERROR(MEDIAN(D21:M21),0) -> 0.32857331
B22: Retained Earnings % | D22: =FS!D50 -> 0.58777419 | E22: =FS!E50 -> 0.49058228 | F22: =FS!F50 -> 0.5907167 | G22: =FS!G50 -> 0.53283981 | H22: =FS!H50 -> 0.57450364 | I22: =FS!I50 -> 0.45459961 | J22: =FS!J50 -> 0.3938863 | K22: =FS!K50 -> 0.40085719 | ... M22: =FS!M50 -> 0.35133057 | O22: =IFERROR(AVERAGE(E22:M22),0) -> 0.46714816 | P22: =IFERROR(MEDIAN(D22:M22),0) -> 0.47259095
B23: Return on Equity % | D23: =FS!D33/SUM(FS!D55:D56) -> 0.40060109 | E23: =FS!E33/SUM(FS!E55:E56) -> 0.38921394 | F23: =FS!F33/SUM(FS!F55:F56) -> 0.3731741 | G23: =FS!G33/SUM(FS!G55:G56) -> 0.34909271 | H23: =FS!H33/SUM(FS!H55:H56) -> 0.35824113 | I23: =FS!I33/SUM(FS!I55:I56) -> 0.33611218 | J23: =FS!J33/SUM(FS!J55:J56) -> 0.30320398 | K23: =FS!K33/SUM(FS!K55:K56) -> 0.35572462 | ... M23: =FS!M33/SUM(FS!M55:M56) -> 0.26304742 | O23: =IFERROR(AVERAGE(E23:M23),0) -> 0.3466828 | P23: =IFERROR(MEDIAN(D23:M23),0) -> 0.35698288
B24: Self sustained growth rate | D24: =D22*D23 -> 0.23546298 | E24: =E22*E23 -> 0.19094146 | F24: =F22*F23 -> 0.22044017 | G24: =G22*G23 -> 0.18601049 | H24: =H22*H23 -> 0.20581083 | I24: =I22*I23 -> 0.15279646 | J24: =J22*J23 -> 0.11942789 | K24: =K22*K23 -> 0.14259477 | ... M24: =M22*M23 -> 0.0924166 | O24: =IFERROR(AVERAGE(E24:M24),0) -> 0.16369606 | P24: =IFERROR(MEDIAN(D24:M24),0) -> 0.17441818
B25: Interest Coverage Ratio | D25: =FS!D27/FS!D30 -> 54.343878 | E25: =FS!E27/FS!E30 -> 80.280471 | F25: =FS!F27/FS!F30 -> 76.680733 | G25: =FS!G27/FS!G30 -> 30.927582 | H25: =FS!H27/FS!H30 -> 36.464087 | I25: =FS!I27/FS!I30 -> 47.975336 | J25: =FS!J27/FS!J30 -> 44.891835 | K25: =FS!K27/FS!K30 -> 40.382693 | ... M25: =FS!M27/FS!M30 -> 23.478504 | O25: =IFERROR(AVERAGE(E25:M25),0) -> 46.432703 | P25: =IFERROR(MEDIAN(D25:M25),0) -> 42.637264
B27: Debtor Turnover Ratio | D27: =FS!D9/'Data Sheet'!B67 -> 12.02478 | E27: =FS!E9/'Data Sheet'!C67 -> 10.411994 | F27: =FS!F9/'Data Sheet'!D67 -> 9.7216332 | G27: =FS!G9/'Data Sheet'!E67 -> 10.087468 | H27: =FS!H9/'Data Sheet'!F67 -> 11.258369 | I27: =FS!I9/'Data Sheet'!G67 -> 8.344109 | J27: =FS!J9/'Data Sheet'!H67 -> 7.5169136 | K27: =FS!K9/'Data Sheet'!I67 -> 7.4377909 | ... M27: =FS!M9/'Data Sheet'!K67 -> 7.8600767 | O27: =IFERROR(AVERAGE(E27:M27),0) -> 8.8776001 | P27: =IFERROR(MEDIAN(D27:M27),0) -> 9.0328711
B28: Creditor Turnover Ratio | D28: =FS!D9/FS!D58 -> 3.8458091 | E28: =FS!E9/FS!E58 -> 3.551552 | F28: =FS!F9/FS!F58 -> 3.4907009 | G28: =FS!G9/FS!G58 -> 3.524679 | H28: =FS!H9/FS!H58 -> 4.1337633 | I28: =FS!I9/FS!I58 -> 3.3632319 | J28: =FS!J9/FS!J58 -> 3.8493808 | K28: =FS!K9/FS!K58 -> 4.390945 | ... M28: =FS!M9/FS!M58 -> 3.9128717 | O28: =IFERROR(AVERAGE(E28:M28),0) -> 3.8108749 | P28: =IFERROR(MEDIAN(D28:M28),0) -> 3.8475949
B29: Inventory Turnover Ratio | D29: =FS!D9/FS!D69 -> 7.14203 | E29: =FS!E9/FS!E69 -> 5.7336635 | F29: =FS!F9/FS!F69 -> 6.3290399 | G29: =FS!G9/FS!G69 -> 6.1082493 | H29: =FS!H9/FS!H69 -> 5.9623548 | I29: =FS!I9/FS!I69 -> 5.715998 | J29: =FS!J9/FS!J69 -> 4.7296237 | K29: =FS!K9/FS!K69 -> 5.5531459 | ... M29: =FS!M9/FS!M69 -> 5.0460273 | O29: =IFERROR(AVERAGE(E29:M29),0) -> 5.685598 | P29: =IFERROR(MEDIAN(D29:M29),0) -> 5.8480092
B30: Fixed Asset Turnover Ratio | D30: =FS!D9/FS!D61 -> 4.1774086 | E30: =FS!E9/FS!E61 -> 4.5590724 | F30: =FS!F9/FS!F61 -> 4.5078961 | G30: =FS!G9/FS!G61 -> 2.9615874 | H30: =FS!H9/FS!H61 -> 3.2222977 | I30: =FS!I9/FS!I61 -> 3.7061903 | J30: =FS!J9/FS!J61 -> 5.2728689 | K30: =FS!K9/FS!K61 -> 5.9767488 | ... M30: =FS!M9/FS!M61 -> 3.6773592 | O30: =IFERROR(AVERAGE(E30:M30),0) -> 4.3167407 | P30: =IFERROR(MEDIAN(D30:M30),0) -> 4.3426524
B31: Capital Turnover Ratio | D31: =FS!D9/SUM(FS!D55:D56) -> 2.1872619 | E31: =FS!E9/SUM(FS!E55:E56) -> 1.9808269 | F31: =FS!F9/SUM(FS!F55:F56) -> 2.0004863 | G31: =FS!G9/SUM(FS!G55:G56) -> 2.0315747 | H31: =FS!H9/SUM(FS!H55:H56) -> 1.995156 | I31: =FS!I9/SUM(FS!I55:I56) -> 1.6954785 | J31: =FS!J9/SUM(FS!J55:J56) -> 2.1070234 | K31: =FS!K9/SUM(FS!K55:K56) -> 2.1565842 | ... M31: =FS!M9/SUM(FS!M55:M56) -> 1.7477295 | O31: =IFERROR(AVERAGE(E31:M31),0) -> 1.9566784 | P31: =IFERROR(MEDIAN(D31:M31),0) -> 1.9978212
B33: Debtor Days | D33: =IFERROR(365/D27,0) -> 30.353985 | E33: =IFERROR(365/E27,0) -> 35.055726 | F33: =IFERROR(365/F27,0) -> 37.545132 | G33: =IFERROR(365/G27,0) -> 36.183511 | H33: =IFERROR(365/H27,0) -> 32.420325 | I33: =IFERROR(365/I27,0) -> 43.743436 | J33: =IFERROR(365/J27,0) -> 48.557163 | K33: =IFERROR(365/K27,0) -> 49.073711 | ... M33: =IFERROR(365/M27,0) -> 46.437206 | O33: =IFERROR(AVERAGE(E33:M33),0) -> 42.143486 | P33: =IFERROR(MEDIAN(D33:M33),0) -> 40.644284
B34: Payable Days | D34: =IFERROR(365/D28,0) -> 94.908506 | E34: =IFERROR(365/E28,0) -> 102.77197 | F34: =IFERROR(365/F28,0) -> 104.56353 | G34: =IFERROR(365/G28,0) -> 103.55553 | H34: =IFERROR(365/H28,0) -> 88.297268 | I34: =IFERROR(365/I28,0) -> 108.52656 | J34: =IFERROR(365/J28,0) -> 94.820446 | K34: =IFERROR(365/K28,0) -> 83.125613 | ... M34: =IFERROR(365/M28,0) -> 93.281873 | O34: =IFERROR(AVERAGE(E34:M34),0) -> 96.487459 | P34: =IFERROR(MEDIAN(D34:M34),0) -> 94.864476
B35: Inventory Days | D35: =IFERROR(365/D29,0) -> 51.105918 | E35: =IFERROR(365/E29,0) -> 63.659125 | F35: =IFERROR(365/F29,0) -> 57.670675 | G35: =IFERROR(365/G29,0) -> 59.755256 | H35: =IFERROR(365/H29,0) -> 61.217423 | I35: =IFERROR(365/I29,0) -> 63.855866 | J35: =IFERROR(365/J29,0) -> 77.173159 | K35: =IFERROR(365/K29,0) -> 65.728509 | ... M35: =IFERROR(365/M29,0) -> 72.334131 | O35: =IFERROR(AVERAGE(E35:M35),0) -> 64.70065 | P35: =IFERROR(MEDIAN(D35:M35),0) -> 62.438274
B36: Cash Conversion Cycle (Days) | D36: =IFERROR(365/D30,0) -> 87.374742 | E36: =IFERROR(365/E30,0) -> 80.060145 | F36: =IFERROR(365/F30,0) -> 80.969036 | G36: =IFERROR(365/G30,0) -> 123.24472 | H36: =IFERROR(365/H30,0) -> 113.27321 | I36: =IFERROR(365/I30,0) -> 98.48388 | J36: =IFERROR(365/J30,0) -> 69.222278 | K36: =IFERROR(365/K30,0) -> 61.069992 | ... M36: =IFERROR(365/M30,0) -> 99.256008 | O36: =IFERROR(AVERAGE(E36:M36),0) -> 88.785501 | P36: =IFERROR(MEDIAN(D36:M36),0) -> 84.171889
B38: CFO/Sales | D38: =FS!D86/FS!D9 -> 0.15723656 | E38: =FS!E86/FS!E9 -> 0.10144742 | F38: =FS!F86/FS!F9 -> 0.12559028 | G38: =FS!G86/FS!G9 -> 0.12832554 | H38: =FS!H86/FS!H9 -> 0.15031233 | I38: =FS!I86/FS!I9 -> 0.16966958 | J38: =FS!J86/FS!J9 -> 0.033881671 | K38: =FS!K86/FS!K9 -> 0.12160544 | ... M38: =FS!M86/FS!M9 -> 0.13047984 | O38: =IFERROR(AVERAGE(E38:M38),0) -> 0.12592014 | P38: =IFERROR(MEDIAN(D38:M38),0) -> 0.12940269
B39: CFO/Total Assets | D39: =FS!D86/FS!D72 -> 0.21251952 | E39: =FS!E86/FS!E72 -> 0.12317425 | F39: =FS!F86/FS!F72 -> 0.15352222 | G39: =FS!G86/FS!G72 -> 0.15194931 | H39: =FS!H86/FS!H72 -> 0.18825168 | I39: =FS!I86/FS!I72 -> 0.18098445 | J39: =FS!J86/FS!J72 -> 0.042947188 | K39: =FS!K86/FS!K72 -> 0.16268848 | ... M39: =FS!M86/FS!M72 -> 0.14574085 | O39: =IFERROR(AVERAGE(E39:M39),0) -> 0.15037781 | P39: =IFERROR(MEDIAN(D39:M39),0) -> 0.15810535
B40: CFO/Total Debt | D40: =FS!D86/FS!D57 -> 6.9411364 | E40: =FS!E86/FS!E57 -> 2.7269158 | F40: =FS!F86/FS!F57 -> 3.961157 | G40: =FS!G86/FS!G57 -> 1.8710215 | H40: =FS!H86/FS!H57 -> 2.7161377 | I40: =FS!I86/FS!I57 -> 3.3701698 | J40: =FS!J86/FS!J57 -> 0.62134503 | K40: =FS!K86/FS!K57 -> 2.170111 | ... M40: =FS!M86/FS!M57 -> 1.9316331 | O40: =IFERROR(AVERAGE(E40:M40),0) -> 2.4261524 | P40: =IFERROR(MEDIAN(D40:M40),0) -> 2.5915091

Sheet Forecasting
B2: ="Sales - Forecasting "&'Data Sheet'!B1 -> Sales - Forecasting ASIAN PAINTS LTD
B3: Year Weight | C3: =FS!B5 -> Years | D3: =FS!B9 -> Sales | E3: =FS!B10 -> Sales Growth
B4: 1 | C4: {=TRANSPOSE(FS!D5:M5)} -> 42460 | D4: {=TRANSPOSE(FS!D9:M9)} -> 14271.49
B5: =B4+1 -> 2 | C5: 42825 | D5: 15061.99 | E5: =D5/D4-1 -> 0.055390152
B6: =B5+1 -> 3 | C6: 43190 | D6: 16824.55 | E6: =D6/D5-1 -> 0.11702039
B7: =B6+1 -> 4 | C7: 43555 | D7: 19240.13 | E7: =D7/D6-1 -> 0.14357472
B8: =B7+1 -> 5 | C8: 43921 | D8: 20211.25 | E8: =D8/D7-1 -> 0.050473671
B9: =B8+1 -> 6 | C9: 44286 | D9: 21712.79 | E9: =D9/D8-1 -> 0.074292288
B10: =B9+1 -> 7 | C10: 44651 | D10: 29101.28 | E10: =D10/D9-1 -> 0.34028285
B11: =B10+1 -> 8 | C11: 45016 | D11: 34488.59 | E11: =D11/D10-1 -> 0.18512278
B12: =B11+1 -> 9 | C12: 45382 | D12: 35494.73 | E12: =D12/D11-1 -> 0.029173127
B13: =B12+1 -> 10 | C13: 45747 | D13: 33905.62 | E13: =D13/D12-1 -> -0.044770308
B14: =B13+1 -> 11 | C14: =C13+365 -> 46112 | D14: =FORECAST(B14,$D$4:$D$13,$B$4:$B$13) -> 38669.293 | E14: =D14/D13-1 -> 0.14049805
B15: =B14+1 -> 12 | C15: =C14+365 -> 46477 | D15: =FORECAST(B15,$D$4:$D$13,$B$4:$B$13) -> 41330.757 | E15: =D15/D14-1 -> 0.068826287
B16: =B15+1 -> 13 | C16: =C15+365 -> 46842 | D16: =FORECAST(B16,$D$4:$D$13,$B$4:$B$13) -> 43992.221 | E16: =D16/D15-1 -> 0.064394269
B17: =B16+1 -> 14 | C17: =C16+365 -> 47207 | D17: =FORECAST(B17,$D$4:$D$13,$B$4:$B$13) -> 46653.685 | E17: =D17/D16-1 -> 0.060498511
B18: =B17+1 -> 15 | C18: =C17+365 -> 47572 | D18: =FORECAST(B18,$D$4:$D$13,$B$4:$B$13) -> 49315.149 | E18: =D18/D17-1 -> 0.057047238

Sheet DATA ->

Sheet Profit & Loss
A1: ='Data Sheet'!B1 -> ASIAN PAINTS LTD | H1: =UPDATE | M1: SCREENER.IN
A3: Narration | B3: ='Data Sheet'!B16 -> 42460 | C3: ='Data Sheet'!C16 -> 42825 | D3: ='Data Sheet'!D16 -> 43190 | E3: ='Data Sheet'!E16 -> 43555 | F3: ='Data Sheet'!F16 -> 43921 | G3: ='Data Sheet'!G16 -> 44286 | H3: ='Data Sheet'!H16 -> 44651 | I3: ='Data Sheet'!I16 -> 45016 | ... K3: ='Data Sheet'!K16 -> 45747 | L3: Trailing | M3: Best Case | N3: Worst Case
A4: Sales | B4: ='Data Sheet'!B17 -> 14271.49 | C4: ='Data Sheet'!C17 -> 15061.99 | D4: ='Data Sheet'!D17 -> 16824.55 | E4: ='Data Sheet'!E17 -> 19240.13 | F4: ='Data Sheet'!F17 -> 20211.25 | G4: ='Data Sheet'!G17 -> 21712.79 | H4: ='Data Sheet'!H17 -> 29101.28 | I4: ='Data Sheet'!I17 -> 34488.59 | ... K4: ='Data Sheet'!K17 -> 33905.62 | L4: =SUM(Quarters!H4:K4) -> 33874.44 | M4: =$K4+M23*K4 -> 35677.265 | N4: =$K4+N23*L4 -> 33874.469
A5: Expenses | B5: =SUM('Data Sheet'!B18,'Data Sheet'!B20:B24, -1*'Data Sheet'!B19) -> 11546.45 | C5: =SUM('Data Sheet'!C18,'Data Sheet'!C20:C24, -1*'Data Sheet'!C19) -> 12068.23 | D5: =SUM('Data Sheet'!D18,'Data Sheet'!D20:D24, -1*'Data Sheet'!D19) -> 13620.54 | E5: =SUM('Data Sheet'!E18,'Data Sheet'!E20:E24, -1*'Data Sheet'!E19) -> 15475.19 | F5: =SUM('Data Sheet'!F18,'Data Sheet'!F20:F24, -1*'Data Sheet'!F19) -> 16054.43 | G5: =SUM('Data Sheet'!G18,'Data Sheet'!G20:G24, -1*'Data Sheet'!G19) -> 16857.19 | H5: =SUM('Data Sheet'!H18,'Data Sheet'!H20:H24, -1*'Data Sheet'!H19) -> 24297.67 | I5: =SUM('Data Sheet'!I18,'Data Sheet'!I20:I24, -1*'Data Sheet'!I19) -> 28228.75 | ... K5: =SUM('Data Sheet'!K18,'Data Sheet'!K20:K24, -1*'Data Sheet'!K19) -> 27899.41 | L5: =SUM(Quarters!H5:K5) -> 27937.03 | M5: =M4-M6 -> 28860.077 | N5: =N4-N6 -> 27937.054
A6: Operating Profit | B6: =B4-B5 -> 2725.04 | C6: =C4-C5 -> 2993.76 | D6: =D4-D5 -> 3204.01 | E6: =E4-E5 -> 3764.94 | F6: =F4-F5 -> 4156.82 | G6: =G4-G5 -> 4855.6 | H6: =H4-H5 -> 4803.61 | I6: =I4-I5 -> 6259.84 | ... K6: =K4-K5 -> 6006.21 | L6: =SUM(Quarters!H6:K6) -> 5937.41 | M6: =M4*M24 -> 6817.1883 | N6: =N4*N24 -> 5937.415
A7: Other Income | B7: ='Data Sheet'!B25 -> 213.39 | C7: ='Data Sheet'!C25 -> 337.9 | D7: ='Data Sheet'!D25 -> 336.41 | E7: ='Data Sheet'!E25 -> 273.77 | F7: ='Data Sheet'!F25 -> 355.05 | G7: ='Data Sheet'!G25 -> 331.65 | H7: ='Data Sheet'!H25 -> 295.88 | I7: ='Data Sheet'!I25 -> 431.46 | ... K7: ='Data Sheet'!K25 -> 350.22 | L7: =SUM(Quarters!H7:K7) -> 386.4 | M7: 0 | N7: 0
A8: Depreciation | B8: ='Data Sheet'!B26 -> 275.58 | C8: ='Data Sheet'!C26 -> 334.79 | D8: ='Data Sheet'!D26 -> 360.47 | E8: ='Data Sheet'!E26 -> 622.14 | F8: ='Data Sheet'!F26 -> 780.5 | G8: ='Data Sheet'!G26 -> 791.27 | H8: ='Data Sheet'!H26 -> 816.36 | I8: ='Data Sheet'!I26 -> 858.02 | ... K8: ='Data Sheet'!K26 -> 1026.34 | L8: =SUM(Quarters!H8:K8) -> 1099.51 | M8: =+$L8 -> 1099.51 | N8: =+$L8 -> 1099.51
A9: Interest | B9: ='Data Sheet'!B27 -> 49 | C9: ='Data Sheet'!C27 -> 37.33 | D9: ='Data Sheet'!D27 -> 41.47 | E9: ='Data Sheet'!E27 -> 110.47 | F9: ='Data Sheet'!F27 -> 102.33 | G9: ='Data Sheet'!G27 -> 91.63 | H9: ='Data Sheet'!H27 -> 95.41 | I9: ='Data Sheet'!I27 -> 144.45 | ... K9: ='Data Sheet'!K27 -> 227.02 | L9: =SUM(Quarters!H9:K9) -> 216.14 | M9: =+$L9 -> 216.14 | N9: =+$L9 -> 216.14
A10: Profit before tax | B10: ='Data Sheet'!B28 -> 2613.85 | C10: ='Data Sheet'!C28 -> 2959.54 | D10: ='Data Sheet'!D28 -> 3138.48 | E10: ='Data Sheet'!E28 -> 3306.1 | F10: ='Data Sheet'!F28 -> 3629.04 | G10: ='Data Sheet'!G28 -> 4304.35 | H10: ='Data Sheet'!H28 -> 4187.72 | I10: ='Data Sheet'!I28 -> 5688.83 | ... K10: ='Data Sheet'!K28 -> 5103.07 | L10: =SUM(Quarters!H10:K10) -> 5008.16 | M10: =M6+M7-SUM(M8:M9) -> 5501.5383 | N10: =N6+N7-SUM(N8:N9) -> 4621.765
A11: Tax | B11: ='Data Sheet'!B29 -> 844.49 | C11: ='Data Sheet'!C29 -> 943.29 | D11: ='Data Sheet'!D29 -> 1040.96 | E11: ='Data Sheet'!E29 -> 1098.06 | F11: ='Data Sheet'!F29 -> 854.85 | G11: ='Data Sheet'!G29 -> 1097.6 | H11: ='Data Sheet'!H29 -> 1102.91 | I11: ='Data Sheet'!I29 -> 1493.5 | ... K11: ='Data Sheet'!K29 -> 1393.36 | L11: =SUM(Quarters!H11:K11) -> 1368.19 | M11: =IF($L10>0,$L11/$L10,0) -> 0.27319215 | N11: =IF($L10>0,$L11/$L10,0) -> 0.27319215
A12: Net profit | B12: ='Data Sheet'!B30 -> 1745.16 | C12: ='Data Sheet'!C30 -> 1939.43 | D12: ='Data Sheet'!D30 -> 2038.93 | E12: ='Data Sheet'!E30 -> 2155.92 | F12: ='Data Sheet'!F30 -> 2705.17 | G12: ='Data Sheet'!G30 -> 3139.29 | H12: ='Data Sheet'!H30 -> 3030.57 | I12: ='Data Sheet'!I30 -> 4106.45 | ... K12: ='Data Sheet'!K30 -> 3667.23 | L12: =SUM(Quarters!H12:K12) -> 3597.02 | M12: =M10-M11*M10 -> 3998.5612 | N12: =N10-N11*N10 -> 3359.1351
A13: EPS | B13: =IF('Data Sheet'!B93>0,B12/'Data Sheet'!B93,0) -> 18.193912 | C13: =IF('Data Sheet'!C93>0,C12/'Data Sheet'!C93,0) -> 20.219245 | D13: =IF('Data Sheet'!D93>0,D12/'Data Sheet'!D93,0) -> 21.256568 | E13: =IF('Data Sheet'!E93>0,E12/'Data Sheet'!E93,0) -> 22.47623 | F13: =IF('Data Sheet'!F93>0,F12/'Data Sheet'!F93,0) -> 28.202356 | G13: =IF('Data Sheet'!G93>0,G12/'Data Sheet'!G93,0) -> 32.728211 | H13: =IF('Data Sheet'!H93>0,H12/'Data Sheet'!H93,0) -> 31.594766 | I13: =IF('Data Sheet'!I93>0,I12/'Data Sheet'!I93,0) -> 42.811197 | ... K13: =IF('Data Sheet'!K93>0,K12/'Data Sheet'!K93,0) -> 38.232173 | L13: =IF('Data Sheet'!$B6>0,'Profit & Loss'!L12/'Data Sheet'!$B6,0) -> 37.500294 | M13: =IF('Data Sheet'!$B6>0,'Profit & Loss'!M12/'Data Sheet'!$B6,0) -> 41.686513 | N13: =IF('Data Sheet'!$B6>0,'Profit & Loss'!N12/'Data Sheet'!$B6,0) -> 35.020254
A14: Price to earning | B14: =IF(B15>0,B15/B13,"") -> 47.730253 | C14: =IF(C15>0,C15/C13,"") -> 53.092981 | D14: =IF(D15>0,D15/D13,"") -> 52.708415 | E14: =IF(E15>0,E15/E13,"") -> 66.412383 | F14: =IF(F15>0,F15/F13,"") -> 59.090808 | G14: =IF(G15>0,G15/G13,"") -> 77.529444 | H14: =IF(H15>0,H15/H13,"") -> 97.482917 | I14: =IF(I15>0,I15/I13,"") -> 64.507657 | ... K14: =IF(K15>0,K15/K13,"") -> 61.221998 | L14: =IF(L13>0,L15/L13,0) -> 67.431471 | M14: =M25 -> 67.431471 | N14: =N25 -> 60.792514
A15: Price | B15: ='Data Sheet'!B90 -> 868.4 | C15: ='Data Sheet'!C90 -> 1073.5 | D15: ='Data Sheet'!D90 -> 1120.4 | E15: ='Data Sheet'!E90 -> 1492.7 | F15: ='Data Sheet'!F90 -> 1666.5 | G15: ='Data Sheet'!G90 -> 2537.4 | H15: ='Data Sheet'!H90 -> 3079.95 | I15: ='Data Sheet'!I90 -> 2761.65 | ... K15: ='Data Sheet'!K90 -> 2340.65 | L15: ='Data Sheet'!B8 -> 2528.7 | M15: =M13*M14 -> 2810.9829 | N15: =N13*N14 -> 2128.9693
A17: RATIOS:
A18: Dividend Payout | B18: =IF('Data Sheet'!B30>0, 'Data Sheet'!B31/'Data Sheet'!B30, 0) -> 0.41222581 | C18: =IF('Data Sheet'!C30>0, 'Data Sheet'!C31/'Data Sheet'!C30, 0) -> 0.50941772 | D18: =IF('Data Sheet'!D30>0, 'Data Sheet'!D31/'Data Sheet'!D30, 0) -> 0.4092833 | E18: =IF('Data Sheet'!E30>0, 'Data Sheet'!E31/'Data Sheet'!E30, 0) -> 0.46716019 | F18: =IF('Data Sheet'!F30>0, 'Data Sheet'!F31/'Data Sheet'!F30, 0) -> 0.42549636 | G18: =IF('Data Sheet'!G30>0, 'Data Sheet'!G31/'Data Sheet'!G30, 0) -> 0.54540039 | H18: =IF('Data Sheet'!H30>0, 'Data Sheet'!H31/'Data Sheet'!H30, 0) -> 0.6061137 | I18: =IF('Data Sheet'!I30>0, 'Data Sheet'!I31/'Data Sheet'!I30, 0) -> 0.59914281 | ... K18: =IF('Data Sheet'!K30>0, 'Data Sheet'!K31/'Data Sheet'!K30, 0) -> 0.64866943
A19: OPM | B19: =IF(B6>0,B6/B4,0) -> 0.19094292 | C19: =IF(C6>0,C6/C4,0) -> 0.19876258 | D19: =IF(D6>0,D6/D4,0) -> 0.19043659 | E19: =IF(E6>0,E6/E4,0) -> 0.19568163 | F19: =IF(F6>0,F6/F4,0) -> 0.20566863 | G19: =IF(G6>0,G6/G4,0) -> 0.22362856 | H19: =IF(H6>0,H6/H4,0) -> 0.16506525 | I19: =IF(I6>0,I6/I4,0) -> 0.18150467 | ... L19: =IF(L6>0,L6/L4,0) -> 0.17527699
G22: TRENDS: | H22: 10 YEARS | I22: 7 YEARS | J22: 5 YEARS | K22: 3 YEARS | L22: RECENT | M22: BEST | N22: WORST
G23: Sales Growth | H23: =IF(B4=0,"",POWER($K4/B4,1/9)-1) -> 0.10092015 | I23: =IF(D4=0,"",POWER($K4/D4,1/7)-1) -> 0.10528802 | J23: =IF(F4=0,"",POWER($K4/F4,1/5)-1) -> 0.10901062 | K23: =IF(H4=0,"",POWER($K4/H4, 1/3)-1) -> 0.052252258 | L23: =IF(ISERROR(MAX(IF(J4=0,"",(K4-J4)/J4),IF(K4=0,"",(L4-K4)/K4))),"",MAX(IF(J4=0,"",(K4-J4)/J4),IF(K4=0,"",(L4-K4)/K4))) -> -0.00091961156 | M23: =MAX(K23:L23) -> 0.052252258 | N23: =MIN(H23:L23) -> -0.00091961156
G24: OPM | H24: =IF(SUM(B4:$K$4)=0,"",SUMPRODUCT(B19:$K$19,B4:$K$4)/SUM(B4:$K$4)) -> 0.19289394 | I24: =IF(SUM(E4:$K$4)=0,"",SUMPRODUCT(E19:$K$19,E4:$K$4)/SUM(E4:$K$4)) -> 0.19279502 | J24: =IF(SUM(G4:$K$4)=0,"",SUMPRODUCT(G19:$K$19,G4:$K$4)/SUM(G4:$K$4)) -> 0.19075414 | K24: =IF(SUM(I4:$K$4)=0, "", SUMPRODUCT(I19:$K$19,I4:$K$4)/SUM(I4:$K$4)) -> 0.19107934 | L24: =L19 -> 0.17527699 | M24: =MAX(K24:L24) -> 0.19107934 | N24: =MIN(H24:L24) -> 0.17527699
G25: Price to Earning | H25: =IF(ISERROR(AVERAGEIF(B14:$L14,">0")),"",AVERAGEIF(B14:$L14,">0")) -> 63.383387 | I25: =IF(ISERROR(AVERAGEIF(E14:$L14,">0")),"",AVERAGEIF(E14:$L14,">0")) -> 67.960701 | J25: =IF(ISERROR(AVERAGEIF(G14:$L14,">0")),"",AVERAGEIF(G14:$L14,">0")) -> 69.69707 | K25: =IF(ISERROR(AVERAGEIF(I14:$L14,">0")),"",AVERAGEIF(I14:$L14,">0")) -> 60.792514 | L25: =L14 -> 67.431471 | M25: =MAX(K25:L25) -> 67.431471 | N25: =MIN(H25:L25) -> 60.792514

Sheet Data Sheet
A1: COMPANY NAME | B1: ASIAN PAINTS LTD | E1: =IF(B2<>B3, "A NEW VERSION OF THE WORKSHEET IS AVAILABLE", "")
A2: LATEST VERSION | B2: 2.1 | E2: PLEASE DO NOT MAKE ANY CHANGES TO THIS SHEET
A3: CURRENT VERSION | B3: 2.1
A5: META
A6: Number of shares | B6: =IF(B9>0, B9/B8, 0) -> 95.919781
A7: Face Value | B7: 1
A8: Current Price | B8: 2528.7
A9: Market Capitalization | B9: 242552.35
A15: PROFIT & LOSS
A16: Report Date | B16: 42460 | C16: 42825 | D16: 43190 | E16: 43555 | F16: 43921 | G16: 44286 | H16: 44651 | I16: 45016 | J16: 45382 | K16: 45747
A17: Sales | B17: 14271.49 | C17: 15061.99 | D17: 16824.55 | E17: 19240.13 | F17: 20211.25 | G17: 21712.79 | H17: 29101.28 | I17: 34488.59 | J17: 35494.73 | K17: 33905.62
A18: Raw Material Cost | B18: 6569.83 | C18: 7452.6 | D18: 8128.17 | E18: 9974.4 | F18: 9981.99 | G18: 10425.55 | H18: 17123.25 | I18: 18985.53 | J18: 17410.84 | K18: 17504.51 | M18: =SUM(B18:B24) -> 11147.79
A19: Change in Inventory | B19: -199.33 | C19: 528.6 | D19: -142.13 | E19: 293.26 | F19: 239.15 | G19: 92.45 | H19: 1324.97 | I19: 309.73 | J19: -363.8 | K19: 205 | M19: =SUM(B22:B24) -> 3127.59
A20: Power and Fuel | B20: 114.48 | C20: 106.02 | D20: 110.3 | E20: 119.63 | F20: 97.79 | G20: 86.05 | H20: 117.23 | I20: 138.29 | J20: 133.25 | K20: 148.58 | M20: =M18-M19 -> 8020.2
A21: Other Mfr. Exp | B21: 1535.22 | C21: 1662.75 | D21: 1691.68 | E21: 1862.35 | F21: 1946.12 | G21: 2068.31 | H21: 2880.45 | I21: 2916.2 | J21: 2767.18 | K21: 2687.4
A22: Employee Cost | B22: 994.98 | C22: 1039.89 | D22: 1121.89 | E22: 1242.69 | F22: 1371.27 | G22: 1547.61 | H22: 1794.61 | I22: 2036.41 | J22: 2334.92 | K22: 2605.78
A23: Selling and admin | B23: 3912.3 | C23: 4364.04 | D23: 2254.92 | E23: 2366.87 | F23: 2311.51 | G23: 2245.69 | H23: 2941.98 | I23: 3500.84 | J23: 3811.86 | K23: 3874.94
A24: Other Expenses | B24: -1779.69 | C24: -2028.47 | D24: 171.45 | E24: 202.51 | F24: 584.9 | G24: 576.43 | H24: 765.12 | I24: 961.21 | J24: 1087.9 | K24: 1283.2
A25: Other Income | B25: 213.39 | C25: 337.9 | D25: 336.41 | E25: 273.77 | F25: 355.05 | G25: 331.65 | H25: 295.88 | I25: 431.46 | J25: 820.96 | K25: 350.22
A26: Depreciation | B26: 275.58 | C26: 334.79 | D26: 360.47 | E26: 622.14 | F26: 780.5 | G26: 791.27 | H26: 816.36 | I26: 858.02 | J26: 853 | K26: 1026.34
A27: Interest | B27: 49 | C27: 37.33 | D27: 41.47 | E27: 110.47 | F27: 102.33 | G27: 91.63 | H27: 95.41 | I27: 144.45 | J27: 205.17 | K27: 227.02
A28: Profit before tax | B28: 2613.85 | C28: 2959.54 | D28: 3138.48 | E28: 3306.1 | F28: 3629.04 | G28: 4304.35 | H28: 4187.72 | I28: 5688.83 | J28: 7347.77 | K28: 5103.07
A29: Tax | B29: 844.49 | C29: 943.29 | D29: 1040.96 | E29: 1098.06 | F29: 854.85 | G29: 1097.6 | H29: 1102.91 | I29: 1493.5 | J29: 1790.08 | K29: 1393.36
A30: Net profit | B30: 1745.16 | C30: 1939.43 | D30: 2038.93 | E30: 2155.92 | F30: 2705.17 | G30: 3139.29 | H30: 3030.57 | I30: 4106.45 | J30: 5460.23 | K30: 3667.23
A31: Dividend Amount | B31: 719.4 | C31: 987.98 | D31: 834.5 | E31: 1007.16 | F31: 1151.04 | G31: 1712.17 | H31: 1836.87 | I31: 2460.35 | J31: 3194.14 | K31: 2378.82
A40: Quarters
A41: Report Date | B41: 45016 | C41: 45107 | D41: 45199 | E41: 45291 | F41: 45382 | G41: 45473 | H41: 45565 | I41: 45657 | J41: 45747 | K41: 45838
A42: Sales | B42: 8787.34 | C42: 9182.31 | D42: 8478.57 | E42: 9103.09 | F42: 8730.76 | G42: 8969.73 | H42: 8027.54 | I42: 8549.44 | J42: 8358.91 | K42: 8938.55
A43: Expenses | B43: 6922.58 | C43: 7061.02 | D43: 6762.34 | E43: 7047 | F43: 7039.39 | G43: 7275.96 | H43: 6788.03 | I43: 6912.71 | J43: 6922.71 | K43: 7313.58
A44: Other Income | B44: 104.17 | C44: 227.74 | D44: 194.33 | E44: 186.46 | F44: 212.43 | G44: 192.93 | H44: 24.53 | I44: 192.82 | J44: -60.06 | K44: 229.11
A45: Depreciation | B45: 220.17 | C45: 198.32 | D45: 208.72 | E45: 220.35 | F45: 225.61 | G45: 227.7 | H45: 241.99 | I45: 255.55 | J45: 301.1 | K45: 300.87
A46: Interest | B46: 38.91 | C46: 45.75 | D46: 50.9 | E46: 54.42 | F46: 54.1 | G46: 55.38 | H46: 63.01 | I46: 55.84 | J46: 52.79 | K46: 44.5
A47: Profit before tax | B47: 1709.85 | C47: 2104.96 | D47: 1650.94 | E47: 1967.78 | F47: 1624.09 | G47: 1603.62 | H47: 959.04 | I47: 1518.16 | J47: 1022.25 | K47: 1508.71
A48: Tax | B48: 451.44 | C48: 530.12 | D48: 418.55 | E48: 492.62 | F48: 348.79 | G48: 416.83 | H48: 265.38 | I48: 389.73 | J48: 321.42 | K48: 391.66
A49: Net profit | B49: 1234.14 | C49: 1550.37 | D49: 1205.42 | E49: 1447.72 | F49: 1256.72 | G49: 1169.98 | H49: 694.64 | I49: 1110.48 | J49: 692.13 | K49: 1099.77
A50: Operating Profit | B50: 1864.76 | C50: 2121.29 | D50: 1716.23 | E50: 2056.09 | F50: 1691.37 | G50: 1693.77 | H50: 1239.51 | I50: 1636.73 | J50: 1436.2 | K50: 1624.97
A55: BALANCE SHEET
A56: Report Date | B56: 42460 | C56: 42825 | D56: 43190 | E56: 43555 | F56: 43921 | G56: 44286 | H56: 44651 | I56: 45016 | J56: 45382 | K56: 45747
A57: Equity Share Capital | B57: 95.92 | C57: 95.92 | D57: 95.92 | E57: 95.92 | F57: 95.92 | G57: 95.92 | H57: 95.92 | I57: 95.92 | J57: 95.92 | K57: 95.92
A58: Reserves | B58: 6428.9 | C58: 7507.97 | D58: 8314.31 | E58: 9374.63 | F58: 10034.24 | G58: 12710.37 | H58: 13715.64 | I58: 15896.31 | J58: 18632.38 | K58: 19303.89
A59: Borrowings | B59: 323.29 | C59: 560.34 | D59: 533.43 | E59: 1319.6 | F59: 1118.5 | G59: 1093.12 | H59: 1586.88 | I59: 1932.62 | J59: 2474.38 | K59: 2290.29
A60: Other Liabilities | B60: 3710.92 | C60: 4240.96 | D60: 4819.82 | E60: 5458.69 | F60: 4889.31 | G60: 6455.93 | H60: 7559.99 | I60: 7854.48 | J60: 8698.09 | K60: 8665.15
A61: Total | B61: 10559.03 | C61: 12405.19 | D61: 13763.48 | E61: 16248.84 | F61: 16137.97 | G61: 20355.34 | H61: 22958.43 | I61: 25779.33 | J61: 29900.77 | K61: 30355.25
A62: Net Block | B62: 3416.35 | C62: 3303.74 | D62: 3732.24 | E62: 6496.56 | F62: 6272.31 | G62: 5858.52 | H62: 5519.06 | I62: 5770.46 | J62: 7146.62 | K62: 9220.1
A63: Capital Work in Progress | B63: 106.59 | C63: 257.54 | D63: 1405.11 | E63: 209.67 | F63: 140.24 | G63: 182.98 | H63: 426.43 | I63: 1019.59 | J63: 2698.37 | K63: 1254.49
A64: Investments | B64: 2712.13 | C64: 2651.99 | D64: 2140.7 | E64: 2568.58 | F64: 2018.85 | G64: 4736.8 | H64: 3247.53 | I64: 4261.71 | J64: 4587.92 | K64: 4724.75
A65: Other Assets | B65: 4323.96 | C65: 6191.92 | D65: 6485.43 | E65: 6974.03 | F65: 7706.57 | G65: 9577.04 | H65: 13765.41 | I65: 14727.57 | J65: 15467.86 | K65: 15155.91
A66: Total | B66: 10559.03 | C66: 12405.19 | D66: 13763.48 | E66: 16248.84 | F66: 16137.97 | G66: 20355.34 | H66: 22958.43 | I66: 25779.33 | J66: 29900.77 | K66: 30355.25
A67: Receivables | B67: 1186.84 | C67: 1446.6 | D67: 1730.63 | E67: 1907.33 | F67: 1795.22 | G67: 2602.17 | H67: 3871.44 | I67: 4636.94 | J67: 4889.05 | K67: 4313.65
... A70: No. of Equity Shares | B70: 959197790 | C70: 959197790 | D70: 959197790 | E70: 959197790 | F70: 959197790 | G70: 959197790 | H70: 959197790 | I70: 959197790 | J70: 959197790 | K70: 959197790
A71: New Bonus Shares
A72: Face value | B72: 1 | C72: 1 | D72: 1 | E72: 1 | F72: 1 | G72: 1 | H72: 1 | I72: 1 | J72: 1 | K72: 1
A80: CASH FLOW:
A81: Report Date | B81: 42460 | C81: 42825 | D81: 43190 | E81: 43555 | F81: 43921 | G81: 44286 | H81: 44651 | I81: 45016 | J81: 45382 | K81: 45747
A82: Cash from Operating Activity | B82: 2242.95 | C82: 1527.33 | D82: 2113.44 | E82: 2469.54 | F82: 3038.15 | G82: 3683.35 | H82: 986.49 | I82: 4193.43 | J82: 6103.6 | K82: 4423.96
A83: Cash from Investing Activity | B83: -866.21 | C83: -681.11 | D83: -1556.14 | E83: -917.79 | F83: -517.91 | G83: -540.54 | H83: -316.75 | I83: -1282.34 | J83: -2548.48 | K83: -940.91
A84: Cash from Financing Activity | B84: -848.98 | C84: -756.43 | D84: -1379.14 | E84: -1117.46 | F84: -2871.46 | G84: -650.4 | H84: -1807.61 | I84: -2140.05 | J84: -2982.5 | K84: -3752.58
A85: Net Cash Flow | B85: 527.76 | C85: 89.79 | D85: -821.84 | E85: 434.29 | F85: -351.22 | G85: 2492.41 | H85: -1137.87 | I85: 771.04 | J85: 572.62 | K85: -269.53
A90: PRICE: | B90: 868.4 | C90: 1073.5 | D90: 1120.4 | E90: 1492.7 | F90: 1666.5 | G90: 2537.4 | H90: 3079.95 | I90: 2761.65 | J90: 2846.75 | K90: 2340.65
A92: DERIVED:
A93: Adjusted Equity Shares in Cr | B93: 95.92 | C93: 95.92 | D93: 95.92 | E93: 95.92 | F93: 95.92 | G93: 95.92 | H93: 95.92 | I93: 95.92 | J93: 95.92 | K93: 95.92

Sheet Cash Flow
A1: ='Balance Sheet'!A1 -> ASIAN PAINTS LTD | E1: =UPDATE
A3: Narration | B3: ='Data Sheet'!B81 -> 42460 | C3: ='Data Sheet'!C81 -> 42825 | D3: ='Data Sheet'!D81 -> 43190 | E3: ='Data Sheet'!E81 -> 43555 | F3: ='Data Sheet'!F81 -> 43921 | G3: ='Data Sheet'!G81 -> 44286 | H3: ='Data Sheet'!H81 -> 44651 | I3: ='Data Sheet'!I81 -> 45016 | ... K3: ='Data Sheet'!K81 -> 45747
A4: Cash from Operating Activity | B4: ='Data Sheet'!B82 -> 2242.95 | C4: ='Data Sheet'!C82 -> 1527.33 | D4: ='Data Sheet'!D82 -> 2113.44 | E4: ='Data Sheet'!E82 -> 2469.54 | F4: ='Data Sheet'!F82 -> 3038.15 | G4: ='Data Sheet'!G82 -> 3683.35 | H4: ='Data Sheet'!H82 -> 986.49 | I4: ='Data Sheet'!I82 -> 4193.43 | ... K4: ='Data Sheet'!K82 -> 4423.96
A5: Cash from Investing Activity | B5: ='Data Sheet'!B83 -> -866.21 | C5: ='Data Sheet'!C83 -> -681.11 | D5: ='Data Sheet'!D83 -> -1556.14 | E5: ='Data Sheet'!E83 -> -917.79 | F5: ='Data Sheet'!F83 -> -517.91 | G5: ='Data Sheet'!G83 -> -540.54 | H5: ='Data Sheet'!H83 -> -316.75 | I5: ='Data Sheet'!I83 -> -1282.34 | ... K5: ='Data Sheet'!K83 -> -940.91
A6: Cash from Financing Activity | B6: ='Data Sheet'!B84 -> -848.98 | C6: ='Data Sheet'!C84 -> -756.43 | D6: ='Data Sheet'!D84 -> -1379.14 | E6: ='Data Sheet'!E84 -> -1117.46 | F6: ='Data Sheet'!F84 -> -2871.46 | G6: ='Data Sheet'!G84 -> -650.4 | H6: ='Data Sheet'!H84 -> -1807.61 | I6: ='Data Sheet'!I84 -> -2140.05 | ... K6: ='Data Sheet'!K84 -> -3752.58
A7: Net Cash Flow | B7: ='Data Sheet'!B85 -> 527.76 | C7: ='Data Sheet'!C85 -> 89.79 | D7: ='Data Sheet'!D85 -> -821.84 | E7: ='Data Sheet'!E85 -> 434.29 | F7: ='Data Sheet'!F85 -> -351.22 | G7: ='Data Sheet'!G85 -> 2492.41 | H7: ='Data Sheet'!H85 -> -1137.87 | I7: ='Data Sheet'!I85 -> 771.04 | ... K7: ='Data Sheet'!K85 -> -269.53
B10: 41699 | C10: 42064 | D10: 42430 | E10: 42795 | F10: 43160 | G10: 43525 | H10: 43891 | I10: 44256 | J10: 44621 | K10: 44986 | L10: 45352 | M10: 45717
A11: Cash from Operating Activity - | B11: 1402 | C11: 1188 | D11: 2243 | E11: 1527 | F11: 2113 | G11: 2470 | H11: 3038 | I11: 3683 | J11: 986 | K11: 4193 | L11: 6104 | M11: 4424
A12: Profit from operations | B12: 2051 | C12: 2271 | D12: 2848 | E12: 3056 | F12: 3274 | G12: 3861 | H12: 4380 | I12: 4970 | J12: 4957 | K12: 6460 | L12: 7929 | M12: 6390
A13: Receivables | B13: -254 | C13: -155 | D13: -146 | E13: -475 | F13: -483 | G13: -205 | H13: 160 | I13: -849 | J13: -1326 | K13: -834 | L13: -362 | M13: 282
A14: Inventory | B14: -231 | C14: -144 | D14: 202 | E14: -629 | F14: -39 | G14: -492 | H14: -251 | I14: -409 | J14: -2354 | K14: -56 | L14: 315 | M14: -805
A15: Payables | B15: 317 | C15: -151 | D15: 142 | E15: 501 | F15: 442 | G15: 287 | H15: -241 | I15: 1143 | J15: 644 | K15: -539 | L15: 269 | M15: -160
A16: Other WC items | B16: 0 | C16: 0 | D16: 0 | E16: 0 | F16: 0 | G16: 0 | H16: 0 | I16: -92 | J16: 242 | K16: 657 | L16: -212 | M16: 114
A17: Working capital changes | B17: -168 | C17: -450 | D17: 198 | E17: -603 | F17: -80 | G17: -410 | H17: -331 | I17: -206 | J17: -2795 | K17: -772 | L17: 10 | M17: -570
A18: Direct taxes | B18: -480 | C18: -633 | D18: -802 | E18: -925 | F18: -1081 | G18: -982 | H18: -1011 | I18: -1080 | J18: -1176 | K18: -1494 | L18: -1835 | M18: -1396
A19: Cash from Investing Activity - | B19: -586 | C19: -465 | D19: -866 | E19: -681 | F19: -1556 | G19: -918 | H19: -518 | I19: -541 | J19: -317 | K19: -1282 | L19: -2548 | M19: -941
A20: Fixed assets purchased | B20: -251 | C20: -454 | D20: -817 | E20: -684 | F20: -1426 | G20: -1151 | H20: -404 | I20: -282 | J20: -551 | K20: -1446 | L20: -2496 | M20: -1830
A21: Fixed assets sold | B21: 16 | C21: 16 | D21: 15 | E21: 17 | F21: 17 | G21: 17 | H21: 37 | I21: 28 | J21: 40 | K21: 26 | L21: 5 | M21: 10
A22: Investments purchased | B22: -872 | C22: -243 | D22: -282 | E22: -153 | F22: -320 | G22: -573 | H22: -25 | I22: -140 | J22: 0 | K22: -146 | L22: -212 | M22: -1
... A38: Net Cash Flow | B38: 190 | C38: 147 | D38: 528 | E38: 90 | F38: -822 | G38: 434 | H38: -351 | I38: 2492 | J38: -1138 | K38: 771 | L38: 573 | M38: -270

Sheet Balance Sheet
A1: ='Profit & Loss'!A1 -> ASIAN PAINTS LTD | E1: =UPDATE | J1: SCREENER.IN
A3: Narration | B3: ='Data Sheet'!B56 -> 42460 | C3: ='Data Sheet'!C56 -> 42825 | D3: ='Data Sheet'!D56 -> 43190 | E3: ='Data Sheet'!E56 -> 43555 | F3: ='Data Sheet'!F56 -> 43921 | G3: ='Data Sheet'!G56 -> 44286 | H3: ='Data Sheet'!H56 -> 44651 | I3: ='Data Sheet'!I56 -> 45016 | ... K3: ='Data Sheet'!K56 -> 45747
A4: Equity Share Capital | B4: ='Data Sheet'!B57 -> 95.92 | C4: ='Data Sheet'!C57 -> 95.92 | D4: ='Data Sheet'!D57 -> 95.92 | E4: ='Data Sheet'!E57 -> 95.92 | F4: ='Data Sheet'!F57 -> 95.92 | G4: ='Data Sheet'!G57 -> 95.92 | H4: ='Data Sheet'!H57 -> 95.92 | I4: ='Data Sheet'!I57 -> 95.92 | ... K4: ='Data Sheet'!K57 -> 95.92
A5: Reserves | B5: ='Data Sheet'!B58 -> 6428.9 | C5: ='Data Sheet'!C58 -> 7507.97 | D5: ='Data Sheet'!D58 -> 8314.31 | E5: ='Data Sheet'!E58 -> 9374.63 | F5: ='Data Sheet'!F58 -> 10034.24 | G5: ='Data Sheet'!G58 -> 12710.37 | H5: ='Data Sheet'!H58 -> 13715.64 | I5: ='Data Sheet'!I58 -> 15896.31 | ... K5: ='Data Sheet'!K58 -> 19303.89
A6: Borrowings | B6: ='Data Sheet'!B59 -> 323.29 | C6: ='Data Sheet'!C59 -> 560.34 | D6: ='Data Sheet'!D59 -> 533.43 | E6: ='Data Sheet'!E59 -> 1319.6 | F6: ='Data Sheet'!F59 -> 1118.5 | G6: ='Data Sheet'!G59 -> 1093.12 | H6: ='Data Sheet'!H59 -> 1586.88 | I6: ='Data Sheet'!I59 -> 1932.62 | ... K6: ='Data Sheet'!K59 -> 2290.29
A7: Other Liabilities | B7: ='Data Sheet'!B60 -> 3710.92 | C7: ='Data Sheet'!C60 -> 4240.96 | D7: ='Data Sheet'!D60 -> 4819.82 | E7: ='Data Sheet'!E60 -> 5458.69 | F7: ='Data Sheet'!F60 -> 4889.31 | G7: ='Data Sheet'!G60 -> 6455.93 | H7: ='Data Sheet'!H60 -> 7559.99 | I7: ='Data Sheet'!I60 -> 7854.48 | ... K7: ='Data Sheet'!K60 -> 8665.15
A8: Total | B8: ='Data Sheet'!B61 -> 10559.03 | C8: ='Data Sheet'!C61 -> 12405.19 | D8: ='Data Sheet'!D61 -> 13763.48 | E8: ='Data Sheet'!E61 -> 16248.84 | F8: ='Data Sheet'!F61 -> 16137.97 | G8: ='Data Sheet'!G61 -> 20355.34 | H8: ='Data Sheet'!H61 -> 22958.43 | I8: ='Data Sheet'!I61 -> 25779.33 | ... K8: ='Data Sheet'!K61 -> 30355.25
A10: Net Block | B10: ='Data Sheet'!B62 -> 3416.35 | C10: ='Data Sheet'!C62 -> 3303.74 | D10: ='Data Sheet'!D62 -> 3732.24 | E10: ='Data Sheet'!E62 -> 6496.56 | F10: ='Data Sheet'!F62 -> 6272.31 | G10: ='Data Sheet'!G62 -> 5858.52 | H10: ='Data Sheet'!H62 -> 5519.06 | I10: ='Data Sheet'!I62 -> 5770.46 | ... K10: ='Data Sheet'!K62 -> 9220.1
A11: Capital Work in Progress | B11: ='Data Sheet'!B63 -> 106.59 | C11: ='Data Sheet'!C63 -> 257.54 | D11: ='Data Sheet'!D63 -> 1405.11 | E11: ='Data Sheet'!E63 -> 209.67 | F11: ='Data Sheet'!F63 -> 140.24 | G11: ='Data Sheet'!G63 -> 182.98 | H11: ='Data Sheet'!H63 -> 426.43 | I11: ='Data Sheet'!I63 -> 1019.59 | ... K11: ='Data Sheet'!K63 -> 1254.49
A12: Investments | B12: ='Data Sheet'!B64 -> 2712.13 | C12: ='Data Sheet'!C64 -> 2651.99 | D12: ='Data Sheet'!D64 -> 2140.7 | E12: ='Data Sheet'!E64 -> 2568.58 | F12: ='Data Sheet'!F64 -> 2018.85 | G12: ='Data Sheet'!G64 -> 4736.8 | H12: ='Data Sheet'!H64 -> 3247.53 | I12: ='Data Sheet'!I64 -> 4261.71 | ... K12: ='Data Sheet'!K64 -> 4724.75
A13: Other Assets | B13: ='Data Sheet'!B65 -> 4323.96 | C13: ='Data Sheet'!C65 -> 6191.92 | D13: ='Data Sheet'!D65 -> 6485.43 | E13: ='Data Sheet'!E65 -> 6974.03 | F13: ='Data Sheet'!F65 -> 7706.57 | G13: ='Data Sheet'!G65 -> 9577.04 | H13: ='Data Sheet'!H65 -> 13765.41 | I13: ='Data Sheet'!I65 -> 14727.57 | ... K13: ='Data Sheet'!K65 -> 15155.91
A14: Total | B14: ='Data Sheet'!B66 -> 10559.03 | C14: ='Data Sheet'!C66 -> 12405.19 | D14: ='Data Sheet'!D66 -> 13763.48 | E14: ='Data Sheet'!E66 -> 16248.84 | F14: ='Data Sheet'!F66 -> 16137.97 | G14: ='Data Sheet'!G66 -> 20355.34 | H14: ='Data Sheet'!H66 -> 22958.43 | I14: ='Data Sheet'!I66 -> 25779.33 | ... K14: ='Data Sheet'!K66 -> 30355.25
A16: Working Capital | B16: =B13-B7 -> 613.04 | C16: =C13-C7 -> 1950.96 | D16: =D13-D7 -> 1665.61 | E16: =E13-E7 -> 1515.34 | F16: =F13-F7 -> 2817.26 | G16: =G13-G7 -> 3121.11 | H16: =H13-H7 -> 6205.42 | I16: =I13-I7 -> 6873.09 | ... K16: =K13-K7 -> 6490.76
A17: Debtors | B17: ='Data Sheet'!B67 -> 1186.84 | C17: ='Data Sheet'!C67 -> 1446.6 | D17: ='Data Sheet'!D67 -> 1730.63 | E17: ='Data Sheet'!E67 -> 1907.33 | F17: ='Data Sheet'!F67 -> 1795.22 | G17: ='Data Sheet'!G67 -> 2602.17 | H17: ='Data Sheet'!H67 -> 3871.44 | I17: ='Data Sheet'!I67 -> 4636.94 | ... K17: ='Data Sheet'!K67 -> 4313.65
A18: Inventory | B18: ='Data Sheet'!B68 -> 1998.24 | C18: ='Data Sheet'!C68 -> 2626.94 | D18: ='Data Sheet'!D68 -> 2658.31 | E18: ='Data Sheet'!E68 -> 3149.86 | F18: ='Data Sheet'!F68 -> 3389.81 | G18: ='Data Sheet'!G68 -> 3798.6 | H18: ='Data Sheet'!H68 -> 6152.98 | I18: ='Data Sheet'!I68 -> 6210.64 | ... K18: ='Data Sheet'!K68 -> 6719.27
A20: Debtor Days | B20: =IF('Profit & Loss'!B4>0,'Balance Sheet'!B17/('Profit & Loss'!B4/365),0) -> 30.353985 | C20: =IF('Profit & Loss'!C4>0,'Balance Sheet'!C17/('Profit & Loss'!C4/365),0) -> 35.055726 | D20: =IF('Profit & Loss'!D4>0,'Balance Sheet'!D17/('Profit & Loss'!D4/365),0) -> 37.545132 | E20: =IF('Profit & Loss'!E4>0,'Balance Sheet'!E17/('Profit & Loss'!E4/365),0) -> 36.183511 | F20: =IF('Profit & Loss'!F4>0,'Balance Sheet'!F17/('Profit & Loss'!F4/365),0) -> 32.420325 | G20: =IF('Profit & Loss'!G4>0,'Balance Sheet'!G17/('Profit & Loss'!G4/365),0) -> 43.743436 | H20: =IF('Profit & Loss'!H4>0,'Balance Sheet'!H17/('Profit & Loss'!H4/365),0) -> 48.557163 | I20: =IF('Profit & Loss'!I4>0,'Balance Sheet'!I17/('Profit & Loss'!I4/365),0) -> 49.073711 | ... K20: =IF('Profit & Loss'!K4>0,'Balance Sheet'!K17/('Profit & Loss'!K4/365),0) -> 46.437206
A21: Inventory Turnover | B21: =IF('Balance Sheet'!B18>0,'Profit & Loss'!B4/'Balance Sheet'!B18,0) -> 7.14203 | C21: =IF('Balance Sheet'!C18>0,'Profit & Loss'!C4/'Balance Sheet'!C18,0) -> 5.7336635 | D21: =IF('Balance Sheet'!D18>0,'Profit & Loss'!D4/'Balance Sheet'!D18,0) -> 6.3290399 | E21: =IF('Balance Sheet'!E18>0,'Profit & Loss'!E4/'Balance Sheet'!E18,0) -> 6.1082493 | F21: =IF('Balance Sheet'!F18>0,'Profit & Loss'!F4/'Balance Sheet'!F18,0) -> 5.9623548 | G21: =IF('Balance Sheet'!G18>0,'Profit & Loss'!G4/'Balance Sheet'!G18,0) -> 5.715998 | H21: =IF('Balance Sheet'!H18>0,'Profit & Loss'!H4/'Balance Sheet'!H18,0) -> 4.7296237 | I21: =IF('Balance Sheet'!I18>0,'Profit & Loss'!I4/'Balance Sheet'!I18,0) -> 5.5531459 | ... K21: =IF('Balance Sheet'!K18>0,'Profit & Loss'!K4/'Balance Sheet'!K18,0) -> 5.0460273
A23: Return on Equity | B23: =IF(SUM('Balance Sheet'!B4:B5)>0,'Profit & Loss'!B12/SUM('Balance Sheet'!B4:B5),"") -> 0.26746485 | C23: =IF(SUM('Balance Sheet'!C4:C5)>0,'Profit & Loss'!C12/SUM('Balance Sheet'!C4:C5),"") -> 0.25505761 | D23: =IF(SUM('Balance Sheet'!D4:D5)>0,'Profit & Loss'!D12/SUM('Balance Sheet'!D4:D5),"") -> 0.24243451 | E23: =IF(SUM('Balance Sheet'!E4:E5)>0,'Profit & Loss'!E12/SUM('Balance Sheet'!E4:E5),"") -> 0.22764465 | F23: =IF(SUM('Balance Sheet'!F4:F5)>0,'Profit & Loss'!F12/SUM('Balance Sheet'!F4:F5),"") -> 0.26704119 | G23: =IF(SUM('Balance Sheet'!G4:G5)>0,'Profit & Loss'!G12/SUM('Balance Sheet'!G4:G5),"") -> 0.24513657 | H23: =IF(SUM('Balance Sheet'!H4:H5)>0,'Profit & Loss'!H12/SUM('Balance Sheet'!H4:H5),"") -> 0.21942272 | I23: =IF(SUM('Balance Sheet'!I4:I5)>0,'Profit & Loss'!I12/SUM('Balance Sheet'!I4:I5),"") -> 0.25677782 | ... K23: =IF(SUM('Balance Sheet'!K4:K5)>0,'Profit & Loss'!K12/SUM('Balance Sheet'!K4:K5),"") -> 0.18903433
A24: Return on Capital Emp | C24: =IF((B4+B5+B6+C4+C5+C6)>0,('Profit & Loss'!C10+'Profit & Loss'!C9)*2/(B4+B5+B6+C4+C5+C6),"") -> 0.39925421 | D24: =IF((C4+C5+C6+D4+D5+D6)>0,('Profit & Loss'!D10+'Profit & Loss'!D9)*2/(C4+C5+C6+D4+D5+D6),"") -> 0.37175245 | E24: =IF((D4+D5+D6+E4+E5+E6)>0,('Profit & Loss'!E10+'Profit & Loss'!E9)*2/(D4+D5+D6+E4+E5+E6),"") -> 0.34626562 | F24: =IF((E4+E5+E6+F4+F5+F6)>0,('Profit & Loss'!F10+'Profit & Loss'!F9)*2/(E4+E5+E6+F4+F5+F6),"") -> 0.3386181 | G24: =IF((F4+F5+F6+G4+G5+G6)>0,('Profit & Loss'!G10+'Profit & Loss'!G9)*2/(F4+F5+F6+G4+G5+G6),"") -> 0.34960774 | H24: =IF((G4+G5+G6+H4+H5+H6)>0,('Profit & Loss'!H10+'Profit & Loss'!H9)*2/(G4+G5+G6+H4+H5+H6),"") -> 0.29238528 | I24: =IF((H4+H5+H6+I4+I5+I6)>0,('Profit & Loss'!I10+'Profit & Loss'!I9)*2/(H4+H5+H6+I4+I5+I6),"") -> 0.35010229 | J24: =IF((I4+I5+I6+J4+J5+J6)>0,('Profit & Loss'!J10+'Profit & Loss'!J9)*2/(I4+I5+I6+J4+J5+J6),"") -> 0.38606781 | K24: =IF((J4+J5+J6+K4+K5+K6)>0,('Profit & Loss'!K10+'Profit & Loss'!K9)*2/(J4+J5+J6+K4+K5+K6),"") -> 0.24853087

Sheet Quarters
A1: ='Profit & Loss'!A1 -> ASIAN PAINTS LTD | E1: =UPDATE | J1: SCREENER.IN
A3: Narration | B3: ='Data Sheet'!B41 -> 45016 | C3: ='Data Sheet'!C41 -> 45107 | D3: ='Data Sheet'!D41 -> 45199 | E3: ='Data Sheet'!E41 -> 45291 | F3: ='Data Sheet'!F41 -> 45382 | G3: ='Data Sheet'!G41 -> 45473 | H3: ='Data Sheet'!H41 -> 45565 | I3: ='Data Sheet'!I41 -> 45657 | ... K3: ='Data Sheet'!K41 -> 45838
A4: Sales | B4: ='Data Sheet'!B42 -> 8787.34 | C4: ='Data Sheet'!C42 -> 9182.31 | D4: ='Data Sheet'!D42 -> 8478.57 | E4: ='Data Sheet'!E42 -> 9103.09 | F4: ='Data Sheet'!F42 -> 8730.76 | G4: ='Data Sheet'!G42 -> 8969.73 | H4: ='Data Sheet'!H42 -> 8027.54 | I4: ='Data Sheet'!I42 -> 8549.44 | ... K4: ='Data Sheet'!K42 -> 8938.55
A5: Expenses | B5: ='Data Sheet'!B43 -> 6922.58 | C5: ='Data Sheet'!C43 -> 7061.02 | D5: ='Data Sheet'!D43 -> 6762.34 | E5: ='Data Sheet'!E43 -> 7047 | F5: ='Data Sheet'!F43 -> 7039.39 | G5: ='Data Sheet'!G43 -> 7275.96 | H5: ='Data Sheet'!H43 -> 6788.03 | I5: ='Data Sheet'!I43 -> 6912.71 | ... K5: ='Data Sheet'!K43 -> 7313.58
A6: Operating Profit | B6: ='Data Sheet'!B50 -> 1864.76 | C6: ='Data Sheet'!C50 -> 2121.29 | D6: ='Data Sheet'!D50 -> 1716.23 | E6: ='Data Sheet'!E50 -> 2056.09 | F6: ='Data Sheet'!F50 -> 1691.37 | G6: ='Data Sheet'!G50 -> 1693.77 | H6: ='Data Sheet'!H50 -> 1239.51 | I6: ='Data Sheet'!I50 -> 1636.73 | ... K6: ='Data Sheet'!K50 -> 1624.97
A7: Other Income | B7: ='Data Sheet'!B44 -> 104.17 | C7: ='Data Sheet'!C44 -> 227.74 | D7: ='Data Sheet'!D44 -> 194.33 | E7: ='Data Sheet'!E44 -> 186.46 | F7: ='Data Sheet'!F44 -> 212.43 | G7: ='Data Sheet'!G44 -> 192.93 | H7: ='Data Sheet'!H44 -> 24.53 | I7: ='Data Sheet'!I44 -> 192.82 | ... K7: ='Data Sheet'!K44 -> 229.11
A8: Depreciation | B8: ='Data Sheet'!B45 -> 220.17 | C8: ='Data Sheet'!C45 -> 198.32 | D8: ='Data Sheet'!D45 -> 208.72 | E8: ='Data Sheet'!E45 -> 220.35 | F8: ='Data Sheet'!F45 -> 225.61 | G8: ='Data Sheet'!G45 -> 227.7 | H8: ='Data Sheet'!H45 -> 241.99 | I8: ='Data Sheet'!I45 -> 255.55 | ... K8: ='Data Sheet'!K45 -> 300.87
A9: Interest | B9: ='Data Sheet'!B46 -> 38.91 | C9: ='Data Sheet'!C46 -> 45.75 | D9: ='Data Sheet'!D46 -> 50.9 | E9: ='Data Sheet'!E46 -> 54.42 | F9: ='Data Sheet'!F46 -> 54.1 | G9: ='Data Sheet'!G46 -> 55.38 | H9: ='Data Sheet'!H46 -> 63.01 | I9: ='Data Sheet'!I46 -> 55.84 | ... K9: ='Data Sheet'!K46 -> 44.5
A10: Profit before tax | B10: ='Data Sheet'!B47 -> 1709.85 | C10: ='Data Sheet'!C47 -> 2104.96 | D10: ='Data Sheet'!D47 -> 1650.94 | E10: ='Data Sheet'!E47 -> 1967.78 | F10: ='Data Sheet'!F47 -> 1624.09 | G10: ='Data Sheet'!G47 -> 1603.62 | H10: ='Data Sheet'!H47 -> 959.04 | I10: ='Data Sheet'!I47 -> 1518.16 | ... K10: ='Data Sheet'!K47 -> 1508.71
A11: Tax | B11: ='Data Sheet'!B48 -> 451.44 | C11: ='Data Sheet'!C48 -> 530.12 | D11: ='Data Sheet'!D48 -> 418.55 | E11: ='Data Sheet'!E48 -> 492.62 | F11: ='Data Sheet'!F48 -> 348.79 | G11: ='Data Sheet'!G48 -> 416.83 | H11: ='Data Sheet'!H48 -> 265.38 | I11: ='Data Sheet'!I48 -> 389.73 | ... K11: ='Data Sheet'!K48 -> 391.66
A12: Net profit | B12: ='Data Sheet'!B49 -> 1234.14 | C12: ='Data Sheet'!C49 -> 1550.37 | D12: ='Data Sheet'!D49 -> 1205.42 | E12: ='Data Sheet'!E49 -> 1447.72 | F12: ='Data Sheet'!F49 -> 1256.72 | G12: ='Data Sheet'!G49 -> 1169.98 | H12: ='Data Sheet'!H49 -> 694.64 | I12: ='Data Sheet'!I49 -> 1110.48 | ... K12: ='Data Sheet'!K49 -> 1099.77
A14: OPM | B14: =IF(B4>0,B6/B4,"") -> 0.21220984 | C14: =IF(C4>0,C6/C4,"") -> 0.23101921 | D14: =IF(D4>0,D6/D4,"") -> 0.20241975 | E14: =IF(E4>0,E6/E4,"") -> 0.22586726 | F14: =IF(F4>0,F6/F4,"") -> 0.1937254 | G14: =IF(G4>0,G6/G4,"") -> 0.18883177 | H14: =IF(H4>0,H6/H4,"") -> 0.1544072 | I14: =IF(I4>0,I6/I4,"") -> 0.19144295 | ... K14: =IF(K4>0,K6/K4,"") -> 0.18179347
